Workbook

Sheet Instrucciones
B2: Instrucciones de uso
B4: - Los datos "clave" que debes modificar manualmente para la valoración están marcados con números en NARANJA (Hojas 1, 2 y 4). También puedes modificar las celdas con fondo AZUL FLOJO, si así lo crees necesario.
B6: - Debes introducir todas las partidas con el MISMO SIGNO QUE EN TIKR (Número negativo = SALIDA DE CAJA. Número positivo = ENTRADA DE CAJA)
B8: - Opcional: Para que la plantilla obtenga los datos desde TIKR debes copiar cada uno de los estados financieros y pegarlos en la celda A1 de las hojas 7 (IS), 8 (BS) y 9 (CF)
B10: - OJO: Solo es válido para TIKR en INGLÉS, y es recomendable pegar los datos con "formato de destino"
B12: - Si no te aparece el botón "Copy table", debes seleccionar a mano los datos. Te sitúas con el cursor en la esquina izquierda superior de la tabla de TIKR y desde la franja negra "Income Statement | TIKR.com", arrastras hacia abajo para seleccionar todos los datos de la tabla. Después copias y pegas en la plantilla, como siempre.
B14: - Si no captura bien los datos, revisa que el separador decimal de tu aplicación de hoja de cálculo coincida con TIKR. También puedes probar a ocultar los decimales en TIKR ("Decimals to display" => 0) y pegar de nuevo los datos
B16: Novedades plantilla v2024.3 (9ª edición curso avanzado)
B18: - Hoja 1.IS: Las estimaciones pasan a ser anuales, de manera independiente (Crecimiento ventas, Margen EBIT, Tax Rate y Recompras); Se ha añadido el campo YoY Growth % al EBITDA, EBIT y Net Income
B20: - Hoja 2.FCF: Se ha desglosado la partida "Unearned Revenue" en el WC. Anteriormente, se sumaba a la partida Payables. Esto es meramente informativo, el resultado del WC y de las Variaciones de WC NO cambian
B22: - Hoja 3.ROIC: Hemos incluido en la deuda las partidas correspondientes a la división financiera de las compañías. Ejemplos: Deere & Co, fabricantes de automóviles... ("Finance division debt"). Se ha mejorado la estimación del mix de cash + deuda
B24: - Hoja 4.Valoración: Hemos añadido un campo para calcular el precio de compra según la rentabilidad anual objetivo

Sheet 1.IS
B1: Income Statement | O1: #VALUE!
A2: (millones, excepto EPS) | B2: 2016 | C2: =IFERROR(IF(VLOOKUP("Income Statement*",'7.TIKR_IS'!$A:$K,COLUMN(C3),FALSE)="","",IFERROR(YEAR(VLOOKUP("Income Statement*",'7.TIKR_IS'!$A:$K,COLUMN(C3),FALSE)),B2+1)),"") -> 2017 | D2: =IFERROR(IF(VLOOKUP("Income Statement*",'7.TIKR_IS'!$A:$K,COLUMN(D3),FALSE)="","",IFERROR(YEAR(VLOOKUP("Income Statement*",'7.TIKR_IS'!$A:$K,COLUMN(D3),FALSE)),C2+1)),"") -> 2018 | E2: =IFERROR(IF(VLOOKUP("Income Statement*",'7.TIKR_IS'!$A:$K,COLUMN(E3),FALSE)="","",IFERROR(YEAR(VLOOKUP("Income Statement*",'7.TIKR_IS'!$A:$K,COLUMN(E3),FALSE)),D2+1)),"") -> 2019 | F2: =IFERROR(IF(VLOOKUP("Income Statement*",'7.TIKR_IS'!$A:$K,COLUMN(F3),FALSE)="","",IFERROR(YEAR(VLOOKUP("Income Statement*",'7.TIKR_IS'!$A:$K,COLUMN(F3),FALSE)),E2+1)),"") -> 2020 | G2: =IFERROR(IF(VLOOKUP("Income Statement*",'7.TIKR_IS'!$A:$K,COLUMN(G3),FALSE)="","",IFERROR(YEAR(VLOOKUP("Income Statement*",'7.TIKR_IS'!$A:$K,COLUMN(G3),FALSE)),F2+1)),"") -> 2021 | H2: =IFERROR(IF(VLOOKUP("Income Statement*",'7.TIKR_IS'!$A:$K,COLUMN(H3),FALSE)="","",IFERROR(YEAR(VLOOKUP("Income Statement*",'7.TIKR_IS'!$A:$K,COLUMN(H3),FALSE)),G2+1)),"") -> 2022 | I2: =IFERROR(IF(VLOOKUP("Income Statement*",'7.TIKR_IS'!$A:$K,COLUMN(I3),FALSE)="","",IFERROR(YEAR(VLOOKUP("Income Statement*",'7.TIKR_IS'!$A:$K,COLUMN(I3),FALSE)),H2+1)),"") -> 2023 | J2: =IFERROR(IF(VLOOKUP("Income Statement*",'7.TIKR_IS'!$A:$K,COLUMN(J3),FALSE)="","",IFERROR(YEAR(VLOOKUP("Income Statement*",'7.TIKR_IS'!$A:$K,COLUMN(J3),FALSE)),I2+1)),"") -> 2024 | K2: =IFERROR(IF(VLOOKUP("Income Statement*",'7.TIKR_IS'!$A:$K,COLUMN(K3),FALSE)="","",IFERROR(YEAR(VLOOKUP("Income Statement*",'7.TIKR_IS'!$A:$K,COLUMN(K3),FALSE)),J2+1)),"") -> 2025 | L2: =IF(K2<>"",(K2+1)&"e","") -> 2026e | M2: =IF(L2<>"",(LEFT(L2,4)+1)&"e","") -> 2027e | N2: =IF(M2<>"",(LEFT(M2,4)+1)&"e","") -> 2028e | O2: =IF(N2<>"",(LEFT(N2,4)+1)&"e","") -> 2029e | P2: =IF(O2<>"",(LEFT(O2,4)+1)&"e","") -> 2030e | S2: ="Promedio "&CHAR(10)&B2&" - "&K2 -> Promedio 2016 - 2025
A3: Sales | B3: 118719 | C3: 129025 | D3: 141576 | E3: 152703 | F3: 166761 | G3: 195929 | H3: 226954 | I3: 242290 | J3: 254453 | K3: 275235 | L3: =IFERROR(K3*(1+L4),"") -> 302374.53 | M3: =IFERROR(L3*(1+M4),"") -> 332190.15 | N3: =IFERROR(M3*(1+N4),"") -> 364945.74 | O3: =IFERROR(N3*(1+O4),"") -> 400931.19 | P3: =IFERROR(O3*(1+P4),"") -> 440464.98 | R3: Crecimiento de Ventas | S3: =IFERROR(AVERAGE(C4:K4),"") -> 0.098604933
A4: Y/Y Growth % | C4: =IFERROR((C3-B3)/B3,"") -> 0.08681003 | D4: =IFERROR((D3-C3)/C3,"") -> 0.097275722 | E4: =IFERROR((E3-D3)/D3,"") -> 0.078593829 | F4: =IFERROR((F3-E3)/E3,"") -> 0.09206106 | G4: =IFERROR((G3-F3)/F3,"") -> 0.174909 | H4: =IFERROR((H3-G3)/G3,"") -> 0.15834818 | I4: =IFERROR((I3-H3)/H3,"") -> 0.067573165 | J4: =IFERROR((J3-I3)/I3,"") -> 0.050200173 | K4: =IFERROR((K3-J3)/J3,"") -> 0.081673236 | L4: =S3 -> 0.098604933 | M4: =L4 -> 0.098604933 | N4: =M4 -> 0.098604933 | O4: =N4 -> 0.098604933 | P4: =O4 -> 0.098604933 | R4: Margen EBIT | S4: =IFERROR(AVERAGE(B10:K10),"") -> 0.033688819
A5: EBITDA | B5: =B9-B8 -> 3672 | C5: =C9-C8 -> 4111 | D5: =D9-D8 -> 4480 | E5: =E9-E8 -> 4737 | F5: =F9-F8 -> 5435 | G5: =G9-G8 -> 6792 | H5: =H9-H8 -> 7911 | I5: =I9-I8 -> 8505 | ... K5: =K9-K8 -> 10383 | L5: =IFERROR(L9-L8,"") -> 10186.641 | M5: =IFERROR(M9-M8,"") -> 11191.094 | N5: =IFERROR(N9-N8,"") -> 12294.591 | O5: =IFERROR(O9-O8,"") -> 13506.898 | P5: =IFERROR(P9-P8,"") -> 14838.745 | R5: Tax Rate | S5: =IFERROR(AVERAGE(B17:K17),"") -> 0.26682825
A6: EBITDA margin % | B6: =IFERROR((B5/B3),"") -> 0.03093018 | C6: =IFERROR((C5/C3),"") -> 0.031862042 | D6: =IFERROR((D5/D3),"") -> 0.031643781 | E6: =IFERROR((E5/E3),"") -> 0.031021002 | F6: =IFERROR((F5/F3),"") -> 0.032591553 | G6: =IFERROR((G5/G3),"") -> 0.034665619 | H6: =IFERROR((H5/H3),"") -> 0.034857284 | I6: =IFERROR((I5/I3),"") -> 0.035102563 | ... K6: =IFERROR((K5/K3),"") -> 0.037724127 | L6: =IFERROR(L5/L3,"") -> 0.033688819 | M6: =IFERROR(M5/M3,"") -> 0.033688819 | N6: =IFERROR(N5/N3,"") -> 0.033688819 | O6: =IFERROR(O5/O3,"") -> 0.033688819 | P6: =IFERROR(P5/P3,"") -> 0.033688819 | R6: Aumento nº acciones | S6: =IFERROR(AVERAGE(C26:K26),"") -> 0.00088885342
A7: Y/Y Growth % | C7: =IFERROR((C5-B5)/B5,"") -> 0.11955338 | D7: =IFERROR((D5-C5)/C5,"") -> 0.089759183 | E7: =IFERROR((E5-D5)/D5,"") -> 0.057366071 | F7: =IFERROR((F5-E5)/E5,"") -> 0.14735064 | G7: =IFERROR((G5-F5)/F5,"") -> 0.24967801 | H7: =IFERROR((H5-G5)/G5,"") -> 0.16475265 | I7: =IFERROR((I5-H5)/H5,"") -> 0.075085324 | J7: =IFERROR((J5-I5)/I5,"") -> 0.091710758 | ... P7: =IFERROR((P5-O5)/O5,"") -> 0.098604933
A8: Depreciation & Amortization | B8: 0 | C8: 0 | D8: 0 | E8: 0 | F8: 0 | G8: 0 | H8: 0 | I8: 0 | J8: 0 | K8: 0 | L8: =IFERROR(K8*(1+L4),"") -> 0 | M8: =IFERROR(L8*(1+M4),"") -> 0 | N8: =IFERROR(M8*(1+N4),"") -> 0 | O8: =IFERROR(N8*(1+O4),"") -> 0 | P8: =IFERROR(O8*(1+P4),"") -> 0
A9: EBIT | B9: 3672 | C9: 4111 | D9: 4480 | E9: 4737 | F9: 5435 | G9: 6792 | H9: 7911 | I9: 8505 | J9: 9285 | K9: 10383 | L9: =IFERROR(L3*L10,"") -> 10186.641 | M9: =IFERROR(M3*M10,"") -> 11191.094 | N9: =IFERROR(N3*N10,"") -> 12294.591 | O9: =IFERROR(O3*O10,"") -> 13506.898 | P9: =IFERROR(P3*P10,"") -> 14838.745
A10: EBIT margin % | B10: =IFERROR((B9/B3),"") -> 0.03093018 | C10: =IFERROR((C9/C3),"") -> 0.031862042 | D10: =IFERROR((D9/D3),"") -> 0.031643781 | E10: =IFERROR((E9/E3),"") -> 0.031021002 | F10: =IFERROR((F9/F3),"") -> 0.032591553 | G10: =IFERROR((G9/G3),"") -> 0.034665619 | H10: =IFERROR((H9/H3),"") -> 0.034857284 | I10: =IFERROR((I9/I3),"") -> 0.035102563 | ... K10: =IFERROR((K9/K3),"") -> 0.037724127 | L10: =S4 -> 0.033688819 | M10: =L10 -> 0.033688819 | N10: =M10 -> 0.033688819 | O10: =N10 -> 0.033688819 | P10: =O10 -> 0.033688819
A11: Y/Y Growth % | C11: =IFERROR((C9-B9)/B9,"") -> 0.11955338 | D11: =IFERROR((D9-C9)/C9,"") -> 0.089759183 | E11: =IFERROR((E9-D9)/D9,"") -> 0.057366071 | F11: =IFERROR((F9-E9)/E9,"") -> 0.14735064 | G11: =IFERROR((G9-F9)/F9,"") -> 0.24967801 | H11: =IFERROR((H9-G9)/G9,"") -> 0.16475265 | I11: =IFERROR((I9-H9)/H9,"") -> 0.075085324 | J11: =IFERROR((J9-I9)/I9,"") -> 0.091710758 | ... P11: =IFERROR((P9-O9)/O9,"") -> 0.098604933
A12: Interest Expense | B12: -133 | C12: -134 | D12: -159 | E12: -150 | F12: -160 | G12: -171 | H12: -158 | I12: -160 | J12: -169 | K12: -154 | L12: =IFERROR(-TIKR_Cálculos!$B$27*SUM('3.ROIC'!L6:L7),"") -> -76.732744 | M12: =IFERROR(-TIKR_Cálculos!$B$27*SUM('3.ROIC'!M6:M7),"") -> -84.298971 | N12: =IFERROR(-TIKR_Cálculos!$B$27*SUM('3.ROIC'!N6:N7),"") -> -92.611265 | O12: =IFERROR(-TIKR_Cálculos!$B$27*SUM('3.ROIC'!O6:O7),"") -> -101.74319 | P12: =IFERROR(-TIKR_Cálculos!$B$27*SUM('3.ROIC'!P6:P7),"") -> -111.77557
A13: Interest Income | B13: 41 | C13: 50 | D13: 75 | E13: 126 | F13: 89 | G13: 41 | H13: 61 | I13: 470 | J13: 533 | K13: 469 | L13: =IFERROR(TIKR_Cálculos!$B$26*'3.ROIC'!L5,"") -> 106.00161 | M13: =IFERROR(TIKR_Cálculos!$B$26*'3.ROIC'!M5,"") -> 116.45389 | N13: =IFERROR(TIKR_Cálculos!$B$26*'3.ROIC'!N5,"") -> 127.93681 | O13: =IFERROR(TIKR_Cálculos!$B$26*'3.ROIC'!O5,"") -> 140.55201 | P13: =IFERROR(TIKR_Cálculos!$B$26*'3.ROIC'!P5,"") -> 154.41114 | R13: AJUSTAR MANUALMENTE
A14: Total Interest expense | B14: =B12+B13 -> -92 | C14: =C12+C13 -> -84 | D14: =D12+D13 -> -84 | E14: =E12+E13 -> -24 | F14: =F12+F13 -> -71 | G14: =G12+G13 -> -130 | H14: =H12+H13 -> -97 | I14: =I12+I13 -> 310 | ... K14: =K12+K13 -> 315 | L14: =IFERROR(SUM(L12:L13),"") -> 29.268861 | M14: =IFERROR(SUM(M12:M13),"") -> 32.154915 | N14: =IFERROR(SUM(N12:N13),"") -> 35.325548 | O14: =IFERROR(SUM(O12:O13),"") -> 38.808822 | P14: =IFERROR(SUM(P12:P13),"") -> 42.635563
A15: EBT | B15: =IFERROR(B9+B14,"") -> 3580 | C15: =IFERROR(C9+C14,"") -> 4027 | D15: =IFERROR(D9+D14,"") -> 4396 | E15: =IFERROR(E9+E14,"") -> 4713 | F15: =IFERROR(F9+F14,"") -> 5364 | G15: =IFERROR(G9+G14,"") -> 6662 | H15: =IFERROR(H9+H14,"") -> 7814 | I15: =IFERROR(I9+I14,"") -> 8815 | ... P15: =IFERROR(P9+P14,"") -> 14881.38
A16: Tax Expense - en negativo | B16: -1243 | C16: -1325 | D16: -1263 | E16: -1061 | F16: -1308 | G16: -1601 | H16: -1925 | I16: -2195 | J16: -2373 | K16: -2719 | L16: =IFERROR(-L15*L17,"") -> -2725.8932 | M16: =IFERROR(-M15*M17,"") -> -2994.6798 | N16: =IFERROR(-N15*N17,"") -> -3289.97 | O16: =IFERROR(-O15*O17,"") -> -3614.3772 | P16: =IFERROR(-P15*P17,"") -> -3970.7726
A17: Tax rate % | B17: =IFERROR((ABS(B16)/B15),"") -> 0.3472067 | C17: =IFERROR((ABS(C16)/C15),"") -> 0.32902905 | D17: =IFERROR((ABS(D16)/D15),"") -> 0.28730664 | E17: =IFERROR((ABS(E16)/E15),"") -> 0.225122 | F17: =IFERROR((ABS(F16)/F15),"") -> 0.24384787 | G17: =IFERROR((ABS(G16)/G15),"") -> 0.24031822 | H17: =IFERROR((ABS(H16)/H15),"") -> 0.2463527 | I17: =IFERROR((ABS(I16)/I15),"") -> 0.24900737 | ... K17: =IFERROR((ABS(K16)/K15),"") -> 0.25415966 | L17: =S5 -> 0.26682825 | M17: =L17 -> 0.26682825 | N17: =M17 -> 0.26682825 | O17: =N17 -> 0.26682825 | P17: =O17 -> 0.26682825
A18: Consolidated Net Income | B18: =B15+B16 -> 2337 | C18: =C15+C16 -> 2702 | D18: =D15+D16 -> 3133 | E18: =E15+E16 -> 3652 | F18: =F15+F16 -> 4056 | G18: =G15+G16 -> 5061 | H18: =H15+H16 -> 5889 | I18: =I15+I16 -> 6620 | ... K18: =K15+K16 -> 7979 | L18: =IFERROR(L15+L16,"") -> 7490.0164 | M18: =IFERROR(M15+M16,"") -> 8228.5689 | N18: =IFERROR(N15+N16,"") -> 9039.9464 | O18: =IFERROR(O15+O16,"") -> 9931.3297 | P18: =IFERROR(P15+P16,"") -> 10910.608
A19: Minority Interests | B19: -26 | C19: -35 | D19: -45 | E19: -45 | F19: -57 | G19: -72 | H19: -71 | I19: 0 | J19: 0 | K19: 0 | L19: =IFERROR(K19/K18*L18,"") -> 0 | M19: =IFERROR(L19/L18*M18,"") -> 0 | N19: =IFERROR(M19/M18*N18,"") -> 0 | O19: =IFERROR(N19/N18*O18,"") -> 0 | P19: =IFERROR(O19/O18*P18,"") -> 0
A20: Net Income | B20: =B18+B19 -> 2311 | C20: =C18+C19 -> 2667 | D20: =D18+D19 -> 3088 | E20: =E18+E19 -> 3607 | F20: =F18+F19 -> 3999 | G20: =G18+G19 -> 4989 | H20: =H18+H19 -> 5818 | I20: =I18+I19 -> 6620 | ... K20: =K18+K19 -> 7979 | L20: =IFERROR(L18+L19,"") -> 7490.0164 | M20: =IFERROR(M18+M19,"") -> 8228.5689 | N20: =IFERROR(N18+N19,"") -> 9039.9464 | O20: =IFERROR(O18+O19,"") -> 9931.3297 | P20: =IFERROR(P18+P19,"") -> 10910.608
A21: Net margin % | B21: =IFERROR(B20/B3,"") -> 0.019466134 | C21: =IFERROR(C20/C3,"") -> 0.020670413 | D21: =IFERROR(D20/D3,"") -> 0.021811606 | E21: =IFERROR(E20/E3,"") -> 0.023621016 | F21: =IFERROR(F20/F3,"") -> 0.023980427 | G21: =IFERROR(G20/G3,"") -> 0.025463306 | H21: =IFERROR(H20/H3,"") -> 0.025635151 | I21: =IFERROR(I20/I3,"") -> 0.02732263 | ... P21: =IFERROR(P20/P3,"") -> 0.024770659
A22: Y/Y Growth % | C22: =IFERROR((C20-B20)/B20,"") -> 0.15404587 | D22: =IFERROR((D20-C20)/C20,"") -> 0.15785527 | E22: =IFERROR((E20-D20)/D20,"") -> 0.16806995 | F22: =IFERROR((F20-E20)/E20,"") -> 0.10867757 | G22: =IFERROR((G20-F20)/F20,"") -> 0.24756189 | H22: =IFERROR((H20-G20)/G20,"") -> 0.16616556 | I22: =IFERROR((I20-H20)/H20,"") -> 0.13784806 | J22: =IFERROR((J20-I20)/I20,"") -> 0.099093656 | ... P22: =IFERROR((P20-O20)/O20,"") -> 0.098604933
A23: EPS | B23: =IFERROR(B20/B25,"") -> 5.2372751 | C23: =IFERROR(C20/C25,"") -> 6.048442 | D23: =IFERROR(D20/D25,"") -> 6.9891135 | E23: =IFERROR(E20/E25,"") -> 8.1436828 | F23: =IFERROR(F20/F25,"") -> 9.0087858 | G23: =IFERROR(G20/G25,"") -> 11.227636 | H23: =IFERROR(H20/H25,"") -> 13.081212 | I23: =IFERROR(I20/I25,"") -> 14.894814 | ... P23: =IFERROR(P20/P25,"") -> 24.42052
A24: Y/Y Growth % | C24: =IFERROR((C23-B23)/B23,"") -> 0.15488338 | D24: =IFERROR((D23-C23)/C23,"") -> 0.15552294 | E24: =IFERROR((E23-D23)/D23,"") -> 0.1651954 | F24: =IFERROR((F23-E23)/E23,"") -> 0.10622994 | G24: =IFERROR((G23-F23)/F23,"") -> 0.24629847 | H24: =IFERROR((H23-G23)/G23,"") -> 0.16509054 | I24: =IFERROR((I23-H23)/H23,"") -> 0.1386417 | J24: =IFERROR((J23-I23)/I23,"") -> 0.098327582 | ... P24: =IFERROR((P23-O23)/O23,"") -> 0.097629301
A25: Fully diluted shares - millones | B25: 441.26 | C25: 440.94 | D25: 441.83 | E25: 442.92 | F25: 443.9 | G25: 444.35 | H25: 444.76 | I25: 444.45 | J25: 444.76 | K25: 444.8 | L25: =IFERROR(K25*(1+L26),"") -> 445.19536 | M25: =IFERROR(L25*(1+M26),"") -> 445.59108 | N25: =IFERROR(M25*(1+N26),"") -> 445.98714 | O25: =IFERROR(N25*(1+O26),"") -> 446.38356 | P25: =IFERROR(O25*(1+P26),"") -> 446.78033
A26: Y/Y Growth % | C26: =IFERROR((C25-B25)/B25,"") -> -0.00072519603 | D26: =IFERROR((D25-C25)/C25,"") -> 0.0020184152 | E26: =IFERROR((E25-D25)/D25,"") -> 0.0024670122 | F26: =IFERROR((F25-E25)/E25,"") -> 0.0022125892 | G26: =IFERROR((G25-F25)/F25,"") -> 0.0010137418 | H26: =IFERROR((H25-G25)/G25,"") -> 0.00092269607 | I26: =IFERROR((I25-H25)/H25,"") -> -0.00069700513 | J26: =IFERROR((J25-I25)/I25,"") -> 0.00069749128 | K26: =IFERROR((K25-J25)/J25,"") -> 8.9936145e-05 | L26: =S6 -> 0.00088885342 | M26: =L26 -> 0.00088885342 | N26: =M26 -> 0.00088885342 | O26: =N26 -> 0.00088885342 | P26: =O26 -> 0.00088885342

Sheet 2.FCF
A1: =IF('1.IS'!A1<>"",'1.IS'!A1,"") | B1: Cash Flow Statement | O1: #VALUE!
A2: (millones, excepto FCF per share) | B2: ='1.IS'!B$2 -> 2016 | C2: ='1.IS'!C$2 -> 2017 | D2: ='1.IS'!D$2 -> 2018 | E2: ='1.IS'!E$2 -> 2019 | F2: ='1.IS'!F$2 -> 2020 | G2: ='1.IS'!G$2 -> 2021 | H2: ='1.IS'!H$2 -> 2022 | I2: ='1.IS'!I$2 -> 2023 | ... P2: ='1.IS'!P$2 -> 2030e
A3: EBITDA | B3: ='1.IS'!B5 -> 3672 | C3: ='1.IS'!C5 -> 4111 | D3: ='1.IS'!D5 -> 4480 | E3: ='1.IS'!E5 -> 4737 | F3: ='1.IS'!F5 -> 5435 | G3: ='1.IS'!G5 -> 6792 | H3: ='1.IS'!H5 -> 7911 | I3: ='1.IS'!I5 -> 8505 | ... P3: ='1.IS'!P5 -> 14838.745
A4: (-) CapEx Mantenimiento - en negativo | B4: -2649 | C4: -2502 | D4: -2969 | E4: -2998 | F4: -2810 | G4: -3588 | H4: -3891 | I4: -4323 | J4: -4710 | K4: -5498 | L4: =IFERROR(-L22*'1.IS'!L3,"") -> -6040.1299 | M4: =IFERROR(-M22*'1.IS'!M3,"") -> -6635.7165 | N4: =IFERROR(-N22*'1.IS'!N3,"") -> -7290.0309 | O4: =IFERROR(-O22*'1.IS'!O3,"") -> -8008.8639 | P4: =IFERROR(-P22*'1.IS'!P3,"") -> -8798.5774
A5: (-) Total interest expense | B5: ='1.IS'!B14 -> -92 | C5: ='1.IS'!C14 -> -84 | D5: ='1.IS'!D14 -> -84 | E5: ='1.IS'!E14 -> -24 | F5: ='1.IS'!F14 -> -71 | G5: ='1.IS'!G14 -> -130 | H5: ='1.IS'!H14 -> -97 | I5: ='1.IS'!I14 -> 310 | ... P5: ='1.IS'!P14 -> 42.635563
A6: (-) Taxes paid | B6: ='1.IS'!B16 -> -1243 | C6: ='1.IS'!C16 -> -1325 | D6: ='1.IS'!D16 -> -1263 | E6: ='1.IS'!E16 -> -1061 | F6: ='1.IS'!F16 -> -1308 | G6: ='1.IS'!G16 -> -1601 | H6: ='1.IS'!H16 -> -1925 | I6: ='1.IS'!I16 -> -2195 | ... P6: ='1.IS'!P16 -> -3970.7726
A7: (+) Inventories | B7: 8969 | C7: 9834 | D7: 11040 | E7: 11395 | F7: 12242 | G7: 14215 | H7: 17907 | I7: 16651 | J7: 18647 | K7: 18116
A8: (+) Accounts Receivable | B8: 1252 | C8: 1432 | D8: 1669 | E8: 1535 | F8: 1550 | G8: 1803 | H8: 2241 | I8: 2285 | J8: 2721 | K8: 3203
A9: (-) Accounts Payable | B9: 7612 | C9: 9608 | D9: 11237 | E9: 11679 | F9: 14172 | G9: 16278 | H9: 17848 | I9: 17483 | J9: 19421 | K9: 19783
A10: (-) Unearned Revenue | B10: 1362 | C10: 1498 | D10: 1624 | E10: 1711 | F10: 1851 | G10: 2042 | H10: 2174 | I10: 2337 | J10: 2501 | K10: 2854
A11: Working Capital - WC | B11: =B7+B8-B9-B10 -> 1247 | C11: =C7+C8-C9-C10 -> 160 | D11: =D7+D8-D9-D10 -> -152 | E11: =E7+E8-E9-E10 -> -460 | F11: =F7+F8-F9-F10 -> -2231 | G11: =G7+G8-G9-G10 -> -2302 | H11: =H7+H8-H9-H10 -> 126 | I11: =I7+I8-I9-I10 -> -884 | ... K11: =K7+K8-K9-K10 -> -1318 | L11: =IFERROR(IF(AND(L7<>"",L8<>"",L10<>""),L7+L8-L9-L10,K11+L12),"") -> -1752.5226 | M11: =IFERROR(IF(AND(M7<>"",M8<>"",M10<>""),M7+M8-M9-M10,L11+M12),"") -> -2229.8912 | N11: =IFERROR(IF(AND(N7<>"",N8<>"",N10<>""),N7+N8-N9-N10,M11+N12),"") -> -2754.3308 | O11: =IFERROR(IF(AND(O7<>"",O8<>"",O10<>""),O7+O8-O9-O10,N11+O12),"") -> -3330.4827 | P11: =IFERROR(IF(AND(P7<>"",P8<>"",P10<>""),P7+P8-P9-P10,O11+P12),"") -> -3963.446 | R11: AJUSTAR MANUALMENTE
A12: (-) Variación de Working Capital - CWC | C12: =IF(B9>0,C11-B11,0) -> -1087 | D12: =IF(C9>0,D11-C11,0) -> -312 | E12: =IF(D9>0,E11-D11,0) -> -308 | F12: =IF(E9>0,F11-E11,0) -> -1771 | G12: =IF(F9>0,G11-F11,0) -> -71 | H12: =IF(G9>0,H11-G11,0) -> 2428 | I12: =IF(H9>0,I11-H11,0) -> -1010 | J12: =IF(I9>0,J11-I11,0) -> 330 | K12: =IF(J9>0,K11-J11,0) -> -764 | L12: =IFERROR((SUM(C12:K12)/SUM('1.IS'!C3:K3))*'1.IS'!L3,"") -> -434.52259 | M12: =IFERROR(IF(AND(M7<>"",M8<>"",M10<>""),(M7+M8-M9-M10)-(L7+L8-L9-L10),(L12/'1.IS'!L3)*'1.IS'!M3),"") -> -477.36866 | N12: =IFERROR(IF(AND(N7<>"",N8<>"",N10<>""),(N7+N8-N9-N10)-(M7+M8-M9-M10),(M12/'1.IS'!M3)*'1.IS'!N3),"") -> -524.43956 | O12: =IFERROR(IF(AND(O7<>"",O8<>"",O10<>""),(O7+O8-O9-O10)-(N7+N8-N9-N10),(N12/'1.IS'!N3)*'1.IS'!O3),"") -> -576.15189 | P12: =IFERROR(IF(AND(P7<>"",P8<>"",P10<>""),(P7+P8-P9-P10)-(O7+O8-O9-O10),(O12/'1.IS'!O3)*'1.IS'!P3),"") -> -632.96331
A13: (-) Otros ajustes - Opcional; p.ej. Minority Interests | B13: ='1.IS'!B19 -> -26 | C13: ='1.IS'!C19 -> -35 | D13: ='1.IS'!D19 -> -45 | E13: ='1.IS'!E19 -> -45 | F13: ='1.IS'!F19 -> -57 | G13: ='1.IS'!G19 -> -72 | H13: ='1.IS'!H19 -> -71 | I13: ='1.IS'!I19 -> 0 | ... P13: ='1.IS'!P19 -> 0
A14: Free Cash Flow | B14: =B3+B4+B5+B6-B12+B13 -> -338 | C14: =C3+C4+C5+C6-C12+C13 -> 1252 | D14: =D3+D4+D5+D6-D12+D13 -> 431 | E14: =E3+E4+E5+E6-E12+E13 -> 917 | F14: =F3+F4+F5+F6-F12+F13 -> 2960 | G14: =G3+G4+G5+G6-G12+G13 -> 1472 | H14: =H3+H4+H5+H6-H12+H13 -> -501 | I14: =I3+I4+I5+I6-I12+I13 -> 3307 | ... K14: =K3+K4+K5+K6-K12+K13 -> 3245 | L14: =IFERROR(L3+L4+L5+L6-L12+L13,"") -> 1884.4091 | M14: =IFERROR(M3+M4+M5+M6-M12+M13,"") -> 2070.2211 | N14: =IFERROR(N3+N4+N5+N6-N12+N13,"") -> 2274.3551 | O14: =IFERROR(O3+O4+O5+O6-O12+O13,"") -> 2498.6177 | P14: =IFERROR(P3+P4+P5+P6-P12+P13,"") -> 2744.9938
A15: FCF Margin % | B15: =IFERROR(B14/'1.IS'!B3,"") -> -0.002847059 | C15: =IFERROR(C14/'1.IS'!C3,"") -> 0.0097035458 | D15: =IFERROR(D14/'1.IS'!D3,"") -> 0.0030443013 | E15: =IFERROR(E14/'1.IS'!E3,"") -> 0.0060051211 | F15: =IFERROR(F14/'1.IS'!F3,"") -> 0.017749954 | G15: =IFERROR(G14/'1.IS'!G3,"") -> 0.0075129256 | H15: =IFERROR(H14/'1.IS'!H3,"") -> -0.0022074958 | I15: =IFERROR(I14/'1.IS'!I3,"") -> 0.013648933 | ... P15: =IFERROR(P14/'1.IS'!P3,"") -> 0.0062320363
A16: Y/Y Growth % | C16: =IFERROR((C14-B14)/B14,"") -> -4.704142 | D16: =IFERROR((D14-C14)/C14,"") -> -0.6557508 | E16: =IFERROR((E14-D14)/D14,"") -> 1.1276102 | F16: =IFERROR((F14-E14)/E14,"") -> 2.2279171 | G16: =IFERROR((G14-F14)/F14,"") -> -0.5027027 | H16: =IFERROR((H14-G14)/G14,"") -> -1.3403533 | I16: =IFERROR((I14-H14)/H14,"") -> -7.6007984 | J16: =IFERROR((J14-I14)/I14,"") -> -0.32385848 | ... P16: =IFERROR((P14-O14)/O14,"") -> 0.098604933
A17: Free Cash Flow per share - FCFPS | B17: =IFERROR(B14/'1.IS'!B25,"") -> -0.76598831 | C17: =IFERROR(C14/'1.IS'!C25,"") -> 2.8393886 | D17: =IFERROR(D14/'1.IS'!D25,"") -> 0.97548831 | E17: =IFERROR(E14/'1.IS'!E25,"") -> 2.0703513 | F17: =IFERROR(F14/'1.IS'!F25,"") -> 6.6681685 | G17: =IFERROR(G14/'1.IS'!G25,"") -> 3.3127039 | H17: =IFERROR(H14/'1.IS'!H25,"") -> -1.1264502 | I17: =IFERROR(I14/'1.IS'!I25,"") -> 7.440657 | ... P17: =IFERROR(P14/'1.IS'!P25,"") -> 6.143945
A18: Y/Y Growth % | C18: =IFERROR((C17-B17)/B17,"") -> -4.7068302 | D18: =IFERROR((D17-C17)/C17,"") -> -0.65644424 | E18: =IFERROR((E17-D17)/D17,"") -> 1.1223743 | F18: =IFERROR((F17-E17)/E17,"") -> 2.2207908 | G18: =IFERROR((G17-F17)/F17,"") -> -0.50320632 | H18: =IFERROR((H17-G17)/G17,"") -> -1.3400395 | I18: =IFERROR((I17-H17)/H17,"") -> -7.6054024 | J18: =IFERROR((J17-I17)/I17,"") -> -0.32432976 | ... P18: =IFERROR((P17-O17)/O17,"") -> 0.097629301
A19: Net Change in Cash | B19: =IFERROR(VLOOKUP("Net Change in Cash*",'9.TIKR_CF'!$A:$K,COLUMN(B19),FALSE),"0") -> -1422 | C19: =IFERROR(VLOOKUP("Net Change in Cash*",'9.TIKR_CF'!$A:$K,COLUMN(C19),FALSE),"0") -> 1167 | D19: =IFERROR(VLOOKUP("Net Change in Cash*",'9.TIKR_CF'!$A:$K,COLUMN(D19),FALSE),"0") -> 1509 | E19: =IFERROR(VLOOKUP("Net Change in Cash*",'9.TIKR_CF'!$A:$K,COLUMN(E19),FALSE),"0") -> 2329 | F19: =IFERROR(VLOOKUP("Net Change in Cash*",'9.TIKR_CF'!$A:$K,COLUMN(F19),FALSE),"0") -> 3893 | G19: =IFERROR(VLOOKUP("Net Change in Cash*",'9.TIKR_CF'!$A:$K,COLUMN(G19),FALSE),"0") -> -1019 | H19: =IFERROR(VLOOKUP("Net Change in Cash*",'9.TIKR_CF'!$A:$K,COLUMN(H19),FALSE),"0") -> -1055 | I19: =IFERROR(VLOOKUP("Net Change in Cash*",'9.TIKR_CF'!$A:$K,COLUMN(I19),FALSE),"0") -> 3497 | ... K19: =IFERROR(VLOOKUP("Net Change in Cash*",'9.TIKR_CF'!$A:$K,COLUMN(K19),FALSE),"0") -> 4255 | L19: =IF('4.Valoración'!L4>0,IFERROR('4.Valoración'!L4-'4.Valoración'!K4,0),IFERROR('4.Valoración'!K4-'4.Valoración'!L4,0)) -> -4208.2743 | M19: =IF('4.Valoración'!M4>0,IFERROR('4.Valoración'!M4-'4.Valoración'!L4,0),IFERROR('4.Valoración'!L4-'4.Valoración'!M4,0)) -> 521.39584 | N19: =IF('4.Valoración'!N4>0,IFERROR('4.Valoración'!N4-'4.Valoración'!M4,0),IFERROR('4.Valoración'!M4-'4.Valoración'!N4,0)) -> 572.80804 | O19: =IF('4.Valoración'!O4>0,IFERROR('4.Valoración'!O4-'4.Valoración'!N4,0),IFERROR('4.Valoración'!N4-'4.Valoración'!O4,0)) -> 629.28974 | P19: =IF('4.Valoración'!P4>0,IFERROR('4.Valoración'!P4-'4.Valoración'!O4,0),IFERROR('4.Valoración'!O4-'4.Valoración'!P4,0)) -> 691.34081
A21: Eficiencia y márgenes | B21: ='1.IS'!B$2 -> 2016 | C21: ='1.IS'!C$2 -> 2017 | D21: ='1.IS'!D$2 -> 2018 | E21: ='1.IS'!E$2 -> 2019 | F21: ='1.IS'!F$2 -> 2020 | G21: ='1.IS'!G$2 -> 2021 | H21: ='1.IS'!H$2 -> 2022 | I21: ='1.IS'!I$2 -> 2023 | ... P21: ='1.IS'!P$2 -> 2030e | Q21: ="Promedio "&CHAR(10)&$B$2&"-"&$K$2 -> Promedio 2016-2025
A22: CapEx Mantenimiento / Ventas | B22: =IFERROR(ABS(B4)/'1.IS'!B$3,"") -> 0.022313193 | C22: =IFERROR(ABS(C4)/'1.IS'!C$3,"") -> 0.019391591 | D22: =IFERROR(ABS(D4)/'1.IS'!D$3,"") -> 0.020971069 | E22: =IFERROR(ABS(E4)/'1.IS'!E$3,"") -> 0.019632882 | F22: =IFERROR(ABS(F4)/'1.IS'!F$3,"") -> 0.016850463 | G22: =IFERROR(ABS(G4)/'1.IS'!G$3,"") -> 0.018312756 | H22: =IFERROR(ABS(H4)/'1.IS'!H$3,"") -> 0.017144443 | I22: =IFERROR(ABS(I4)/'1.IS'!I$3,"") -> 0.017842255 | ... K22: =IFERROR(ABS(K4)/'1.IS'!K$3,"") -> 0.019975657 | L22: =IFERROR(ABS((K4*'1.IS'!L4)+'2.FCF'!K4)/'1.IS'!L$3,"") -> 0.019975657 | M22: =$L$22 -> 0.019975657 | N22: =$L$22 -> 0.019975657 | O22: =$L$22 -> 0.019975657 | P22: =$L$22 -> 0.019975657 | Q22: =IFERROR(AVERAGE(B22:K22),"") -> 0.01909446
A23: Working Capital / Ventas | B23: =IFERROR(B11/'1.IS'!B$3,"") -> 0.010503795 | C23: =IFERROR(C11/'1.IS'!C$3,"") -> 0.0012400698 | D23: =IFERROR(D11/'1.IS'!D$3,"") -> -0.0010736283 | E23: =IFERROR(E11/'1.IS'!E$3,"") -> -0.0030123835 | F23: =IFERROR(F11/'1.IS'!F$3,"") -> -0.013378428 | G23: =IFERROR(G11/'1.IS'!G$3,"") -> -0.011749154 | H23: =IFERROR(H11/'1.IS'!H$3,"") -> 0.00055517858 | I23: =IFERROR(I11/'1.IS'!I$3,"") -> -0.0036485204 | ... P23: =IFERROR(P11/'1.IS'!P$3,"") -> -0.0089983227 | Q23: =IFERROR(AVERAGE(B23:K23),"") -> -0.0027528926
A24: FCF / Ventas (FCF Margin) | B24: =IFERROR(B14/'1.IS'!B$3,"") -> -0.002847059 | C24: =IFERROR(C14/'1.IS'!C$3,"") -> 0.0097035458 | D24: =IFERROR(D14/'1.IS'!D$3,"") -> 0.0030443013 | E24: =IFERROR(E14/'1.IS'!E$3,"") -> 0.0060051211 | F24: =IFERROR(F14/'1.IS'!F$3,"") -> 0.017749954 | G24: =IFERROR(G14/'1.IS'!G$3,"") -> 0.0075129256 | H24: =IFERROR(H14/'1.IS'!H$3,"") -> -0.0022074958 | I24: =IFERROR(I14/'1.IS'!I$3,"") -> 0.013648933 | ... P24: =IFERROR(P14/'1.IS'!P$3,"") -> 0.0062320363 | Q24: =IFERROR(AVERAGE(B24:K24),"") -> 0.0073187628
A25: Conversión en Caja (EBITDA que se convierte en FCF) | B25: =IFERROR(B14/B3,"") -> -0.09204793 | C25: =IFERROR(C14/C3,"") -> 0.30454877 | D25: =IFERROR(D14/D3,"") -> 0.096205357 | E25: =IFERROR(E14/E3,"") -> 0.19358244 | F25: =IFERROR(F14/F3,"") -> 0.54461822 | G25: =IFERROR(G14/G3,"") -> 0.21672556 | H25: =IFERROR(H14/H3,"") -> -0.063329541 | I25: =IFERROR(I14/I3,"") -> 0.3888301 | ... P25: =IFERROR(P14/P3,"") -> 0.18498827 | Q25: =IFERROR(AVERAGE(B25:K25),"") -> 0.21424816
A27: Asignación de capital (como % del FCF) | B27: ='1.IS'!B$2 -> 2016 | C27: ='1.IS'!C$2 -> 2017 | D27: ='1.IS'!D$2 -> 2018 | E27: ='1.IS'!E$2 -> 2019 | F27: ='1.IS'!F$2 -> 2020 | G27: ='1.IS'!G$2 -> 2021 | H27: ='1.IS'!H$2 -> 2022 | I27: ='1.IS'!I$2 -> 2023 | ... K27: ='1.IS'!K$2 -> 2025 | L27: ="Promedio "&CHAR(10)&$B$2&"-"&$K$2 -> Promedio 2016-2025
A28: CapEx Expansión (crecimiento orgánico) | B28: =IF(B14>0,IFERROR(TIKR_Cálculos!B40/B$14,""),"-") -> - | C28: =IF(C14>0,IFERROR(TIKR_Cálculos!C40/C$14,""),"-") -> 0 | D28: =IF(D14>0,IFERROR(TIKR_Cálculos!D40/D$14,""),"-") -> 0 | E28: =IF(E14>0,IFERROR(TIKR_Cálculos!E40/E$14,""),"-") -> 0 | F28: =IF(F14>0,IFERROR(TIKR_Cálculos!F40/F$14,""),"-") -> 0 | G28: =IF(G14>0,IFERROR(TIKR_Cálculos!G40/G$14,""),"-") -> 0 | H28: =IF(H14>0,IFERROR(TIKR_Cálculos!H40/H$14,""),"-") -> - | I28: =IF(I14>0,IFERROR(TIKR_Cálculos!I40/I$14,""),"-") -> 0 | ... K28: =IF(K14>0,IFERROR(TIKR_Cálculos!K40/K$14,""),"-") -> 0 | L28: =IFERROR(AVERAGE(B28:K28),"") -> 0
A29: Adquisiciones (crecimiento inorgánico) | B29: =IF(B14>0,IFERROR(TIKR_Cálculos!B43/B$14,""),"-") -> - | C29: =IF(C14>0,IFERROR(TIKR_Cálculos!C43/C$14,""),"-") -> 0 | D29: =IF(D14>0,IFERROR(TIKR_Cálculos!D43/D$14,""),"-") -> 0 | E29: =IF(E14>0,IFERROR(TIKR_Cálculos!E43/E$14,""),"-") -> 0 | F29: =IF(F14>0,IFERROR(TIKR_Cálculos!F43/F$14,""),"-") -> 0.39290541 | G29: =IF(G14>0,IFERROR(TIKR_Cálculos!G43/G$14,""),"-") -> 0 | H29: =IF(H14>0,IFERROR(TIKR_Cálculos!H43/H$14,""),"-") -> - | I29: =IF(I14>0,IFERROR(TIKR_Cálculos!I43/I$14,""),"-") -> 0 | ... K29: =IF(K14>0,IFERROR(TIKR_Cálculos!K43/K$14,""),"-") -> 0 | L29: =IFERROR(AVERAGE(B29:K29),"") -> 0.049113176
A30: Dividendos | B30: =IF(B14>0,IFERROR(TIKR_Cálculos!B41/B$14,""),"-") -> - | C30: =IF(C14>0,IFERROR(TIKR_Cálculos!C41/C$14,""),"-") -> 0 | D30: =IF(D14>0,IFERROR(TIKR_Cálculos!D41/D$14,""),"-") -> 0 | E30: =IF(E14>0,IFERROR(TIKR_Cálculos!E41/E$14,""),"-") -> 0 | F30: =IF(F14>0,IFERROR(TIKR_Cálculos!F41/F$14,""),"-") -> 0 | G30: =IF(G14>0,IFERROR(TIKR_Cálculos!G41/G$14,""),"-") -> 0 | H30: =IF(H14>0,IFERROR(TIKR_Cálculos!H41/H$14,""),"-") -> - | I30: =IF(I14>0,IFERROR(TIKR_Cálculos!I41/I$14,""),"-") -> 0 | ... K30: =IF(K14>0,IFERROR(TIKR_Cálculos!K41/K$14,""),"-") -> 0 | L30: =IFERROR(AVERAGE(B30:K30),"") -> 0
A31: Recompras | B31: =IF(B14>0,IFERROR(TIKR_Cálculos!B42/B$14,""),"-") -> - | C31: =IF(C14>0,IFERROR(TIKR_Cálculos!C42/C$14,""),"-") -> 0.37460064 | D31: =IF(D14>0,IFERROR(TIKR_Cálculos!D42/D$14,""),"-") -> 0.76102088 | E31: =IF(E14>0,IFERROR(TIKR_Cálculos!E42/E$14,""),"-") -> 0.2693566 | F31: =IF(F14>0,IFERROR(TIKR_Cálculos!F42/F$14,""),"-") -> 0.066216216 | G31: =IF(G14>0,IFERROR(TIKR_Cálculos!G42/G$14,""),"-") -> 0.33695652 | H31: =IF(H14>0,IFERROR(TIKR_Cálculos!H42/H$14,""),"-") -> - | I31: =IF(I14>0,IFERROR(TIKR_Cálculos!I42/I$14,""),"-") -> 0.20441488 | ... K31: =IF(K14>0,IFERROR(TIKR_Cálculos!K42/K$14,""),"-") -> 0.27827427 | L31: =IFERROR(AVERAGE(B31:K31),"") -> 0.32548738
A32: Amortización neta de deuda | B32: =IF(B14>0,IFERROR(IF(TIKR_Cálculos!B44>0,TIKR_Cálculos!B44,0)/B14,""),"-") -> - | C32: =IF(C14>0,IFERROR(IF(TIKR_Cálculos!C44>0,TIKR_Cálculos!C44,0)/C14,""),"-") -> 0 | D32: =IF(D14>0,IFERROR(IF(TIKR_Cálculos!D44>0,TIKR_Cálculos!D44,0)/D14,""),"-") -> 0.013921114 | E32: =IF(E14>0,IFERROR(IF(TIKR_Cálculos!E44>0,TIKR_Cálculos!E44,0)/E14,""),"-") -> 0 | F32: =IF(F14>0,IFERROR(IF(TIKR_Cálculos!F44>0,TIKR_Cálculos!F44,0)/F14,""),"-") -> 0 | G32: =IF(G14>0,IFERROR(IF(TIKR_Cálculos!G44>0,TIKR_Cálculos!G44,0)/G14,""),"-") -> 0.081521739 | H32: =IF(H14>0,IFERROR(IF(TIKR_Cálculos!H44>0,TIKR_Cálculos!H44,0)/H14,""),"-") -> - | I32: =IF(I14>0,IFERROR(IF(TIKR_Cálculos!I44>0,TIKR_Cálculos!I44,0)/I14,""),"-") -> 0.11611733 | ... K32: =IF(K14>0,IFERROR(IF(TIKR_Cálculos!K44>0,TIKR_Cálculos!K44,0)/K14,""),"-") -> 0.091217257 | L32: =IFERROR(AVERAGE(B32:K32),"") -> 0.077426786
A33: Total | B33: =SUM(B28:B32) -> 0 | C33: =SUM(C28:C32) -> 0.37460064 | D33: =SUM(D28:D32) -> 0.774942 | E33: =SUM(E28:E32) -> 0.2693566 | F33: =SUM(F28:F32) -> 0.45912162 | G33: =SUM(G28:G32) -> 0.41847826 | H33: =SUM(H28:H32) -> 0 | I33: =SUM(I28:I32) -> 0.3205322 | ... L33: =SUM(L28:L32) -> 0.45202734

Sheet 3.ROIC
A1: =IF('1.IS'!A1<>"",'1.IS'!A1,"") | B1: Retornos sobre el capital invertido | O1: #VALUE!
A2: (millones) | B2: ='1.IS'!B$2 -> 2016 | C2: ='1.IS'!C$2 -> 2017 | D2: ='1.IS'!D$2 -> 2018 | E2: ='1.IS'!E$2 -> 2019 | F2: ='1.IS'!F$2 -> 2020 | G2: ='1.IS'!G$2 -> 2021 | H2: ='1.IS'!H$2 -> 2022 | I2: ='1.IS'!I$2 -> 2023 | ... P2: ='1.IS'!P$2 -> 2030e
A3: EBIT x (1-t) | B3: =IFERROR('1.IS'!B9*(1-'1.IS'!B17),"") -> 2397.057 | C3: =IFERROR('1.IS'!C9*(1-'1.IS'!C17),"") -> 2758.3616 | D3: =IFERROR('1.IS'!D9*(1-'1.IS'!D17),"") -> 3192.8662 | E3: =IFERROR('1.IS'!E9*(1-'1.IS'!E17),"") -> 3670.5971 | F3: =IFERROR('1.IS'!F9*(1-'1.IS'!F17),"") -> 4109.6868 | G3: =IFERROR('1.IS'!G9*(1-'1.IS'!G17),"") -> 5159.7586 | H3: =IFERROR('1.IS'!H9*(1-'1.IS'!H17),"") -> 5962.1038 | I3: =IFERROR('1.IS'!I9*(1-'1.IS'!I17),"") -> 6387.1923 | ... P3: =IFERROR('1.IS'!P9*(1-'1.IS'!P17),"") -> 10879.349
A4: Cash and cash equivalents | B4: 3379 | C4: 4546 | D4: 6055 | E4: 8384 | F4: 12277 | G4: 11258 | H4: 10203 | I4: 13700 | J4: 9906 | K4: 14161 | L4: =IFERROR(TIKR_Cálculos!C32,0) -> 7885.3711 | M4: =IFERROR(TIKR_Cálculos!D32,0) -> 8662.9076 | N4: =IFERROR(TIKR_Cálculos!E32,0) -> 9517.113 | O4: =IFERROR(TIKR_Cálculos!F32,0) -> 10455.547 | P4: =IFERROR(TIKR_Cálculos!G32,0) -> 11486.516
A5: (-) Marketable Securities | B5: 1350 | C5: 1233 | D5: 1204 | E5: 1060 | F5: 1028 | G5: 917 | H5: 846 | I5: 1534 | J5: 1238 | K5: 1123 | L5: =IFERROR(TIKR_Cálculos!C33,0) -> 625.32814 | M5: =IFERROR(TIKR_Cálculos!D33,0) -> 686.98858 | N5: =IFERROR(TIKR_Cálculos!E33,0) -> 754.72904 | O5: =IFERROR(TIKR_Cálculos!F33,0) -> 829.14905 | P5: =IFERROR(TIKR_Cálculos!G33,0) -> 910.90723
A6: (+) Short-Term Debt | B6: 1100 | C6: 86 | D6: 90 | E6: 1699 | F6: 95 | G6: 799 | H6: 73 | I6: 1081 | J6: 103 | K6: 75 | L6: =IFERROR(TIKR_Cálculos!C35,0) -> 41.762788 | M6: =IFERROR(TIKR_Cálculos!D35,0) -> 45.880804 | N6: =IFERROR(TIKR_Cálculos!E35,0) -> 50.404878 | O6: =IFERROR(TIKR_Cálculos!F35,0) -> 55.375048 | P6: =IFERROR(TIKR_Cálculos!G35,0) -> 60.8353
A7: (+) Long-Term Debt | B7: 4061 | C7: 6573 | D7: 6487 | E7: 5124 | F7: 7514 | G7: 6692 | H7: 6484 | I7: 5377 | J7: 5794 | K7: 5713 | L7: =IFERROR(TIKR_Cálculos!C36,0) -> 3181.2107 | M7: =IFERROR(TIKR_Cálculos!D36,0) -> 3494.8938 | N7: =IFERROR(TIKR_Cálculos!E36,0) -> 3839.5076 | O7: =IFERROR(TIKR_Cálculos!F36,0) -> 4218.102 | P7: =IFERROR(TIKR_Cálculos!G36,0) -> 4634.0276
A8: (+) Current Operating Leases Liabilities | B8: 0 | C8: 0 | D8: 0 | E8: 51 | F8: 262 | G8: 294 | H8: 484 | I8: 349 | J8: 326 | K8: 286 | L8: =IFERROR(K8*'1.IS'!L4+K8,"") -> 314.20101 | M8: =IFERROR(L8*'1.IS'!M4+L8,"") -> 345.18278 | N8: =IFERROR(M8*'1.IS'!N4+M8,"") -> 379.21951 | O8: =IFERROR(N8*'1.IS'!O4+N8,"") -> 416.61242 | P8: =IFERROR(O8*'1.IS'!P4+O8,"") -> 457.69246
A9: (+) Non-Current Operating Leases Liabilities | B9: 0 | C9: 0 | D9: 0 | E9: 370 | F9: 3215 | G9: 3622 | H9: 3865 | I9: 3729 | J9: 3726 | K9: 3861 | L9: =IFERROR(K9*'1.IS'!L4+K9,"") -> 4241.7136 | M9: =IFERROR(L9*'1.IS'!M4+L9,"") -> 4659.9675 | N9: =IFERROR(M9*'1.IS'!N4+M9,"") -> 5119.4633 | O9: =IFERROR(N9*'1.IS'!O4+N9,"") -> 5624.2677 | P9: =IFERROR(O9*'1.IS'!P4+O9,"") -> 6178.8482
A10: (+) Equity | B10: 12332 | C10: 11079 | D10: 13103 | E10: 15584 | F10: 18705 | G10: 18078 | H10: 20647 | I10: 25058 | J10: 23622 | K10: 29164 | L10: =IFERROR(K10+'1.IS'!L20+'1.IS'!L26*'4.Valoración'!L3-AVERAGE('2.FCF'!$J$30:$K$30)*'2.FCF'!L14,"") -> 37044.669 | M10: =IFERROR(L10+'1.IS'!M20+'1.IS'!M26*'4.Valoración'!M3-AVERAGE('2.FCF'!$J$30:$K$30)*'2.FCF'!M14,"") -> 45664.237 | N10: =IFERROR(M10+'1.IS'!N20+'1.IS'!N26*'4.Valoración'!N3-AVERAGE('2.FCF'!$J$30:$K$30)*'2.FCF'!N14,"") -> 55095.53 | O10: =IFERROR(N10+'1.IS'!O20+'1.IS'!O26*'4.Valoración'!O3-AVERAGE('2.FCF'!$J$30:$K$30)*'2.FCF'!O14,"") -> 65418.555 | P10: =IFERROR(O10+'1.IS'!P20+'1.IS'!P26*'4.Valoración'!P3-AVERAGE('2.FCF'!$J$30:$K$30)*'2.FCF'!P14,"") -> 76721.206
A11: Invested Capital | B11: =B10+B6+B7+B8+B9-B5 -> 16143 | C11: =C10+C6+C7+C8+C9-C5 -> 16505 | D11: =D10+D6+D7+D8+D9-D5 -> 18476 | E11: =E10+E6+E7+E8+E9-E5 -> 21768 | F11: =F10+F6+F7+F8+F9-F5 -> 28763 | G11: =G10+G6+G7+G8+G9-G5 -> 28568 | H11: =H10+H6+H7+H8+H9-H5 -> 30707 | I11: =I10+I6+I7+I8+I9-I5 -> 34060 | ... K11: =K10+K6+K7+K8+K9-K5 -> 37976 | L11: =IFERROR(L10+L6+L7+L8+L9-L5,"") -> 44198.229 | M11: =IFERROR(M10+M6+M7+M8+M9-M5,"") -> 53523.173 | N11: =IFERROR(N10+N6+N7+N8+N9-N5,"") -> 63729.397 | O11: =IFERROR(O10+O6+O7+O8+O9-O5,"") -> 74903.763 | P11: =IFERROR(P10+P6+P7+P8+P9-P5,"") -> 87141.702
A13: Ratios de rentabilidad | B13: ='1.IS'!B$2 -> 2016 | C13: ='1.IS'!C$2 -> 2017 | D13: ='1.IS'!D$2 -> 2018 | E13: ='1.IS'!E$2 -> 2019 | F13: ='1.IS'!F$2 -> 2020 | G13: ='1.IS'!G$2 -> 2021 | H13: ='1.IS'!H$2 -> 2022 | I13: ='1.IS'!I$2 -> 2023 | ... P13: ='1.IS'!P$2 -> 2030e | Q13: ="Promedio "&CHAR(10)&B$2&" - "&K$2 -> Promedio 2016 - 2025
A14: ROE | B14: =IFERROR('1.IS'!B20/B10,"") -> 0.18739864 | C14: =IFERROR('1.IS'!C20/C10,"") -> 0.2407257 | D14: =IFERROR('1.IS'!D20/D10,"") -> 0.23567122 | E14: =IFERROR('1.IS'!E20/E10,"") -> 0.23145534 | F14: =IFERROR('1.IS'!F20/F10,"") -> 0.2137931 | G14: =IFERROR('1.IS'!G20/G10,"") -> 0.27597079 | H14: =IFERROR('1.IS'!H20/H10,"") -> 0.28178428 | I14: =IFERROR('1.IS'!I20/I10,"") -> 0.26418709 | ... P14: =IFERROR('1.IS'!P20/P10,"") -> 0.14221111 | Q14: =IFERROR(AVERAGE(B14:K14),"") -> 0.25125948
A15: ROIC | B15: =IFERROR(B3/B11,"") -> 0.14848894 | C15: =IFERROR(C3/C11,"") -> 0.16712278 | D15: =IFERROR(D3/D11,"") -> 0.17281155 | E15: =IFERROR(E3/E11,"") -> 0.16862353 | F15: =IFERROR(F3/F11,"") -> 0.14288102 | G15: =IFERROR(G3/G11,"") -> 0.18061323 | H15: =IFERROR(H3/H11,"") -> 0.19416106 | I15: =IFERROR(I3/I11,"") -> 0.18752767 | ... P15: =IFERROR(P3/P11,"") -> 0.12484664 | Q15: =IFERROR(AVERAGE(B15:K15),"") -> 0.17826937
A16: Tasa de reinversión | B16: =IF('2.FCF'!B14>0,IFERROR(TIKR_Cálculos!B12/'2.FCF'!B14,""),0%) -> 0 | C16: =IF('2.FCF'!C14>0,IFERROR(TIKR_Cálculos!C12/'2.FCF'!C14,""),0%) -> 0 | D16: =IF('2.FCF'!D14>0,IFERROR(TIKR_Cálculos!D12/'2.FCF'!D14,""),0%) -> 0 | E16: =IF('2.FCF'!E14>0,IFERROR(TIKR_Cálculos!E12/'2.FCF'!E14,""),0%) -> 0 | F16: =IF('2.FCF'!F14>0,IFERROR(TIKR_Cálculos!F12/'2.FCF'!F14,""),0%) -> 0.39290541 | G16: =IF('2.FCF'!G14>0,IFERROR(TIKR_Cálculos!G12/'2.FCF'!G14,""),0%) -> 0 | H16: =IF('2.FCF'!H14>0,IFERROR(TIKR_Cálculos!H12/'2.FCF'!H14,""),0%) -> 0 | I16: =IF('2.FCF'!I14>0,IFERROR(TIKR_Cálculos!I12/'2.FCF'!I14,""),0%) -> 0 | ... K16: =IF('2.FCF'!K14>0,IFERROR(TIKR_Cálculos!K12/'2.FCF'!K14,""),0%) -> 0 | L16: - | M16: - | N16: - | O16: - | P16: - | Q16: =IFERROR(AVERAGE(B16:K16),"") -> 0.039290541

Sheet 4.Valoración
A1: =IF('1.IS'!A1<>"",'1.IS'!A1,"") | B1: Valoración | O1: #VALUE!
A2: Valoración (millones) | B2: ='1.IS'!B$2 -> 2016 | C2: ='1.IS'!C$2 -> 2017 | D2: ='1.IS'!D$2 -> 2018 | E2: ='1.IS'!E$2 -> 2019 | F2: ='1.IS'!F$2 -> 2020 | G2: ='1.IS'!G$2 -> 2021 | H2: ='1.IS'!H$2 -> 2022 | I2: ='1.IS'!I$2 -> 2023 | ... P2: ='1.IS'!P$2 -> 2030e
A3: Market cap | K3: =$D$12*'1.IS'!K25 -> 439111.01 | L3: =IFERROR($D$12*'1.IS'!L25,"") -> 439501.31 | M3: =IFERROR($D$12*'1.IS'!M25,"") -> 439891.97 | N3: =IFERROR($D$12*'1.IS'!N25,"") -> 440282.97 | O3: =IFERROR($D$12*'1.IS'!O25,"") -> 440674.31 | P3: =IFERROR($D$12*'1.IS'!P25,"") -> 441066.01
A4: Deuda Neta | B4: =('3.ROIC'!B7+'3.ROIC'!B6)-('3.ROIC'!B4+'3.ROIC'!B5) -> 432 | C4: =('3.ROIC'!C7+'3.ROIC'!C6)-('3.ROIC'!C4+'3.ROIC'!C5) -> 880 | D4: =('3.ROIC'!D7+'3.ROIC'!D6)-('3.ROIC'!D4+'3.ROIC'!D5) -> -682 | E4: =('3.ROIC'!E7+'3.ROIC'!E6)-('3.ROIC'!E4+'3.ROIC'!E5) -> -2621 | F4: =('3.ROIC'!F7+'3.ROIC'!F6)-('3.ROIC'!F4+'3.ROIC'!F5) -> -5696 | G4: =('3.ROIC'!G7+'3.ROIC'!G6)-('3.ROIC'!G4+'3.ROIC'!G5) -> -4684 | H4: =('3.ROIC'!H7+'3.ROIC'!H6)-('3.ROIC'!H4+'3.ROIC'!H5) -> -4492 | I4: =('3.ROIC'!I7+'3.ROIC'!I6)-('3.ROIC'!I4+'3.ROIC'!I5) -> -8776 | ... K4: =('3.ROIC'!K7+'3.ROIC'!K6)-('3.ROIC'!K4+'3.ROIC'!K5) -> -9496 | L4: =IFERROR(L5*'1.IS'!L5,"") -> -5287.7257 | M4: =IFERROR(M5*'1.IS'!M5,"") -> -5809.1216 | N4: =IFERROR(N5*'1.IS'!N5,"") -> -6381.9296 | O4: =IFERROR(O5*'1.IS'!O5,"") -> -7011.2194 | P4: =IFERROR(P5*'1.IS'!P5,"") -> -7702.5602
A5: Deuda neta / EBITDA | B5: =IFERROR('4.Valoración'!B4/'1.IS'!B5,"") -> 0.11764706 | C5: =IFERROR('4.Valoración'!C4/'1.IS'!C5,"") -> 0.21405984 | D5: =IFERROR('4.Valoración'!D4/'1.IS'!D5,"") -> -0.15223214 | E5: =IFERROR('4.Valoración'!E4/'1.IS'!E5,"") -> -0.55330378 | F5: =IFERROR('4.Valoración'!F4/'1.IS'!F5,"") -> -1.0480221 | G5: =IFERROR('4.Valoración'!G4/'1.IS'!G5,"") -> -0.68963486 | H5: =IFERROR('4.Valoración'!H4/'1.IS'!H5,"") -> -0.56781696 | I5: =IFERROR('4.Valoración'!I4/'1.IS'!I5,"") -> -1.0318636 | ... K5: =IFERROR('4.Valoración'!K4/'1.IS'!K5,"") -> -0.9145719 | L5: =AVERAGE(B5:K5) -> -0.51908434 | M5: =L5 -> -0.51908434 | N5: =M5 -> -0.51908434 | O5: =N5 -> -0.51908434 | P5: =O5 -> -0.51908434 | Q5: AJUSTAR MANUALMENTE
A6: Enterprise Value (EV) | K6: =K3+K4 -> 429615.01 | L6: =IFERROR((L3+L4),"") -> 434213.59 | M6: =IFERROR((M3+M4),"") -> 434082.84 | N6: =IFERROR((N3+N4),"") -> 433901.04 | O6: =IFERROR((O3+O4),"") -> 433663.09 | P6: =IFERROR((P3+P4),"") -> 433363.45
A7: EBITDA | B7: ='1.IS'!B5 -> 3672 | C7: ='1.IS'!C5 -> 4111 | D7: ='1.IS'!D5 -> 4480 | E7: ='1.IS'!E5 -> 4737 | F7: ='1.IS'!F5 -> 5435 | G7: ='1.IS'!G5 -> 6792 | H7: ='1.IS'!H5 -> 7911 | I7: ='1.IS'!I5 -> 8505 | ... P7: ='1.IS'!P5 -> 14838.745
A8: EBIT | B8: ='1.IS'!B9 -> 3672 | C8: ='1.IS'!C9 -> 4111 | D8: ='1.IS'!D9 -> 4480 | E8: ='1.IS'!E9 -> 4737 | F8: ='1.IS'!F9 -> 5435 | G8: ='1.IS'!G9 -> 6792 | H8: ='1.IS'!H9 -> 7911 | I8: ='1.IS'!I9 -> 8505 | ... P8: ='1.IS'!P9 -> 14838.745
A9: Net income | B9: ='1.IS'!B20 -> 2311 | C9: ='1.IS'!C20 -> 2667 | D9: ='1.IS'!D20 -> 3088 | E9: ='1.IS'!E20 -> 3607 | F9: ='1.IS'!F20 -> 3999 | G9: ='1.IS'!G20 -> 4989 | H9: ='1.IS'!H20 -> 5818 | I9: ='1.IS'!I20 -> 6620 | ... P9: ='1.IS'!P20 -> 10910.608
A10: FCF | B10: ='2.FCF'!B14 -> -338 | C10: ='2.FCF'!C14 -> 1252 | D10: ='2.FCF'!D14 -> 431 | E10: ='2.FCF'!E14 -> 917 | F10: ='2.FCF'!F14 -> 2960 | G10: ='2.FCF'!G14 -> 1472 | H10: ='2.FCF'!H14 -> -501 | I10: ='2.FCF'!I14 -> 3307 | ... P10: ='2.FCF'!P14 -> 2744.9938
A12: Precio por acción actual | D12: 987.21
A14: Múltiplos de valoración | B14: LTM | C14: NTM | D14: Objetivo
A15: PER | B15: =IF(D12<>"",IFERROR(D12/'1.IS'!K23,""),"") -> 55.033339 | C15: =IF(D12<>"",IFERROR(D12/'1.IS'!L23,""),"") -> 58.678285 | D15: =C15 -> 58.678285
A16: EV / FCF | B16: =IF(D12<>"",IFERROR(K6/K10,""),"") -> 132.39291 | C16: =IF(D12<>"",IFERROR(L6/L10,""),"") -> 230.42427 | D16: =D15 -> 58.678285 | G16: AJUSTAR MANUALMENTE
A17: EV / EBITDA | B17: =IF(D12<>"",IFERROR(K6/K7,""),"") -> 41.37677 | C17: =IF(D12<>"",IFERROR(L6/L7,""),"") -> 42.625788 | D17: =C17 -> 42.625788
A18: EV / EBIT | B18: =IF(D12<>"",IFERROR(K6/K8,""),"") -> 41.37677 | C18: =IF(D12<>"",IFERROR(L6/L8,""),"") -> 42.625788 | D18: =C18 -> 42.625788
A20: Precio objetivo | B20: =L2 -> 2026e | C20: =M2 -> 2027e | D20: =N2 -> 2028e | E20: =O2 -> 2029e | F20: =P2 -> 2030e | H20: ="Retorno Anualizado"&CHAR(10)&"valorando por..." -> Retorno Anualizado valorando por... | K20: ="CAGR"&CHAR(10)&"5 años" -> CAGR 5 años
A21: PER ex Cash | B21: =IF(D12<>"",IFERROR(IF(--L4<0,(L9*$D$15-L4),IF(--L4>0,L9*$D$15))/'1.IS'!L25,""),"") -> 999.08732 | C21: =IF(D12<>"",IFERROR(IF(--M4<0,(M9*$D$15-M4),IF(--M4>0,M9*$D$15))/'1.IS'!M25,""),"") -> 1096.6275 | D21: =IF(D12<>"",IFERROR(IF(--N4<0,(N9*$D$15-N4),IF(--N4>0,N9*$D$15))/'1.IS'!N25,""),"") -> 1203.6905 | E21: =IF(D12<>"",IFERROR(IF(--O4<0,(O9*$D$15-O4),IF(--O4>0,O9*$D$15))/'1.IS'!O25,""),"") -> 1321.206 | F21: =IF(D12<>"",IFERROR(IF(--P4<0,(P9*$D$15-P4),IF(--P4>0,P9*$D$15))/'1.IS'!P25,""),"") -> 1450.1944 | H21: PER ex Cash | K21: =IFERROR((F21/$D$12)^(1/5)-1,"") -> 0.079949216
A22: EV / FCF | B22: =IF(D12<>"",IFERROR(((L10*$D$16)-L4)/'1.IS'!L25,""),"") -> 260.24893 | C22: =IF(D12<>"",IFERROR(((M10*$D$16)-M4)/'1.IS'!M25,""),"") -> 285.65685 | D22: =IF(D12<>"",IFERROR(((N10*$D$16)-N4)/'1.IS'!N25,""),"") -> 313.54533 | E22: =IF(D12<>"",IFERROR(((O10*$D$16)-O4)/'1.IS'!O25,""),"") -> 344.15654 | F22: =IF(D12<>"",IFERROR(((P10*$D$16)-P4)/'1.IS'!P25,""),"") -> 377.7563 | H22: EV / FCF | K22: =IFERROR((F22/$D$12)^(1/5)-1,"") -> -0.17479769
A23: EV / EBITDA | B23: =IF(D12<>"",IFERROR(((L7*$D$17)-L4)/'1.IS'!L25,""),"") -> 987.21 | C23: =IF(D12<>"",IFERROR(((M7*$D$17)-M4)/'1.IS'!M25,""),"") -> 1083.5906 | D23: =IF(D12<>"",IFERROR(((N7*$D$17)-N4)/'1.IS'!N25,""),"") -> 1189.3808 | E23: =IF(D12<>"",IFERROR(((O7*$D$17)-O4)/'1.IS'!O25,""),"") -> 1305.4992 | F23: =IF(D12<>"",IFERROR(((P7*$D$17)-P4)/'1.IS'!P25,""),"") -> 1432.9542 | H23: EV / EBITDA | K23: =IFERROR((F23/$D$12)^(1/5)-1,"") -> 0.077369195
A24: EV / EBIT | B24: =IF(D12<>"",IFERROR(((L8*$D$18)-L4)/'1.IS'!L25,""),"") -> 987.21 | C24: =IF(D12<>"",IFERROR(((M8*$D$18)-M4)/'1.IS'!M25,""),"") -> 1083.5906 | D24: =IF(D12<>"",IFERROR(((N8*$D$18)-N4)/'1.IS'!N25,""),"") -> 1189.3808 | E24: =IF(D12<>"",IFERROR(((O8*$D$18)-O4)/'1.IS'!O25,""),"") -> 1305.4992 | F24: =IF(D12<>"",IFERROR(((P8*$D$18)-P4)/'1.IS'!P25,""),"") -> 1432.9542 | H24: EV / EBIT | K24: =IFERROR((F24/$D$12)^(1/5)-1,"") -> 0.077369195
A25: Promedio | B25: =IFERROR(AVERAGE(B21:B24),"") -> 808.43906 | C25: =IFERROR(AVERAGE(C21:C24),"") -> 887.3664 | D25: =IFERROR(AVERAGE(D21:D24),"") -> 973.99936 | E25: =IFERROR(AVERAGE(E21:E24),"") -> 1069.0902 | F25: =IFERROR(AVERAGE(F21:F24),"") -> 1173.4648 | H25: Promedio | K25: =IFERROR(AVERAGE(K21:K24),"") -> 0.014972479
A26: Margen de seguridad (EV/FCF) | B26: =IFERROR((B22/$D$12)-1,"") -> -0.73637936 | C26: =IFERROR((C22/$D$12)-1,"") -> -0.71064226 | D26: =IFERROR((D22/$D$12)-1,"") -> -0.68239247 | E26: =IFERROR((E22/$D$12)-1,"") -> -0.65138467 | F26: =IFERROR((F22/$D$12)-1,"") -> -0.6173496
C43: Precio de compra | D43: Diferencia vs precio actual
A44: Retorno anual objetivo | B44: 0.15 | C44: =IFERROR(F22/((1+B44)^5),"") -> 187.81165 | D44: =IFERROR((C44-D12)/D12,"") -> -0.80975512

Sheet 5.Red Flags
A1: =IF('1.IS'!A1<>"",'1.IS'!A1,"") | B1: Posibles "Red Flags"
A2: Posibles "red flags" (1) | B2: ='1.IS'!B$2 -> 2016 | C2: ='1.IS'!C$2 -> 2017 | D2: ='1.IS'!D$2 -> 2018 | E2: ='1.IS'!E$2 -> 2019 | F2: ='1.IS'!F$2 -> 2020 | G2: ='1.IS'!G$2 -> 2021 | H2: ='1.IS'!H$2 -> 2022 | I2: ='1.IS'!I$2 -> 2023 | ... K2: ='1.IS'!K$2 -> 2025
A3: Como % de ventas...
A4: Impairments | B4: =IFERROR(ABS(VLOOKUP("Asset Writedown*",'7.TIKR_IS'!$A:$K,COLUMN('2.FCF'!B7),FALSE)/'1.IS'!B3),0%)+IFERROR(ABS(VLOOKUP("Impairment of Goodwill*",'7.TIKR_IS'!$A:$K,COLUMN('2.FCF'!B7),FALSE)/'1.IS'!B3),0%) -> 0 | C4: =IFERROR(ABS(VLOOKUP("Asset Writedown*",'7.TIKR_IS'!$A:$K,COLUMN('2.FCF'!C7),FALSE)/'1.IS'!C3),0%)+IFERROR(ABS(VLOOKUP("Impairment of Goodwill*",'7.TIKR_IS'!$A:$K,COLUMN('2.FCF'!C7),FALSE)/'1.IS'!C3),0%) -> 0 | D4: =IFERROR(ABS(VLOOKUP("Asset Writedown*",'7.TIKR_IS'!$A:$K,COLUMN('2.FCF'!D7),FALSE)/'1.IS'!D3),0%)+IFERROR(ABS(VLOOKUP("Impairment of Goodwill*",'7.TIKR_IS'!$A:$K,COLUMN('2.FCF'!D7),FALSE)/'1.IS'!D3),0%) -> 0 | E4: =IFERROR(ABS(VLOOKUP("Asset Writedown*",'7.TIKR_IS'!$A:$K,COLUMN('2.FCF'!E7),FALSE)/'1.IS'!E3),0%)+IFERROR(ABS(VLOOKUP("Impairment of Goodwill*",'7.TIKR_IS'!$A:$K,COLUMN('2.FCF'!E7),FALSE)/'1.IS'!E3),0%) -> 0 | F4: =IFERROR(ABS(VLOOKUP("Asset Writedown*",'7.TIKR_IS'!$A:$K,COLUMN('2.FCF'!F7),FALSE)/'1.IS'!F3),0%)+IFERROR(ABS(VLOOKUP("Impairment of Goodwill*",'7.TIKR_IS'!$A:$K,COLUMN('2.FCF'!F7),FALSE)/'1.IS'!F3),0%) -> 0 | G4: =IFERROR(ABS(VLOOKUP("Asset Writedown*",'7.TIKR_IS'!$A:$K,COLUMN('2.FCF'!G7),FALSE)/'1.IS'!G3),0%)+IFERROR(ABS(VLOOKUP("Impairment of Goodwill*",'7.TIKR_IS'!$A:$K,COLUMN('2.FCF'!G7),FALSE)/'1.IS'!G3),0%) -> 0.00042872673 | H4: =IFERROR(ABS(VLOOKUP("Asset Writedown*",'7.TIKR_IS'!$A:$K,COLUMN('2.FCF'!H7),FALSE)/'1.IS'!H3),0%)+IFERROR(ABS(VLOOKUP("Impairment of Goodwill*",'7.TIKR_IS'!$A:$K,COLUMN('2.FCF'!H7),FALSE)/'1.IS'!H3),0%) -> 0.00051992915 | I4: =IFERROR(ABS(VLOOKUP("Asset Writedown*",'7.TIKR_IS'!$A:$K,COLUMN('2.FCF'!I7),FALSE)/'1.IS'!I3),0%)+IFERROR(ABS(VLOOKUP("Impairment of Goodwill*",'7.TIKR_IS'!$A:$K,COLUMN('2.FCF'!I7),FALSE)/'1.IS'!I3),0%) -> 0.0016137686 | ... K4: =IFERROR(ABS(VLOOKUP("Asset Writedown*",'7.TIKR_IS'!$A:$K,COLUMN('2.FCF'!K7),FALSE)/'1.IS'!K3),0%)+IFERROR(ABS(VLOOKUP("Impairment of Goodwill*",'7.TIKR_IS'!$A:$K,COLUMN('2.FCF'!K7),FALSE)/'1.IS'!K3),0%) -> 0
A5: Desinversiones | B5: =IFERROR(VLOOKUP("Divestitures*",'9.TIKR_CF'!$A:$K,COLUMN('2.FCF'!B2),FALSE)/'1.IS'!B3,0%) -> 0 | C5: =IFERROR(VLOOKUP("Divestitures*",'9.TIKR_CF'!$A:$K,COLUMN('2.FCF'!C2),FALSE)/'1.IS'!C3,0%) -> 0 | D5: =IFERROR(VLOOKUP("Divestitures*",'9.TIKR_CF'!$A:$K,COLUMN('2.FCF'!D2),FALSE)/'1.IS'!D3,0%) -> 0 | E5: =IFERROR(VLOOKUP("Divestitures*",'9.TIKR_CF'!$A:$K,COLUMN('2.FCF'!E2),FALSE)/'1.IS'!E3,0%) -> 0 | F5: =IFERROR(VLOOKUP("Divestitures*",'9.TIKR_CF'!$A:$K,COLUMN('2.FCF'!F2),FALSE)/'1.IS'!F3,0%) -> 0 | G5: =IFERROR(VLOOKUP("Divestitures*",'9.TIKR_CF'!$A:$K,COLUMN('2.FCF'!G2),FALSE)/'1.IS'!G3,0%) -> 0 | H5: =IFERROR(VLOOKUP("Divestitures*",'9.TIKR_CF'!$A:$K,COLUMN('2.FCF'!H2),FALSE)/'1.IS'!H3,0%) -> 0 | I5: =IFERROR(VLOOKUP("Divestitures*",'9.TIKR_CF'!$A:$K,COLUMN('2.FCF'!I2),FALSE)/'1.IS'!I3,0%) -> 0 | ... K5: =IFERROR(VLOOKUP("Divestitures*",'9.TIKR_CF'!$A:$K,COLUMN('2.FCF'!K2),FALSE)/'1.IS'!K3,0%) -> 0
A6: Pagos en acciones | B6: =IFERROR(VLOOKUP("Stock-Based Compensation*",'9.TIKR_CF'!$A:$K,COLUMN('2.FCF'!B2),FALSE)/'1.IS'!B3,0%) -> 0.0038662725 | C6: =IFERROR(VLOOKUP("Stock-Based Compensation*",'9.TIKR_CF'!$A:$K,COLUMN('2.FCF'!C2),FALSE)/'1.IS'!C3,0%) -> 0.0039837241 | D6: =IFERROR(VLOOKUP("Stock-Based Compensation*",'9.TIKR_CF'!$A:$K,COLUMN('2.FCF'!D2),FALSE)/'1.IS'!D3,0%) -> 0.0038424592 | E6: =IFERROR(VLOOKUP("Stock-Based Compensation*",'9.TIKR_CF'!$A:$K,COLUMN('2.FCF'!E2),FALSE)/'1.IS'!E3,0%) -> 0.0038964526 | F6: =IFERROR(VLOOKUP("Stock-Based Compensation*",'9.TIKR_CF'!$A:$K,COLUMN('2.FCF'!F2),FALSE)/'1.IS'!F3,0%) -> 0.0037118991 | G6: =IFERROR(VLOOKUP("Stock-Based Compensation*",'9.TIKR_CF'!$A:$K,COLUMN('2.FCF'!G2),FALSE)/'1.IS'!G3,0%) -> 0.0033940866 | H6: =IFERROR(VLOOKUP("Stock-Based Compensation*",'9.TIKR_CF'!$A:$K,COLUMN('2.FCF'!H2),FALSE)/'1.IS'!H3,0%) -> 0.0031900738 | I6: =IFERROR(VLOOKUP("Stock-Based Compensation*",'9.TIKR_CF'!$A:$K,COLUMN('2.FCF'!I2),FALSE)/'1.IS'!I3,0%) -> 0.003194519 | ... K6: =IFERROR(VLOOKUP("Stock-Based Compensation*",'9.TIKR_CF'!$A:$K,COLUMN('2.FCF'!K2),FALSE)/'1.IS'!K3,0%) -> 0.0031246026
A7: Emisión de acciones | B7: =IFERROR(VLOOKUP("Issuance of Common Stock*",'9.TIKR_CF'!$A:$K,COLUMN('2.FCF'!B2),FALSE)/'1.IS'!B3,0%) -> 0 | C7: =IFERROR(VLOOKUP("Issuance of Common Stock*",'9.TIKR_CF'!$A:$K,COLUMN('2.FCF'!C2),FALSE)/'1.IS'!C3,0%) -> 0 | D7: =IFERROR(VLOOKUP("Issuance of Common Stock*",'9.TIKR_CF'!$A:$K,COLUMN('2.FCF'!D2),FALSE)/'1.IS'!D3,0%) -> 0 | E7: =IFERROR(VLOOKUP("Issuance of Common Stock*",'9.TIKR_CF'!$A:$K,COLUMN('2.FCF'!E2),FALSE)/'1.IS'!E3,0%) -> 0 | F7: =IFERROR(VLOOKUP("Issuance of Common Stock*",'9.TIKR_CF'!$A:$K,COLUMN('2.FCF'!F2),FALSE)/'1.IS'!F3,0%) -> 0 | G7: =IFERROR(VLOOKUP("Issuance of Common Stock*",'9.TIKR_CF'!$A:$K,COLUMN('2.FCF'!G2),FALSE)/'1.IS'!G3,0%) -> 0 | H7: =IFERROR(VLOOKUP("Issuance of Common Stock*",'9.TIKR_CF'!$A:$K,COLUMN('2.FCF'!H2),FALSE)/'1.IS'!H3,0%) -> 0 | I7: =IFERROR(VLOOKUP("Issuance of Common Stock*",'9.TIKR_CF'!$A:$K,COLUMN('2.FCF'!I2),FALSE)/'1.IS'!I3,0%) -> 0 | ... K7: =IFERROR(VLOOKUP("Issuance of Common Stock*",'9.TIKR_CF'!$A:$K,COLUMN('2.FCF'!K2),FALSE)/'1.IS'!K3,0%) -> 0
A9: Posibles "red flags" (2) | B9: Total
A10: # de años con...
A11: Decrecimiento de ventas | B11: =TIKR_Cálculos!L72 -> 0
A12: Decrecimiento de margen operativo | B12: =TIKR_Cálculos!L73 -> 2
A13: FCF negativo | B13: =TIKR_Cálculos!L74 -> 2
A14: ROIC "Pobre" (<10%) | B14: =TIKR_Cálculos!L75 -> 0
A15: Ratio Deuda Neta / EBITDA elevado (>2,5x) | B15: =TIKR_Cálculos!L76 -> 0

Sheet 6.Gráficos
A1: =IF('1.IS'!A1<>"",'1.IS'!A1,"") | B1: Evolución histórica

Sheet 7.TIKR_IS
A2: Income Statement | TIKR.com | B2: 8/28/16 | C2: 42803 | D2: 43140 | E2: 43474 | F2: 8/30/20 | G2: 8/29/21 | H2: 8/28/22 | I2: 44994 | J2: 45300 | K2: 8/31/25
A4: Revenues | B4: 118719 | C4: 129025 | D4: 141576 | E4: 152703 | F4: 166761 | G4: 195929 | H4: 226954 | I4: 242290 | J4: 254453 | K4: 275235
A5: Total Revenues | B5: 118719 | C5: 129025 | D5: 141576 | E5: 152703 | F5: 166761 | G5: 195929 | H5: 226954 | I5: 242290 | J5: 254453 | K5: 275235
A6: % Change YoY | B6: 0.022 | C6: 0.087 | D6: 0.097 | E6: 0.079 | F6: 0.092 | G6: 0.175 | H6: 0.158 | I6: 0.068 | J6: 0.05 | K6: 0.082
A7: Cost of Goods Sold | B7: -102901 | C7: -111882 | D7: -123152 | E7: -132886 | F7: -144939 | G7: -170684 | H7: -199382 | I7: -212195 | J7: -222358 | K7: -239886
A8: Gross Profit | B8: 15818 | C8: 17143 | D8: 18424 | E8: 19817 | F8: 21822 | G8: 25245 | H8: 27572 | I8: 30095 | J8: 32095 | K8: 35349
A9: % Change YoY | B9: 0.045 | C9: 0.084 | D9: 0.075 | E9: 0.076 | F9: 0.101 | G9: 0.157 | H9: 0.092 | I9: 0.092 | J9: 0.066 | K9: 0.101
A10: % Gross Margins | B10: 0.133 | C10: 0.133 | D10: 0.13 | E10: 0.13 | F10: 0.131 | G10: 0.129 | H10: 0.121 | I10: 0.124 | J10: 0.126 | K10: 0.128
A11: Selling General & Admin Expenses | B11: -12068 | C11: -12950 | D11: -13876 | E11: -14994 | F11: -16387 | G11: -18453 | H11: -19661 | I11: -21590 | J11: -22810 | K11: -24966
A12: Pre-Opening Costs | B12: -78 | C12: -82 | D12: -68 | E12: -86
A13: Other Operating Expenses
A14: Total Operating Expenses | B14: -12146 | C14: -13032 | D14: -13944 | E14: -15080 | F14: -16387 | G14: -18453 | H14: -19661 | I14: -21590 | J14: -22810 | K14: -24966
A15: Operating Income | B15: 3672 | C15: 4111 | D15: 4480 | E15: 4737 | F15: 5435 | G15: 6792 | H15: 7911 | I15: 8505 | J15: 9285 | K15: 10383
A16: % Change YoY | B16: 0.013 | C16: 0.12 | D16: 0.09 | E16: 0.057 | F16: 0.147 | G16: 0.25 | H16: 0.165 | I16: 0.075 | J16: 0.092 | K16: 0.118
A17: % Operating Margins | B17: 0.031 | C17: 0.032 | D17: 0.032 | E17: 0.031 | F17: 0.033 | G17: 0.035 | H17: 0.035 | I17: 0.035 | J17: 0.036 | K17: 0.038
A18: Interest Expense | B18: -133 | C18: -134 | D18: -159 | E18: -150 | F18: -160 | G18: -171 | H18: -158 | I18: -160 | J18: -169 | K18: -154
A19: Interest And Investment Income | B19: 41 | C19: 50 | D19: 75 | E19: 126 | F19: 89 | G19: 41 | H19: 61 | I19: 470 | J19: 533 | K19: 469
A20: Income (Loss) On Equity Invest.
A21: Currency Exchange Gains (Loss) | B21: 28 | C21: -5 | D21: 23 | E21: 27 | F21: 7 | G21: 56 | H21: 106 | I21: 29 | J21: 26 | K21: 84
A22: Other Non Operating Income (Expenses) | B22: 11 | C22: 17 | D22: 23 | E22: 25 | F22: -4 | G22: 46 | H22: 38 | I22: 34 | J22: 65 | K22: 36
A23: EBT Excl. Unusual Items | B23: 3619 | C23: 4039 | D23: 4442 | E23: 4765 | F23: 5367 | G23: 6764 | H23: 7958 | I23: 8878 | J23: 9740 | K23: 10818
A24: Gain (Loss) On Sale Of Investments
A25: Asset Writedown | G25: -84 | H25: -118 | I25: -391
A26: Legal Settlements
A27: Other Unusual Items
A28: EBT Incl. Unusual Items | B28: 3619 | C28: 4039 | D28: 4442 | E28: 4765 | F28: 5367 | G28: 6680 | H28: 7840 | I28: 8487 | J28: 9740 | K28: 10818
A29: Income Tax Expense | B29: -1243 | C29: -1325 | D29: -1263 | E29: -1061 | F29: -1308 | G29: -1601 | H29: -1925 | I29: -2195 | J29: -2373 | K29: -2719
A30: Earnings From Continuing Operations | B30: 2376 | C30: 2714 | D30: 3179 | E30: 3704 | F30: 4059 | G30: 5079 | H30: 5915 | I30: 6292 | J30: 7367 | K30: 8099
A31: Earnings Of Discontinued Operations
A32: Extraordinary Item & Accounting Change
A33: Net Income to Company | B33: 2376 | C33: 2714 | D33: 3179 | E33: 3704 | F33: 4059 | G33: 5079 | H33: 5915 | I33: 6292 | J33: 7367 | K33: 8099
A34: Minority Interest | B34: -26 | C34: -35 | D34: -45 | E34: -45 | F34: -57 | G34: -72 | H34: -71
A35: Net Income | B35: 2350 | C35: 2679 | D35: 3134 | E35: 3659 | F35: 4002 | G35: 5007 | H35: 5844 | I35: 6292 | J35: 7367 | K35: 8099
A36: Net Income to Common Incl Extra Items | B36: 2350 | C36: 2679 | D36: 3134 | E36: 3659 | F36: 4002 | G36: 5007 | H36: 5844 | I36: 6292 | J36: 7367 | K36: 8099
A37: % Net Income to Common Incl Extra Items Margins | B37: 0.02 | C37: 0.021 | D37: 0.022 | E37: 0.024 | F37: 0.024 | G37: 0.026 | H37: 0.026 | I37: 0.026 | J37: 0.029 | K37: 0.029
A38: Net Income to Common Excl. Extra Items | B38: 2350 | C38: 2679 | D38: 3134 | E38: 3659 | F38: 4002 | G38: 5007 | H38: 5844 | I38: 6292 | J38: 7367 | K38: 8099
A39: % Net Income to Common Excl. Extra Items Margins | B39: 0.02 | C39: 0.021 | D39: 0.022 | E39: 0.024 | F39: 0.024 | G39: 0.026 | H39: 0.026 | I39: 0.026 | J39: 0.029 | K39: 0.029
A40: Supplementary Data:
A41: Diluted EPS Excl Extra Items | B41: 5.33 | C41: 6.08 | D41: 7.09 | E41: 8.26 | F41: 9.02 | G41: 11.27 | H41: 13.14 | I41: 14.16 | J41: 16.56 | K41: 18.21
A42: % Change YoY | B42: -0.007 | C42: 0.141 | D42: 0.166 | E42: 0.165 | F42: 0.092 | G42: 0.249 | H42: 0.166 | I42: 0.078 | J42: 0.169 | K42: 0.1
A43: Weighted Average Diluted Shares Outstanding | B43: 441.26 | C43: 440.94 | D43: 441.83 | E43: 442.92 | F43: 443.9 | G43: 444.35 | H43: 444.76 | I43: 444.45 | J43: 444.76 | K43: 444.8
A44: % Change YoY | B44: -0.003 | C44: -0.001 | D44: 0.002 | E44: 0.002 | F44: 0.002 | G44: 0.001 | H44: 0.001 | I44: -0.001 | J44: 0.001 | K44: 0
A45: Weighted Average Basic Shares Outstanding | B45: 438.59 | C45: 438.44 | D45: 438.52 | E45: 439.76 | F45: 442.3 | G45: 443.09 | H45: 443.65 | I45: 443.85 | J45: 443.91 | K45: 443.99
A46: % Change YoY | B46: -0.002 | C46: 0 | D46: 0 | E46: 0.003 | F46: 0.006 | G46: 0.002 | H46: 0.001 | I46: 0 | J46: 0 | K46: 0
A47: Dividends Per Share | B47: 1.7 | C47: 1.9 | D47: 2.14 | E47: 2.44 | F47: 2.7 | G47: 2.98 | H47: 3.38 | I47: 3.84 | J47: 4.36 | K47: 4.92
A48: % Change YoY | B48: 0.126 | C48: 0.118 | D48: 0.126 | E48: 0.14 | F48: 0.107 | G48: 0.104 | H48: 0.134 | I48: 0.136 | J48: 0.135 | K48: 0.128
A49: Special Dividends Per Share | C49: 7 | G49: 10 | J49: 15
A50: Payout Ratio % | B50: 0.317 | C50: 0.3 | D50: 0.22 | E50: 0.284 | F50: 0.37 | G50: 1.148 | H50: 0.256 | I50: 0.199 | J50: 0.324 | K50: 0.27
A51: Basic EPS | B51: 5.36 | C51: 6.11 | D51: 7.15 | E51: 8.32 | F51: 9.05 | G51: 11.3 | H51: 13.17 | I51: 14.18 | J51: 16.6 | K51: 18.24
A52: EBITDA | B52: 4927 | C52: 5481 | D52: 5917 | E52: 6229 | F52: 7080 | G52: 8573 | H52: 9811 | I52: 10582 | J52: 11522 | K52: 12809
A53: % Change YoY | B53: 0.037 | C53: 0.112 | D53: 0.08 | E53: 0.053 | F53: 0.137 | G53: 0.211 | H53: 0.144 | I53: 0.079 | J53: 0.089 | K53: 0.112
A54: EBITDAR | B54: 5177 | C54: 5739 | F54: 7419 | G54: 9020 | H54: 10265 | I54: 11051 | J54: 11969 | K54: 13262
A55: Effective Tax Rate % | B55: 0.343 | C55: 0.328 | D55: 0.284 | E55: 0.223 | F55: 0.244 | G55: 0.24 | H55: 0.246 | I55: 0.259 | J55: 0.244 | K55: 0.251
A56: Same Store Sales Growth % | B56: 0.04 | C56: 0.04 | D56: 0.07 | E56: 0.06 | F56: 0.09 | G56: 0.13 | H56: 0.11 | I56: 0.05 | J56: 0.06 | K56: 0.08
A57: Price Factors:
A58: Market Cap | B58: 71812.82 | C58: 69402.48 | D58: 102237.19 | E58: 129632.26 | F58: 153813.62 | G58: 199081.39 | H58: 235576.56 | I58: 241183.56 | J58: 395623.31 | K58: 418340.8
A59: Price Close | B59: 163.93 | C59: 158.24 | D59: 233.13 | E59: 294.76 | F59: 348.37 | G59: 450.34 | H59: 531.82 | I59: 544.25 | J59: 892.38 | K59: 943.32
A60: TEV | B60: 71148.82 | C60: 67943.48 | D60: 101989.19 | E60: 128297.26 | F60: 154951.62 | G60: 198675.39 | H60: 233326.56 | I60: 236484.56 | J60: 393421.31 | K60: 411848.8
A61: Active Watchlist: None
A62: © 2019 - 2026, TIKR Inc.
A63: Terms
A64: Privacy

Sheet 8.TIKR_BS
A2: Balance Sheet | TIKR.com | B2: 8/28/16 | C2: 42803 | D2: 43140 | E2: 43474 | F2: 8/30/20 | G2: 8/29/21 | H2: 8/28/22 | I2: 44994 | J2: 45300 | K2: 8/31/25
A4: Cash And Equivalents | B4: 3379 | C4: 4546 | D4: 6055 | E4: 8384 | F4: 12277 | G4: 11258 | H4: 10203 | I4: 13700 | J4: 9906 | K4: 14161
A5: Short Term Investments | B5: 1350 | C5: 1233 | D5: 1204 | E5: 1060 | F5: 1028 | G5: 917 | H5: 846 | I5: 1534 | J5: 1238 | K5: 1123
A6: Trading Asset Securities
A7: Total Cash And Short Term Investments | B7: 4729 | C7: 5779 | D7: 7259 | E7: 9444 | F7: 13305 | G7: 12175 | H7: 11049 | I7: 15234 | J7: 11144 | K7: 15284
A8: Accounts Receivable | B8: 1252 | C8: 1432 | D8: 1669 | E8: 1535 | F8: 1550 | G8: 1803 | H8: 2241 | I8: 2285 | J8: 2721 | K8: 3203
A9: Other Receivables
A10: Total Receivables | B10: 1252 | C10: 1432 | D10: 1669 | E10: 1535 | F10: 1550 | G10: 1803 | H10: 2241 | I10: 2285 | J10: 2721 | K10: 3203
A11: Inventory | B11: 8969 | C11: 9834 | D11: 11040 | E11: 11395 | F11: 12242 | G11: 14215 | H11: 17907 | I11: 16651 | J11: 18647 | K11: 18116
A12: Deferred Tax Assets Current
A13: Other Current Assets | B13: 268 | C13: 272 | D13: 321 | E13: 1111 | F13: 1023 | G13: 1312 | H13: 1499 | I13: 1709 | J13: 1734 | K13: 1777
A14: Total Current Assets | B14: 15218 | C14: 17317 | D14: 20289 | E14: 23485 | F14: 28120 | G14: 29505 | H14: 32696 | I14: 35879 | J14: 34246 | K14: 38380
A15: Gross Property Plant And Equipment | B15: 26167 | C15: 28341 | D15: 30714 | E15: 32626 | F15: 38083 | G15: 41548 | H15: 44326 | I15: 47407 | J15: 51000 | K15: 55053
A16: Accumulated Depreciation | B16: -9124 | C16: -10180 | D16: -11033 | E16: -11736 | F16: -12896 | G16: -14166 | H16: -15286 | I16: -16685 | J16: -17918 | K16: -18931
A17: Net Property Plant And Equipment | B17: 17043 | C17: 18161 | D17: 19681 | E17: 20890 | F17: 25187 | G17: 27382 | H17: 29040 | I17: 30722 | J17: 33082 | K17: 36122
A18: Long-term Investments
A19: Goodwill | E19: 53 | F19: 988 | G19: 996 | H19: 993 | I19: 994 | J19: 26 | K19: 953
A20: Loans Receivable Long-Term
A21: Deferred Tax Assets Long-Term | B21: 202 | C21: 254 | D21: 316 | E21: 398 | F21: 406 | G21: 444 | H21: 445 | I21: 491 | J21: 548 | K21: 592
A22: Other Long-Term Assets | B22: 700 | C22: 615 | D22: 544 | E22: 574 | F22: 855 | G22: 941 | H22: 992 | I22: 908 | J22: 1929 | K22: 1052
A23: Total Assets | B23: 33163 | C23: 36347 | D23: 40830 | E23: 45400 | F23: 55556 | G23: 59268 | H23: 64166 | I23: 68994 | J23: 69831 | K23: 77099
A24: Accounts Payable | B24: 7612 | C24: 9608 | D24: 11237 | E24: 11679 | F24: 14172 | G24: 16278 | H24: 17848 | I24: 17483 | J24: 19421 | K24: 19783
A25: Accrued Expenses | B25: 3498 | C25: 3664 | D25: 4051 | E25: 4356 | F25: 4998 | G25: 5761 | H25: 6292 | I25: 6428 | J25: 7229 | K25: 7882
A26: Short-term Borrowings
A27: Current Portion of Long-Term Debt | B27: 1100 | C27: 86 | D27: 90 | E27: 1699 | F27: 95 | G27: 799 | H27: 73 | I27: 1081 | J27: 103 | K27: 75
A28: Current Portion of Capital Lease Obligations | E28: 51 | F28: 262 | G28: 294 | H28: 484 | I28: 349 | J28: 326 | K28: 286
A29: Current Income Taxes Payable
A30: Unearned Revenue Current | B30: 1362 | C30: 1498 | D30: 1624 | E30: 1711 | F30: 1851 | G30: 2042 | H30: 2174 | I30: 2337 | J30: 2501 | K30: 2854
A31: Deferred Tax Liability Current
A32: Other Current Liabilities | B32: 2003 | C32: 2639 | D32: 2924 | E32: 3741 | F32: 3466 | G32: 4267 | H32: 5127 | I32: 5905 | J32: 5884 | K32: 6228
A33: Total Current Liabilities | B33: 15575 | C33: 17495 | D33: 19926 | E33: 23237 | F33: 24844 | G33: 29441 | H33: 31998 | I33: 33583 | J33: 35464 | K33: 37108
A34: Long-Term Debt | B34: 4061 | C34: 6573 | D34: 6487 | E34: 5124 | F34: 7514 | G34: 6692 | H34: 6484 | I34: 5377 | J34: 5794 | K34: 5713
A35: Capital Leases | E35: 370 | F35: 3215 | G35: 3622 | H35: 3865 | I35: 3729 | J35: 3726 | K35: 3861
A36: Deferred Tax Liability Non Current | B36: 297 | C36: 312 | D36: 317 | E36: 543 | F36: 665 | G36: 754 | H36: 724 | I36: 795 | J36: 769 | K36: 724
A37: Other Non Current Liabilities | B37: 898 | C37: 888 | D37: 997 | E37: 542 | F37: 613 | G37: 681 | H37: 448 | I37: 452 | J37: 456 | K37: 529
A38: Total Liabilities | B38: 20831 | C38: 25268 | D38: 27727 | E38: 29816 | F38: 36851 | G38: 41190 | H38: 43519 | I38: 43936 | J38: 46209 | K38: 47935
A39: Common Stock | B39: 2 | C39: 4 | D39: 4 | E39: 4 | F39: 4 | G39: 4 | H39: 2 | I39: 2 | J39: 2 | K39: 2
A40: Additional Paid In Capital | B40: 5490 | C40: 5800 | D40: 6107 | E40: 6417 | F40: 6698 | G40: 7031 | H40: 6884 | I40: 7340 | J40: 7829 | K40: 8282
A41: Retained Earnings | B41: 7686 | C41: 5988 | D41: 7887 | E41: 10258 | F41: 12879 | G41: 11666 | H41: 15585 | I41: 19521 | J41: 17619 | K41: 22650
A42: Comprehensive Income and Other | B42: -1099 | C42: -1014 | D42: -1199 | E42: -1436 | F42: -1297 | G42: -1137 | H42: -1829 | I42: -1805 | J42: -1828 | K42: -1770
A43: Total Common Equity | B43: 12079 | C43: 10778 | D43: 12799 | E43: 15243 | F43: 18284 | G43: 17564 | H43: 20642 | I43: 25058 | J43: 23622 | K43: 29164
A44: Minority Interest | B44: 253 | C44: 301 | D44: 304 | E44: 341 | F44: 421 | G44: 514 | H44: 5
A45: Total Equity | B45: 12332 | C45: 11079 | D45: 13103 | E45: 15584 | F45: 18705 | G45: 18078 | H45: 20647 | I45: 25058 | J45: 23622 | K45: 29164
A46: Total Liabilities And Equity | B46: 33163 | C46: 36347 | D46: 40830 | E46: 45400 | F46: 55556 | G46: 59268 | H46: 64166 | I46: 68994 | J46: 69831 | K46: 77099
A47: Supplementary Data:
A48: Total Shares Out. on Filing Date | B48: 437.13 | C48: 436.99 | D48: 438.21 | F48: 441.23 | G48: 441.82 | H48: 442.6 | I48: 442.74 | J48: 443.07 | K48: 443.18
A49: Book Value / Share | B49: 27.61 | C49: 24.65 | D49: 29.21 | E49: 34.67 | F49: 41.44 | G49: 39.75 | H49: 46.63 | I49: 56.59 | J49: 53.31 | K49: 65.8
A50: Tangible Book Value | B50: 12079 | C50: 10778 | D50: 12799 | E50: 15190 | F50: 17296 | G50: 16568 | H50: 19649 | I50: 24064 | J50: 23596 | K50: 28211
A51: Tangible Book Value / Share | B51: 27.61 | C51: 24.65 | D51: 29.21 | E51: 34.55 | F51: 39.2 | G51: 37.5 | H51: 44.39 | I51: 54.35 | J51: 53.25 | K51: 63.65
A52: Total Debt | B52: 5161 | C52: 6659 | D52: 6577 | E52: 7244 | F52: 11086 | G52: 11407 | H52: 10906 | I52: 10536 | J52: 9949 | K52: 9935
A53: Net Debt | B53: 432 | C53: 880 | D53: -682 | E53: -2200 | F53: -2219 | G53: -768 | H53: -143 | I53: -4698 | J53: -1195 | K53: -5349
A54: Total Minority Interest | B54: 253 | C54: 301 | D54: 304 | E54: 341 | F54: 421 | G54: 514 | H54: 5
A55: Equity Method Investments
A56: Land | B56: 5395 | C56: 5690 | D56: 6193 | E56: 6417 | F56: 6696 | G56: 7507 | H56: 7955 | I56: 8590 | J56: 9447 | K56: 10323
A57: Buildings | B57: 13994 | C57: 15127 | D57: 16107 | E57: 17136 | F57: 17982 | G57: 19139 | H57: 20120 | I57: 22001 | J57: 23727 | K57: 25508
A58: Construction In Progress | B58: 701 | C58: 843 | D58: 1140 | E58: 1272 | F58: 1276 | G58: 1507 | H58: 1582 | I58: 1266 | J58: 1389 | K58: 1882
A59: Full Time Employees | B59: 126000 | C59: 133000 | D59: 143000 | E59: 149000 | F59: 156000 | G59: 288000 | H59: 304000 | I59: 316000 | J59: 333000 | K59: 341000
A60: Active Watchlist: None
A61: © 2019 - 2026, TIKR Inc.
A62: Terms
A63: Privacy

Sheet 9.TIKR_CF
A2: Cash Flow | TIKR.com | B2: 8/31/16 | C2: 8/31/17 | D2: 8/31/18 | E2: 8/31/19 | F2: 8/31/20 | G2: 8/31/21 | H2: 8/31/22 | I2: 8/31/23 | J2: 8/31/24 | K2: 8/31/25
A4: Net Income | B4: 2376 | C4: 2714 | D4: 3179 | E4: 3704 | F4: 4059 | G4: 5079 | H4: 5915 | I4: 6292 | J4: 7367 | K4: 8099
A5: Total Depreciation & Amortization | B5: 1255 | C5: 1370 | D5: 1437 | E5: 1492 | F5: 1645 | G5: 1781 | H5: 1900 | I5: 2077 | J5: 2237 | K5: 2426
A6: Total Depreciation & Amortization & Depletion | B6: 1255 | C6: 1370 | D6: 1437 | E6: 1492 | F6: 1645 | G6: 1781 | H6: 1900 | I6: 2077 | J6: 2237 | K6: 2426
A7: (Income) Loss On Equity Investments
A8: (Gain) Loss From Sale Of Asset
A9: Stock-Based Compensation | B9: 459 | C9: 514 | D9: 544 | E9: 595 | F9: 619 | G9: 665 | H9: 724 | I9: 774 | J9: 818 | K9: 860
A10: Deferred Taxes | B10: 269 | C10: -29 | D10: -49 | E10: 147 | F10: 104 | G10: 59 | H10: -37
A11: Asset Impairment Charge | G11: 144 | H11: 39 | I11: 495 | J11: -9 | K11: -117
A12: Excess Tax Benefit From Stock Based Compensation | B12: -74 | C12: -38
A13: Change In Accounts Receivable
A14: Change In Inventories | B14: -25 | C14: -894 | D14: -1313 | E14: -536 | F14: -791 | G14: -1892 | H14: -4003 | I14: 1228 | J14: -2068 | K14: 559
A15: Change In Accounts Payable | B15: -1532 | C15: 2258 | D15: 1561 | E15: 322 | F15: 2261 | G15: 1838 | H15: 1891 | I15: -382 | J15: 1938 | K15: 404
A16: Change In Payable | B16: -1532 | C16: 2258 | D16: 1561 | E16: 322 | F16: 2261 | G16: 1838 | H16: 1891 | I16: -382 | J16: 1938 | K16: 404
A17: Change in Other Current Assets
A18: Change in Other Current Liabilities
A19: Change in Other Working Capital | B19: 547 | C19: 807 | D19: 421 | E19: 623 | F19: 728 | G19: 1057 | H19: 549 | I19: 172 | J19: 741 | K19: 801
A20: Other Operating Activities | B20: 1549 | C20: -2234 | D20: -1567 | E20: -313 | F20: -2025 | G20: -1611 | H20: -1477 | I20: 794 | J20: -1623 | K20: -101
A21: Cash Flow From Continuing Operating Activities | B21: 3292 | C21: 6726 | D21: 5774 | E21: 6356 | F21: 8861 | G21: 8958 | H21: 7392 | I21: 11068 | J21: 11339 | K21: 13335
A22: Cash from Operations | B22: 3292 | C22: 6726 | D22: 5774 | E22: 6356 | F22: 8861 | G22: 8958 | H22: 7392 | I22: 11068 | J22: 11339 | K22: 13335
A23: Memo: Change in Net Working Capital | B23: -1010 | C23: 2171 | D23: 669 | E23: 409 | F23: 2198 | G23: 1003 | H23: -1563 | I23: 1018 | J23: 611 | K23: 1764
A24: Capital Expenditure | B24: -2649 | C24: -2502 | D24: -2969 | E24: -2998 | F24: -2810 | G24: -3588 | H24: -3891 | I24: -4323 | J24: -4710 | K24: -5498
A25: Sale of Property, Plant, and Equipment
A26: Net Sale (Purchase) of PP&E | B26: -2649 | C26: -2502 | D26: -2969 | E26: -2998 | F26: -2810 | G26: -3588 | H26: -3891 | I26: -4323 | J26: -4710 | K26: -5498
A27: Cash Acquisitions | F27: -1163
A28: Divestitures
A29: Net Sale (Purchase) of Business | F29: -1163
A30: Investment in Marketable and Equity Securities | B30: 277 | C30: 106 | D30: 18 | E30: 137 | F30: 52 | G30: 115 | H30: 24 | I30: -685 | J30: 320 | K30: 113
A31: Other Investing Activities | B31: 27 | C31: 30 | D31: 4 | E31: -4 | F31: 30 | G31: -62 | H31: -48 | I31: 36 | J31: -19 | K31: 74
A32: Cash Flow From Continuing Investing Activities | B32: -2345 | C32: -2366 | D32: -2947 | E32: -2865 | F32: -3891 | G32: -3535 | H32: -3915 | I32: -4972 | J32: -4409 | K32: -5311
A33: Cash from Investing | B33: -2345 | C33: -2366 | D33: -2947 | E33: -2865 | F33: -3891 | G33: -3535 | H33: -3915 | I33: -4972 | J33: -4409 | K33: -5311
A34: Short-Term Debt Issuance | B34: 187 | D34: 80 | G34: 41 | H34: 53 | I34: 917 | J34: 928 | K34: 816
A35: Long-Term Debt Issuance | B35: 185 | C35: 3782 | D35: 80 | E35: 508 | F35: 3992 | G35: 188 | J35: 498
A36: Total Debt Issued | B36: 372 | C36: 3782 | D36: 80 | E36: 508 | F36: 3992 | G36: 41 | H36: 53 | I36: 917 | J36: 1426 | K36: 816
A37: Short-Term Debt Payments | B37: -106 | C37: -236 | H37: -6 | I37: -935 | J37: -920 | K37: -862
A38: Long-Term Debt Payments | B38: -1288 | C38: -2436 | D38: -86 | E38: -89 | F38: -3200 | G38: -161 | H38: -980 | I38: -366 | J38: -1214 | K38: -250
A39: Total Debt Repaid | B39: -1394 | C39: -2436 | D39: -86 | E39: -89 | F39: -3200 | G39: -161 | H39: -986 | I39: -1301 | J39: -2134 | K39: -1112
A40: Issuance of Common Stock
A41: Repurchase of Common Stock | B41: -486 | C41: -469 | D41: -328 | E41: -247 | F41: -196 | G41: -496 | H41: -439 | I41: -676 | J41: -700 | K41: -903
A42: Common Dividends Paid | B42: -746 | C42: -3904 | D42: -689 | E42: -1038 | F42: -1479 | G42: -5748 | H42: -1498 | I42: -1251
A43: Total Dividends Paid | B43: -746 | C43: -3904 | D43: -689 | E43: -1038 | F43: -1479 | G43: -5748 | H43: -1498 | I43: -1251 | J43: -9041 | K43: -2183
A44: Proceeds From Stock Option Exercised
A45: Other Financing Activities | B45: -165 | C45: -191 | D45: -258 | E45: -281 | F45: -264 | G45: -124 | H45: -1413 | I45: -303 | J45: -315 | K45: -393
A46: Other CFF Items
A47: Cash from Financing | B47: -2419 | C47: -3218 | D47: -1281 | E47: -1147 | F47: -1147 | G47: -6488 | H47: -4283 | I47: -2614 | J47: -10764 | K47: -3775
A48: Changes In Cash | B48: -1472 | C48: 1142 | D48: 1546 | E48: 2344 | F48: 3823 | G48: -1065 | H48: -806 | I48: 3482 | J48: -3834 | K48: 4249
A49: Foreign Exchange Rate Adjustments | B49: 50 | C49: 25 | D49: -37 | E49: -15 | F49: 70 | G49: 46 | H49: -249 | I49: 15 | J49: 40 | K49: 6
A50: Cash and Cash Equivalents, Beginning of Period | B50: 4801 | C50: 3379 | D50: 4546 | E50: 6055 | F50: 8384 | G50: 12277 | H50: 11258 | I50: 10203 | J50: 13700 | K50: 9906
A51: Cash and Cash Equivalents, End of Period | B51: 3379 | C51: 4546 | D51: 6055 | E51: 8384 | F51: 12277 | G51: 11258 | H51: 10203 | I51: 13700 | J51: 9906 | K51: 14161
A52: Supplementary Data:
A53: Free Cash Flow | B53: 643 | C53: 4224 | D53: 2805 | E53: 3358 | F53: 6051 | G53: 5370 | H53: 3501 | I53: 6745 | J53: 6629 | K53: 7837
A54: % Change YoY | B54: -0.66 | C54: 5.569 | D54: -0.336 | E54: 0.197 | F54: 0.802 | G54: -0.113 | H54: -0.348 | I54: 0.927 | J54: -0.017 | K54: 0.182
A55: % Free Cash Flow Margins | B55: 0.005 | C55: 0.033 | D55: 0.02 | E55: 0.022 | F55: 0.036 | G55: 0.027 | H55: 0.015 | I55: 0.028 | J55: 0.026 | K55: 0.028
A56: Net Change in Cash (As Reported) | B56: -1422 | C56: 1167 | D56: 1509 | E56: 2329 | F56: 3893 | G56: -1019 | H56: -1055 | I56: 3497 | J56: -3794 | K56: 4255
A57: Cash Flow from Operations before NWC | B57: 4302 | C57: 4555 | D57: 5105 | E57: 5947 | F57: 6663 | G57: 7955 | H57: 8955 | I57: 10050 | J57: 10728 | K57: 11571
A58: Cash Taxes Paid | B58: 953 | C58: 1185 | D58: 1204 | E58: 1187 | F58: 1052 | G58: 1527 | H58: 1940 | I58: 2234 | J58: 2319 | K58: 2917
A59: Cash Interest Paid | B59: 123 | C59: 131 | D59: 143 | E59: 141 | F59: 124 | G59: 149 | H59: 145 | I59: 125 | J59: 129 | K59: 106
A60: Active Watchlist: None
A61: © 2019 - 2026, TIKR Inc.
A62: Terms
A63: Privacy

Sheet 10.Glosario
B2: P&L - Beneficio "contable" | C2: Fórmula #1 | D2: Fórmula #2 | E2: Fórmula #3
B3: EBITDA | C3: Net Income + Interests (net) + Taxes + Depreciation + Amortization | D3: Ingresos - Gastos de Explotación | E3: EBIT + D&A
B4: EBIT | C4: Net Income + Interests (net) + Taxes | D4: Ingresos - Gastos de Explotación - D&A | E4: EBITDA - D&A
B5: EBT | C5: Net Income + Interests (net) | D5: Ingresos - Gastos de Explotación - D&A - Interests (net) - Other financial items | E5: EBIT - Interests (net) - Other financial items
B6: Net Income | C6: Ingresos - Gastos de Explotación - D&A - Interests (net) - Other financial items - taxes | D6: EBT - Taxes
B7: EPS | C7: Net Income / Nº total de acciones diluídas
B9: Valoración | C9: Fórmula #1 | D9: Fórmula #2 | E9: Fórmula #3
B10: Net Debt (Deuda Financiera Neta) | C10: Short-Term Debt + Short-Term Borrowings + Long-Term Debt + Long-Term Borrowings - Cash
B11: Market Cap. | C11: Nº de acciones totales diluídas x Precio por acción
B12: Enterprise Value (EV) | C12: Market Cap + Net Debt | D12: Market Cap - Caja Neta
B13: EV / EBITDA | C13: Enterprise Value / EBITDA
B14: EV / EBIT | C14: Enterprise Value / EBIT
B15: EV / FCF | C15: Enterprise Value / FCF
B16: PER | C16: Market Cap. / Beneficio Neto | D16: Precio por acción / EPS
B18: Márgenes % | C18: Fórmula #1 | D18: Fórmula #2 | E18: Fórmula #3
B19: EBITDA | C19: EBITDA / Ventas x 100
B20: EBIT | C20: EBIT / Ventas x 100
B21: Neto | C21: Net Income / Ventas x 100
B22: FCF | C22: FCF / Ventas x 100
B24: Rentabilidad % | C24: Fórmula #1 | D24: Fórmula #2 | E24: Fórmula #3
B25: ROIC | C25: EBIT * (1 - T) / Capital Invertido | D25: Capital Invertido = Equity + Deuda financiera total + Operating Leases Total – Marketable Securities
B26: ROE | C26: Net Income / Total Shareholders' Equity
B27: ROA | C27: Net Income / Total Assets
B29: FCF | C29: Fórmula #1 | D29: Fórmula #2 | E29: Fórmula #3
B30: Working Capital (WC) | C30: Inventarios + Cuentas a Cobrar de Clientes - Cuentas a pagar a proveedores | D30: Inventories + Accounts Receivable + Accounts Payable | E30: En empresas ligeras de activos podemos restar también la partida "Unearned revenue", tanto "Current" como "Non-current"
B31: Variación de WC (CWC) | C31: WC año más reciente - WC año anterior. (P.ej.: WC 2021 - WC 2020) | D31: Si la CWC es positiva DISMINUYE el FCF ya que la empresa tiene que financiar ese aumento de inventarios y/o de cuentas a cobrar | E31: Si la CWC es negativa AUMENTA el FCF, ya que se 'libera'' capital, es como si la empresa vendiese inventarios y/o cobrase más facturas a clientes
B32: CapEx de Mantenimiento | C32: Si la directiva no proporciona un capex de mantenimiento exacto, usaremos la D&A como "atajo" para el capex de mantenimiento en los casos que el capex total sea notablemente superior a la D&A | D32: Otra opción es usar el % CapEx / Sales del sector, pero esto lleva trabajo, no hay una página que recoja este ratio para todas y cada una de los cientos de industrias que componen todos los sectores
B33: FCF | C33: EBITDA - Interests (net) - Taxes - CapEx Mantenimiento - Variación de WC

Sheet TIKR_Cálculos
A1: Cálculos CF | B1: ='1.IS'!B2 -> 2016 | C1: ='1.IS'!C2 -> 2017 | D1: ='1.IS'!D2 -> 2018 | E1: ='1.IS'!E2 -> 2019 | F1: ='1.IS'!F2 -> 2020 | G1: ='1.IS'!G2 -> 2021 | H1: ='1.IS'!H2 -> 2022 | I1: ='1.IS'!I2 -> 2023 | ... K1: ='1.IS'!K2 -> 2025
A2: Capital Expenditure* | B2: =IFERROR(VLOOKUP($A2,'9.TIKR_CF'!$A:$K,COLUMN(B2),FALSE),"0") -> -2649 | C2: =IFERROR(VLOOKUP($A2,'9.TIKR_CF'!$A:$K,COLUMN(C2),FALSE),"0") -> -2502 | D2: =IFERROR(VLOOKUP($A2,'9.TIKR_CF'!$A:$K,COLUMN(D2),FALSE),"0") -> -2969 | E2: =IFERROR(VLOOKUP($A2,'9.TIKR_CF'!$A:$K,COLUMN(E2),FALSE),"0") -> -2998 | F2: =IFERROR(VLOOKUP($A2,'9.TIKR_CF'!$A:$K,COLUMN(F2),FALSE),"0") -> -2810 | G2: =IFERROR(VLOOKUP($A2,'9.TIKR_CF'!$A:$K,COLUMN(G2),FALSE),"0") -> -3588 | H2: =IFERROR(VLOOKUP($A2,'9.TIKR_CF'!$A:$K,COLUMN(H2),FALSE),"0") -> -3891 | I2: =IFERROR(VLOOKUP($A2,'9.TIKR_CF'!$A:$K,COLUMN(I2),FALSE),"0") -> -4323 | ... K2: =IFERROR(VLOOKUP($A2,'9.TIKR_CF'!$A:$K,COLUMN(K2),FALSE),"0") -> -5498
A3: Sale (Purchase) of Intangible assets* | B3: =IFERROR(VLOOKUP($A3,'9.TIKR_CF'!$A:$K,COLUMN(B3),FALSE),"0") -> 0 | C3: =IFERROR(VLOOKUP($A3,'9.TIKR_CF'!$A:$K,COLUMN(C3),FALSE),"0") -> 0 | D3: =IFERROR(VLOOKUP($A3,'9.TIKR_CF'!$A:$K,COLUMN(D3),FALSE),"0") -> 0 | E3: =IFERROR(VLOOKUP($A3,'9.TIKR_CF'!$A:$K,COLUMN(E3),FALSE),"0") -> 0 | F3: =IFERROR(VLOOKUP($A3,'9.TIKR_CF'!$A:$K,COLUMN(F3),FALSE),"0") -> 0 | G3: =IFERROR(VLOOKUP($A3,'9.TIKR_CF'!$A:$K,COLUMN(G3),FALSE),"0") -> 0 | H3: =IFERROR(VLOOKUP($A3,'9.TIKR_CF'!$A:$K,COLUMN(H3),FALSE),"0") -> 0 | I3: =IFERROR(VLOOKUP($A3,'9.TIKR_CF'!$A:$K,COLUMN(I3),FALSE),"0") -> 0 | ... K3: =IFERROR(VLOOKUP($A3,'9.TIKR_CF'!$A:$K,COLUMN(K3),FALSE),"0") -> 0
A4: Sale of Property, Plant, and Equipment* | B4: =IFERROR(VLOOKUP($A4,'9.TIKR_CF'!$A:$K,COLUMN(B4),FALSE),"0") -> 0 | C4: =IFERROR(VLOOKUP($A4,'9.TIKR_CF'!$A:$K,COLUMN(C4),FALSE),"0") -> 0 | D4: =IFERROR(VLOOKUP($A4,'9.TIKR_CF'!$A:$K,COLUMN(D4),FALSE),"0") -> 0 | E4: =IFERROR(VLOOKUP($A4,'9.TIKR_CF'!$A:$K,COLUMN(E4),FALSE),"0") -> 0 | F4: =IFERROR(VLOOKUP($A4,'9.TIKR_CF'!$A:$K,COLUMN(F4),FALSE),"0") -> 0 | G4: =IFERROR(VLOOKUP($A4,'9.TIKR_CF'!$A:$K,COLUMN(G4),FALSE),"0") -> 0 | H4: =IFERROR(VLOOKUP($A4,'9.TIKR_CF'!$A:$K,COLUMN(H4),FALSE),"0") -> 0 | I4: =IFERROR(VLOOKUP($A4,'9.TIKR_CF'!$A:$K,COLUMN(I4),FALSE),"0") -> 0 | ... K4: =IFERROR(VLOOKUP($A4,'9.TIKR_CF'!$A:$K,COLUMN(K4),FALSE),"0") -> 0
A5: CapEx Neto | B5: =SUM(B2:B4) -> -2649 | C5: =SUM(C2:C4) -> -2502 | D5: =SUM(D2:D4) -> -2969 | E5: =SUM(E2:E4) -> -2998 | F5: =SUM(F2:F4) -> -2810 | G5: =SUM(G2:G4) -> -3588 | H5: =SUM(H2:H4) -> -3891 | I5: =SUM(I2:I4) -> -4323 | ... K5: =SUM(K2:K4) -> -5498
A6: Depreciation & Amortization* | B6: =IFERROR(VLOOKUP($A6,'9.TIKR_CF'!$A:$K,COLUMN(B6),FALSE),"0") -> 0 | C6: =IFERROR(VLOOKUP($A6,'9.TIKR_CF'!$A:$K,COLUMN(C6),FALSE),"0") -> 0 | D6: =IFERROR(VLOOKUP($A6,'9.TIKR_CF'!$A:$K,COLUMN(D6),FALSE),"0") -> 0 | E6: =IFERROR(VLOOKUP($A6,'9.TIKR_CF'!$A:$K,COLUMN(E6),FALSE),"0") -> 0 | F6: =IFERROR(VLOOKUP($A6,'9.TIKR_CF'!$A:$K,COLUMN(F6),FALSE),"0") -> 0 | G6: =IFERROR(VLOOKUP($A6,'9.TIKR_CF'!$A:$K,COLUMN(G6),FALSE),"0") -> 0 | H6: =IFERROR(VLOOKUP($A6,'9.TIKR_CF'!$A:$K,COLUMN(H6),FALSE),"0") -> 0 | I6: =IFERROR(VLOOKUP($A6,'9.TIKR_CF'!$A:$K,COLUMN(I6),FALSE),"0") -> 0 | ... K6: =IFERROR(VLOOKUP($A6,'9.TIKR_CF'!$A:$K,COLUMN(K6),FALSE),"0") -> 0
A7: CapEx Mantenimiento | B7: =IF(ABS(B5)<B6,B5,-B6) -> -2649 | C7: =IF(ABS(C5)<C6,C5,-C6) -> -2502 | D7: =IF(ABS(D5)<D6,D5,-D6) -> -2969 | E7: =IF(ABS(E5)<E6,E5,-E6) -> -2998 | F7: =IF(ABS(F5)<F6,F5,-F6) -> -2810 | G7: =IF(ABS(G5)<G6,G5,-G6) -> -3588 | H7: =IF(ABS(H5)<H6,H5,-H6) -> -3891 | I7: =IF(ABS(I5)<I6,I5,-I6) -> -4323 | ... K7: =IF(ABS(K5)<K6,K5,-K6) -> -5498
A9: Reinversión | B9: ='1.IS'!B2 -> 2016 | C9: ='1.IS'!C2 -> 2017 | D9: ='1.IS'!D2 -> 2018 | E9: ='1.IS'!E2 -> 2019 | F9: ='1.IS'!F2 -> 2020 | G9: ='1.IS'!G2 -> 2021 | H9: ='1.IS'!H2 -> 2022 | I9: ='1.IS'!I2 -> 2023 | ... K9: ='1.IS'!K2 -> 2025
A10: CapEx Expansión | B10: =B5-B7 -> 0 | C10: =C5-C7 -> 0 | D10: =D5-D7 -> 0 | E10: =E5-E7 -> 0 | F10: =F5-F7 -> 0 | G10: =G5-G7 -> 0 | H10: =H5-H7 -> 0 | I10: =I5-I7 -> 0 | ... K10: =K5-K7 -> 0
A11: Adquisiciones | B11: =IFERROR(VLOOKUP("Cash Acquisitions*",'9.TIKR_CF'!$A:$K,COLUMN(B11),FALSE),"0") -> 0 | C11: =IFERROR(VLOOKUP("Cash Acquisitions*",'9.TIKR_CF'!$A:$K,COLUMN(C11),FALSE),"0") -> 0 | D11: =IFERROR(VLOOKUP("Cash Acquisitions*",'9.TIKR_CF'!$A:$K,COLUMN(D11),FALSE),"0") -> 0 | E11: =IFERROR(VLOOKUP("Cash Acquisitions*",'9.TIKR_CF'!$A:$K,COLUMN(E11),FALSE),"0") -> 0 | F11: =IFERROR(VLOOKUP("Cash Acquisitions*",'9.TIKR_CF'!$A:$K,COLUMN(F11),FALSE),"0") -> -1163 | G11: =IFERROR(VLOOKUP("Cash Acquisitions*",'9.TIKR_CF'!$A:$K,COLUMN(G11),FALSE),"0") -> 0 | H11: =IFERROR(VLOOKUP("Cash Acquisitions*",'9.TIKR_CF'!$A:$K,COLUMN(H11),FALSE),"0") -> 0 | I11: =IFERROR(VLOOKUP("Cash Acquisitions*",'9.TIKR_CF'!$A:$K,COLUMN(I11),FALSE),"0") -> 0 | ... K11: =IFERROR(VLOOKUP("Cash Acquisitions*",'9.TIKR_CF'!$A:$K,COLUMN(K11),FALSE),"0") -> 0
A12: Inversión en crecimiento | B12: =ABS(SUM(B10:B11)) -> 0 | C12: =ABS(SUM(C10:C11)) -> 0 | D12: =ABS(SUM(D10:D11)) -> 0 | E12: =ABS(SUM(E10:E11)) -> 0 | F12: =ABS(SUM(F10:F11)) -> 1163 | G12: =ABS(SUM(G10:G11)) -> 0 | H12: =ABS(SUM(H10:H11)) -> 0 | I12: =ABS(SUM(I10:I11)) -> 0 | ... K12: =ABS(SUM(K10:K11)) -> 0
A14: Valoración | B14: ='1.IS'!L2 -> 2026e | C14: ='1.IS'!M2 -> 2027e | D14: ='1.IS'!N2 -> 2028e | E14: ='1.IS'!O2 -> 2029e | F14: ='1.IS'!P2 -> 2030e
A15: Precio actual | B15: ='4.Valoración'!$D$12 -> 987.21 | C15: ='4.Valoración'!$D$12 -> 987.21 | D15: ='4.Valoración'!$D$12 -> 987.21 | E15: ='4.Valoración'!$D$12 -> 987.21 | F15: ='4.Valoración'!$D$12 -> 987.21
A17: Deuda Neta | B17: ='1.IS'!K2 -> 2025
A18: % Corto plazo | B18: =IFERROR(SUM('3.ROIC'!$B$6:$K$6)/SUM('3.ROIC'!$B$6:$K$7),0) -> 0.079990772
A19: % Largo plazo | B19: =IF(B18=0,0,1-B18) -> 0.92000923
A20: Caja histórica acumulada | B20: =SUM('3.ROIC'!B4:K5) -> 105402
A21: Marketable securities acumulados | B21: =SUM('3.ROIC'!B5:K5) -> 11533
A22: Deuda histórica acumulada | B22: =SUM('3.ROIC'!B6:K7) -> 65020
A23: Deuda neta histórica acumulada | B23: =B22-B20 -> -40382
A24: Interest income acumulado | B24: =SUM('1.IS'!B13:K13) -> 1955
A25: Interest expense acumulado | B25: =SUM('1.IS'!B12:K12) -> -1548
A26: % Interest income promedio | B26: =IFERROR(B24/B21,0) -> 0.16951357
A27: % Interest expense promedio | B27: =ABS(SUM('1.IS'!B12:K12))/B22 -> 0.023808059
A29: Estimación Caja y Deuda a futuro | B29: ='1.IS'!K2 -> 2025 | C29: ='1.IS'!L2 -> 2026e | D29: ='1.IS'!M2 -> 2027e | E29: ='1.IS'!N2 -> 2028e | F29: ='1.IS'!O2 -> 2029e | G29: ='1.IS'!P2 -> 2030e
A30: Deuda Neta | B30: ='4.Valoración'!K4 -> -9496 | C30: ='4.Valoración'!L4 -> -5287.7257 | D30: ='4.Valoración'!M4 -> -5809.1216 | E30: ='4.Valoración'!N4 -> -6381.9296 | F30: ='4.Valoración'!O4 -> -7011.2194 | G30: ='4.Valoración'!P4 -> -7702.5602
A31: Cash + Marketable securities | B31: =B32+B33 -> 15284 | C31: =IF(C30<=0,B31/ABS(B30)*ABS(C30),MIN(B45:K45)*'1.IS'!L3) -> 8510.6993 | D31: =C31/ABS(C30)*ABS(D30) -> 9349.8962 | E31: =D31/ABS(D30)*ABS(E30) -> 10271.842 | F31: =E31/ABS(E30)*ABS(F30) -> 11284.696 | G31: =F31/ABS(F30)*ABS(G30) -> 12397.423
A32: Cash | B32: ='3.ROIC'!K4 -> 14161 | C32: =B32/B31*C31 -> 7885.3711 | D32: =C32/'1.IS'!L3*'1.IS'!M3 -> 8662.9076 | E32: =D32/'1.IS'!M3*'1.IS'!N3 -> 9517.113 | F32: =E32/'1.IS'!N3*'1.IS'!O3 -> 10455.547 | G32: =F32/'1.IS'!O3*'1.IS'!P3 -> 11486.516
A33: Marketable securities | B33: ='3.ROIC'!K5 -> 1123 | C33: =B33/B31*C31 -> 625.32814 | D33: =C33/'1.IS'!L3*'1.IS'!M3 -> 686.98858 | E33: =D33/'1.IS'!M3*'1.IS'!N3 -> 754.72904 | F33: =E33/'1.IS'!N3*'1.IS'!O3 -> 829.14905 | G33: =F33/'1.IS'!O3*'1.IS'!P3 -> 910.90723
A34: Deuda Total | B34: =B30+B31 -> 5788 | C34: =IF(C30<=0,B34/ABS(B30)*ABS(C30),C30+C31) -> 3222.9735 | D34: =C34/ABS(C30)*ABS(D30) -> 3540.7746 | E34: =D34/ABS(D30)*ABS(E30) -> 3889.9125 | F34: =E34/ABS(E30)*ABS(F30) -> 4273.477 | G34: =F34/ABS(F30)*ABS(G30) -> 4694.8629
A35: Deuda CP | B35: ='3.ROIC'!K6 -> 75 | C35: =B35/B34*C34 -> 41.762788 | D35: =C35/C34*D34 -> 45.880804 | E35: =D35/D34*E34 -> 50.404878 | F35: =E35/E34*F34 -> 55.375048 | G35: =F35/F34*G34 -> 60.8353
A36: Deuda LP | B36: ='3.ROIC'!K7 -> 5713 | C36: =B36/B34*C34 -> 3181.2107 | D36: =C36/C34*D34 -> 3494.8938 | E36: =D36/D34*E34 -> 3839.5076 | F36: =E36/E34*F34 -> 4218.102 | G36: =F36/F34*G34 -> 4634.0276
A39: Asignación de capital (2. FCF) | B39: ='1.IS'!B2 -> 2016 | C39: ='1.IS'!C2 -> 2017 | D39: ='1.IS'!D2 -> 2018 | E39: ='1.IS'!E2 -> 2019 | F39: ='1.IS'!F2 -> 2020 | G39: ='1.IS'!G2 -> 2021 | H39: ='1.IS'!H2 -> 2022 | I39: ='1.IS'!I2 -> 2023 | ... K39: ='1.IS'!K2 -> 2025 | L39: Acumulado
A40: CapEx Expansión (Crecimiento orgánico) | B40: =ABS(B10) -> 0 | C40: =ABS(C10) -> 0 | D40: =ABS(D10) -> 0 | E40: =ABS(E10) -> 0 | F40: =ABS(F10) -> 0 | G40: =ABS(G10) -> 0 | H40: =ABS(H10) -> 0 | I40: =ABS(I10) -> 0 | ... K40: =ABS(K10) -> 0 | L40: =SUM(B40:K40) -> 0
A41: Dividendos | B41: =IFERROR(ABS(VLOOKUP("Common & Preferred Stock Dividends Paid*",'9.TIKR_CF'!$A:$K,COLUMN(B14),FALSE)),"0") -> 0 | C41: =IFERROR(ABS(VLOOKUP("Common & Preferred Stock Dividends Paid*",'9.TIKR_CF'!$A:$K,COLUMN(C14),FALSE)),"0") -> 0 | D41: =IFERROR(ABS(VLOOKUP("Common & Preferred Stock Dividends Paid*",'9.TIKR_CF'!$A:$K,COLUMN(D14),FALSE)),"0") -> 0 | E41: =IFERROR(ABS(VLOOKUP("Common & Preferred Stock Dividends Paid*",'9.TIKR_CF'!$A:$K,COLUMN(E14),FALSE)),"0") -> 0 | F41: =IFERROR(ABS(VLOOKUP("Common & Preferred Stock Dividends Paid*",'9.TIKR_CF'!$A:$K,COLUMN(F14),FALSE)),"0") -> 0 | G41: =IFERROR(ABS(VLOOKUP("Common & Preferred Stock Dividends Paid*",'9.TIKR_CF'!$A:$K,COLUMN(G14),FALSE)),"0") -> 0 | H41: =IFERROR(ABS(VLOOKUP("Common & Preferred Stock Dividends Paid*",'9.TIKR_CF'!$A:$K,COLUMN(H14),FALSE)),"0") -> 0 | I41: =IFERROR(ABS(VLOOKUP("Common & Preferred Stock Dividends Paid*",'9.TIKR_CF'!$A:$K,COLUMN(I14),FALSE)),"0") -> 0 | ... K41: =IFERROR(ABS(VLOOKUP("Common & Preferred Stock Dividends Paid*",'9.TIKR_CF'!$A:$K,COLUMN(K14),FALSE)),"0") -> 0 | L41: =SUM(B41:K41) -> 0
A42: Recompras | B42: =IFERROR(ABS(VLOOKUP("Repurchase of Common Stock*",'9.TIKR_CF'!$A:$K,COLUMN(B15),FALSE)),"0") -> 486 | C42: =IFERROR(ABS(VLOOKUP("Repurchase of Common Stock*",'9.TIKR_CF'!$A:$K,COLUMN(C15),FALSE)),"0") -> 469 | D42: =IFERROR(ABS(VLOOKUP("Repurchase of Common Stock*",'9.TIKR_CF'!$A:$K,COLUMN(D15),FALSE)),"0") -> 328 | E42: =IFERROR(ABS(VLOOKUP("Repurchase of Common Stock*",'9.TIKR_CF'!$A:$K,COLUMN(E15),FALSE)),"0") -> 247 | F42: =IFERROR(ABS(VLOOKUP("Repurchase of Common Stock*",'9.TIKR_CF'!$A:$K,COLUMN(F15),FALSE)),"0") -> 196 | G42: =IFERROR(ABS(VLOOKUP("Repurchase of Common Stock*",'9.TIKR_CF'!$A:$K,COLUMN(G15),FALSE)),"0") -> 496 | H42: =IFERROR(ABS(VLOOKUP("Repurchase of Common Stock*",'9.TIKR_CF'!$A:$K,COLUMN(H15),FALSE)),"0") -> 439 | I42: =IFERROR(ABS(VLOOKUP("Repurchase of Common Stock*",'9.TIKR_CF'!$A:$K,COLUMN(I15),FALSE)),"0") -> 676 | ... K42: =IFERROR(ABS(VLOOKUP("Repurchase of Common Stock*",'9.TIKR_CF'!$A:$K,COLUMN(K15),FALSE)),"0") -> 903 | L42: =SUM(B42:K42) -> 4940
A43: Adquisiciones (Crecimiento inorgánico) | B43: =ABS(B11) -> 0 | C43: =ABS(C11) -> 0 | D43: =ABS(D11) -> 0 | E43: =ABS(E11) -> 0 | F43: =ABS(F11) -> 1163 | G43: =ABS(G11) -> 0 | H43: =ABS(H11) -> 0 | I43: =ABS(I11) -> 0 | ... K43: =ABS(K11) -> 0 | L43: =SUM(B43:K43) -> 1163
A44: Amortización neta de deuda | B44: =IFERROR(ABS(VLOOKUP("Total Debt Repaid*",'9.TIKR_CF'!$A:$K,COLUMN(B19),FALSE))-VLOOKUP("Total Debt Issued*",'9.TIKR_CF'!$A:$K,COLUMN(B19),FALSE),0) -> 1022 | C44: =IFERROR(ABS(VLOOKUP("Total Debt Repaid*",'9.TIKR_CF'!$A:$K,COLUMN(C19),FALSE))-VLOOKUP("Total Debt Issued*",'9.TIKR_CF'!$A:$K,COLUMN(C19),FALSE),0) -> -1346 | D44: =IFERROR(ABS(VLOOKUP("Total Debt Repaid*",'9.TIKR_CF'!$A:$K,COLUMN(D19),FALSE))-VLOOKUP("Total Debt Issued*",'9.TIKR_CF'!$A:$K,COLUMN(D19),FALSE),0) -> 6 | E44: =IFERROR(ABS(VLOOKUP("Total Debt Repaid*",'9.TIKR_CF'!$A:$K,COLUMN(E19),FALSE))-VLOOKUP("Total Debt Issued*",'9.TIKR_CF'!$A:$K,COLUMN(E19),FALSE),0) -> -419 | F44: =IFERROR(ABS(VLOOKUP("Total Debt Repaid*",'9.TIKR_CF'!$A:$K,COLUMN(F19),FALSE))-VLOOKUP("Total Debt Issued*",'9.TIKR_CF'!$A:$K,COLUMN(F19),FALSE),0) -> -792 | G44: =IFERROR(ABS(VLOOKUP("Total Debt Repaid*",'9.TIKR_CF'!$A:$K,COLUMN(G19),FALSE))-VLOOKUP("Total Debt Issued*",'9.TIKR_CF'!$A:$K,COLUMN(G19),FALSE),0) -> 120 | H44: =IFERROR(ABS(VLOOKUP("Total Debt Repaid*",'9.TIKR_CF'!$A:$K,COLUMN(H19),FALSE))-VLOOKUP("Total Debt Issued*",'9.TIKR_CF'!$A:$K,COLUMN(H19),FALSE),0) -> 933 | I44: =IFERROR(ABS(VLOOKUP("Total Debt Repaid*",'9.TIKR_CF'!$A:$K,COLUMN(I19),FALSE))-VLOOKUP("Total Debt Issued*",'9.TIKR_CF'!$A:$K,COLUMN(I19),FALSE),0) -> 384 | ... K44: =IFERROR(ABS(VLOOKUP("Total Debt Repaid*",'9.TIKR_CF'!$A:$K,COLUMN(K19),FALSE))-VLOOKUP("Total Debt Issued*",'9.TIKR_CF'!$A:$K,COLUMN(K19),FALSE),0) -> 296 | L44: =SUM(B44:K44) -> 912
A45: % Cash + Marketable Securities / Ventas | B45: =IFERROR(SUM('3.ROIC'!B4:B5)/'1.IS'!B3,"") -> 0.039833557 | C45: =IFERROR(SUM('3.ROIC'!C4:C5)/'1.IS'!C3,"") -> 0.044789769 | D45: =IFERROR(SUM('3.ROIC'!D4:D5)/'1.IS'!D3,"") -> 0.051272815 | E45: =IFERROR(SUM('3.ROIC'!E4:E5)/'1.IS'!E3,"") -> 0.061845543 | F45: =IFERROR(SUM('3.ROIC'!F4:F5)/'1.IS'!F3,"") -> 0.079784842 | G45: =IFERROR(SUM('3.ROIC'!G4:G5)/'1.IS'!G3,"") -> 0.062139857 | H45: =IFERROR(SUM('3.ROIC'!H4:H5)/'1.IS'!H3,"") -> 0.048683874 | I45: =IFERROR(SUM('3.ROIC'!I4:I5)/'1.IS'!I3,"") -> 0.062875067 | ... K45: =IFERROR(SUM('3.ROIC'!K4:K5)/'1.IS'!K3,"") -> 0.055530728
A47: Crecimiento (Gráficos)
B48: ='1.IS'!C$2 -> 2017 | C48: ='1.IS'!D$2 -> 2018 | D48: ='1.IS'!E$2 -> 2019 | E48: ='1.IS'!F$2 -> 2020 | F48: ='1.IS'!G$2 -> 2021 | G48: ='1.IS'!H$2 -> 2022 | H48: ='1.IS'!I$2 -> 2023 | I48: ='1.IS'!J$2 -> 2024 | J48: ='1.IS'!K$2 -> 2025
A49: Ventas | B49: ='1.IS'!C4 -> 0.08681003 | C49: ='1.IS'!D4 -> 0.097275722 | D49: ='1.IS'!E4 -> 0.078593829 | E49: ='1.IS'!F4 -> 0.09206106 | F49: ='1.IS'!G4 -> 0.174909 | G49: ='1.IS'!H4 -> 0.15834818 | H49: ='1.IS'!I4 -> 0.067573165 | I49: ='1.IS'!J4 -> 0.050200173 | J49: ='1.IS'!K4 -> 0.081673236
A50: EPS | B50: ='1.IS'!C24 -> 0.15488338 | C50: ='1.IS'!D24 -> 0.15552294 | D50: ='1.IS'!E24 -> 0.1651954 | E50: ='1.IS'!F24 -> 0.10622994 | F50: ='1.IS'!G24 -> 0.24629847 | G50: ='1.IS'!H24 -> 0.16509054 | H50: ='1.IS'!I24 -> 0.1386417 | I50: ='1.IS'!J24 -> 0.098327582 | J50: ='1.IS'!K24 -> 0.096520405
A51: FCF per share | B51: ='2.FCF'!C16 -> -4.704142 | C51: ='2.FCF'!D16 -> -0.6557508 | D51: ='2.FCF'!E16 -> 1.1276102 | E51: ='2.FCF'!F16 -> 2.2279171 | F51: ='2.FCF'!G16 -> -0.5027027 | G51: ='2.FCF'!H16 -> -1.3403533 | H51: ='2.FCF'!I16 -> -7.6007984 | I51: ='2.FCF'!J16 -> -0.32385848 | J51: ='2.FCF'!K16 -> 0.45125224
A53: Márgenes (Gráficos)
B54: ='1.IS'!B$2 -> 2016 | C54: ='1.IS'!C$2 -> 2017 | D54: ='1.IS'!D$2 -> 2018 | E54: ='1.IS'!E$2 -> 2019 | F54: ='1.IS'!F$2 -> 2020 | G54: ='1.IS'!G$2 -> 2021 | H54: ='1.IS'!H$2 -> 2022 | I54: ='1.IS'!I$2 -> 2023 | ... K54: ='1.IS'!K$2 -> 2025
A55: EBITDA | B55: ='1.IS'!B6 -> 0.03093018 | C55: ='1.IS'!C6 -> 0.031862042 | D55: ='1.IS'!D6 -> 0.031643781 | E55: ='1.IS'!E6 -> 0.031021002 | F55: ='1.IS'!F6 -> 0.032591553 | G55: ='1.IS'!G6 -> 0.034665619 | H55: ='1.IS'!H6 -> 0.034857284 | I55: ='1.IS'!I6 -> 0.035102563 | ... K55: ='1.IS'!K6 -> 0.037724127
A56: EBIT | B56: ='1.IS'!B10 -> 0.03093018 | C56: ='1.IS'!C10 -> 0.031862042 | D56: ='1.IS'!D10 -> 0.031643781 | E56: ='1.IS'!E10 -> 0.031021002 | F56: ='1.IS'!F10 -> 0.032591553 | G56: ='1.IS'!G10 -> 0.034665619 | H56: ='1.IS'!H10 -> 0.034857284 | I56: ='1.IS'!I10 -> 0.035102563 | ... K56: ='1.IS'!K10 -> 0.037724127
A57: FCF | B57: ='2.FCF'!B15 -> -0.002847059 | C57: ='2.FCF'!C15 -> 0.0097035458 | D57: ='2.FCF'!D15 -> 0.0030443013 | E57: ='2.FCF'!E15 -> 0.0060051211 | F57: ='2.FCF'!F15 -> 0.017749954 | G57: ='2.FCF'!G15 -> 0.0075129256 | H57: ='2.FCF'!H15 -> -0.0022074958 | I57: ='2.FCF'!I15 -> 0.013648933 | ... K57: ='2.FCF'!K15 -> 0.011789925
A59: FCF vs ROIC (Gráficos)
B60: ='1.IS'!B$2 -> 2016 | C60: ='1.IS'!C$2 -> 2017 | D60: ='1.IS'!D$2 -> 2018 | E60: ='1.IS'!E$2 -> 2019 | F60: ='1.IS'!F$2 -> 2020 | G60: ='1.IS'!G$2 -> 2021 | H60: ='1.IS'!H$2 -> 2022 | I60: ='1.IS'!I$2 -> 2023 | ... K60: ='1.IS'!K$2 -> 2025
A61: FCF | B61: ='2.FCF'!B14 -> -338 | C61: ='2.FCF'!C14 -> 1252 | D61: ='2.FCF'!D14 -> 431 | E61: ='2.FCF'!E14 -> 917 | F61: ='2.FCF'!F14 -> 2960 | G61: ='2.FCF'!G14 -> 1472 | H61: ='2.FCF'!H14 -> -501 | I61: ='2.FCF'!I14 -> 3307 | ... K61: ='2.FCF'!K14 -> 3245
A62: ROIC | B62: ='3.ROIC'!B15 -> 0.14848894 | C62: ='3.ROIC'!C15 -> 0.16712278 | D62: ='3.ROIC'!D15 -> 0.17281155 | E62: ='3.ROIC'!E15 -> 0.16862353 | F62: ='3.ROIC'!F15 -> 0.14288102 | G62: ='3.ROIC'!G15 -> 0.18061323 | H62: ='3.ROIC'!H15 -> 0.19416106 | I62: ='3.ROIC'!I15 -> 0.18752767 | ... K62: ='3.ROIC'!K15 -> 0.20391985
A64: Costes (Gráficos) | B64: ='1.IS'!B$2 -> 2016 | C64: ='1.IS'!C$2 -> 2017 | D64: ='1.IS'!D$2 -> 2018 | E64: ='1.IS'!E$2 -> 2019 | F64: ='1.IS'!F$2 -> 2020 | G64: ='1.IS'!G$2 -> 2021 | H64: ='1.IS'!H$2 -> 2022 | I64: ='1.IS'!I$2 -> 2023 | ... K64: ='1.IS'!K$2 -> 2025
A65: Costes de ventas y operativos | B65: =IFERROR(('1.IS'!B3-'1.IS'!B5)/'1.IS'!B3,"") -> 0.96906982 | C65: =IFERROR(('1.IS'!C3-'1.IS'!C5)/'1.IS'!C3,"") -> 0.96813796 | D65: =IFERROR(('1.IS'!D3-'1.IS'!D5)/'1.IS'!D3,"") -> 0.96835622 | E65: =IFERROR(('1.IS'!E3-'1.IS'!E5)/'1.IS'!E3,"") -> 0.968979 | F65: =IFERROR(('1.IS'!F3-'1.IS'!F5)/'1.IS'!F3,"") -> 0.96740845 | G65: =IFERROR(('1.IS'!G3-'1.IS'!G5)/'1.IS'!G3,"") -> 0.96533438 | H65: =IFERROR(('1.IS'!H3-'1.IS'!H5)/'1.IS'!H3,"") -> 0.96514272 | I65: =IFERROR(('1.IS'!I3-'1.IS'!I5)/'1.IS'!I3,"") -> 0.96489744 | ... K65: =IFERROR(('1.IS'!K3-'1.IS'!K5)/'1.IS'!K3,"") -> 0.96227587
A66: CapEx Mant. | B66: ='2.FCF'!B22 -> 0.022313193 | C66: ='2.FCF'!C22 -> 0.019391591 | D66: ='2.FCF'!D22 -> 0.020971069 | E66: ='2.FCF'!E22 -> 0.019632882 | F66: ='2.FCF'!F22 -> 0.016850463 | G66: ='2.FCF'!G22 -> 0.018312756 | H66: ='2.FCF'!H22 -> 0.017144443 | I66: ='2.FCF'!I22 -> 0.017842255 | ... K66: ='2.FCF'!K22 -> 0.019975657
A67: Intereses | B67: =IFERROR(('1.IS'!B14/'1.IS'!B3),"") -> -0.00077493914 | C67: =IFERROR(('1.IS'!C14/'1.IS'!C3),"") -> -0.00065103662 | D67: =IFERROR(('1.IS'!D14/'1.IS'!D3),"") -> -0.0005933209 | E67: =IFERROR(('1.IS'!E14/'1.IS'!E3),"") -> -0.00015716784 | F67: =IFERROR(('1.IS'!F14/'1.IS'!F3),"") -> -0.00042575902 | G67: =IFERROR(('1.IS'!G14/'1.IS'!G3),"") -> -0.00066350566 | H67: =IFERROR(('1.IS'!H14/'1.IS'!H3),"") -> -0.00042739938 | I67: =IFERROR(('1.IS'!I14/'1.IS'!I3),"") -> 0.0012794585 | ... K67: =IFERROR(('1.IS'!K14/'1.IS'!K3),"") -> 0.0011444765
A68: Impuestos y otros | B68: =IFERROR(('1.IS'!B16+'1.IS'!B19)/'1.IS'!B3,"") -> -0.010689106 | C68: =IFERROR(('1.IS'!C16+'1.IS'!C19)/'1.IS'!C3,"") -> -0.010540593 | D68: =IFERROR(('1.IS'!D16+'1.IS'!D19)/'1.IS'!D3,"") -> -0.009238854 | E68: =IFERROR(('1.IS'!E16+'1.IS'!E19)/'1.IS'!E3,"") -> -0.0072428178 | F68: =IFERROR(('1.IS'!F16+'1.IS'!F19)/'1.IS'!F3,"") -> -0.0081853671 | G68: =IFERROR(('1.IS'!G16+'1.IS'!G19)/'1.IS'!G3,"") -> -0.0085388074 | H68: =IFERROR(('1.IS'!H16+'1.IS'!H19)/'1.IS'!H3,"") -> -0.0087947337 | I68: =IFERROR(('1.IS'!I16+'1.IS'!I19)/'1.IS'!I3,"") -> -0.0090593916 | ... K68: =IFERROR(('1.IS'!K16+'1.IS'!K19)/'1.IS'!K3,"") -> -0.0098788308
A69: Cambios de WC | C69: =IFERROR('2.FCF'!C12/'1.IS'!C3,"") -> -0.0084247239 | D69: =IFERROR('2.FCF'!D12/'1.IS'!D3,"") -> -0.0022037633 | E69: =IFERROR('2.FCF'!E12/'1.IS'!E3,"") -> -0.0020169872 | F69: =IFERROR('2.FCF'!F12/'1.IS'!F3,"") -> -0.010619989 | G69: =IFERROR('2.FCF'!G12/'1.IS'!G3,"") -> -0.00036237617 | H69: =IFERROR('2.FCF'!H12/'1.IS'!H3,"") -> 0.010698203 | I69: =IFERROR('2.FCF'!I12/'1.IS'!I3,"") -> -0.0041685583 | J69: =IFERROR('2.FCF'!J12/'1.IS'!J3,"") -> 0.0012968996 | K69: =IFERROR('2.FCF'!K12/'1.IS'!K3,"") -> -0.0027758098
A71: Posibles red flags | B71: ='1.IS'!B2 -> 2016 | C71: ='1.IS'!C2 -> 2017 | D71: ='1.IS'!D2 -> 2018 | E71: ='1.IS'!E2 -> 2019 | F71: ='1.IS'!F2 -> 2020 | G71: ='1.IS'!G2 -> 2021 | H71: ='1.IS'!H2 -> 2022 | I71: ='1.IS'!I2 -> 2023 | ... K71: ='1.IS'!K2 -> 2025 | L71: Total
A72: Decrecimiento ventas | C72: =IF('1.IS'!C4<0,1,0) -> 0 | D72: =IF('1.IS'!D4<0,1,0) -> 0 | E72: =IF('1.IS'!E4<0,1,0) -> 0 | F72: =IF('1.IS'!F4<0,1,0) -> 0 | G72: =IF('1.IS'!G4<0,1,0) -> 0 | H72: =IF('1.IS'!H4<0,1,0) -> 0 | I72: =IF('1.IS'!I4<0,1,0) -> 0 | J72: =IF('1.IS'!J4<0,1,0) -> 0 | K72: =IF('1.IS'!K4<0,1,0) -> 0 | L72: =SUM(B72:K72) -> 0
A73: Decrecimiento margen operativo | C73: =IF('1.IS'!C10<'1.IS'!B10,1,0) -> 0 | D73: =IF('1.IS'!D10<'1.IS'!C10,1,0) -> 1 | E73: =IF('1.IS'!E10<'1.IS'!D10,1,0) -> 1 | F73: =IF('1.IS'!F10<'1.IS'!E10,1,0) -> 0 | G73: =IF('1.IS'!G10<'1.IS'!F10,1,0) -> 0 | H73: =IF('1.IS'!H10<'1.IS'!G10,1,0) -> 0 | I73: =IF('1.IS'!I10<'1.IS'!H10,1,0) -> 0 | J73: =IF('1.IS'!J10<'1.IS'!I10,1,0) -> 0 | K73: =IF('1.IS'!K10<'1.IS'!J10,1,0) -> 0 | L73: =SUM(B73:K73) -> 2
A74: FCF negativo | B74: =IF('2.FCF'!B14<0,1,0) -> 1 | C74: =IF('2.FCF'!C14<0,1,0) -> 0 | D74: =IF('2.FCF'!D14<0,1,0) -> 0 | E74: =IF('2.FCF'!E14<0,1,0) -> 0 | F74: =IF('2.FCF'!F14<0,1,0) -> 0 | G74: =IF('2.FCF'!G14<0,1,0) -> 0 | H74: =IF('2.FCF'!H14<0,1,0) -> 1 | I74: =IF('2.FCF'!I14<0,1,0) -> 0 | ... K74: =IF('2.FCF'!K14<0,1,0) -> 0 | L74: =SUM(B74:K74) -> 2
A75: ROIC "Pobre" (<10%) | B75: =IF('3.ROIC'!B15<10%,1,0) -> 0 | C75: =IF('3.ROIC'!C15<10%,1,0) -> 0 | D75: =IF('3.ROIC'!D15<10%,1,0) -> 0 | E75: =IF('3.ROIC'!E15<10%,1,0) -> 0 | F75: =IF('3.ROIC'!F15<10%,1,0) -> 0 | G75: =IF('3.ROIC'!G15<10%,1,0) -> 0 | H75: =IF('3.ROIC'!H15<10%,1,0) -> 0 | I75: =IF('3.ROIC'!I15<10%,1,0) -> 0 | ... K75: =IF('3.ROIC'!K15<10%,1,0) -> 0 | L75: =SUM(B75:K75) -> 0
A76: Ratio Deuda Neta / EBITDA elevado (>2,5x) | B76: =IF('4.Valoración'!B5<>"",IF('4.Valoración'!B5>2.5,1,0),0) -> 0 | C76: =IF('4.Valoración'!C5<>"",IF('4.Valoración'!C5>2.5,1,0),0) -> 0 | D76: =IF('4.Valoración'!D5<>"",IF('4.Valoración'!D5>2.5,1,0),0) -> 0 | E76: =IF('4.Valoración'!E5<>"",IF('4.Valoración'!E5>2.5,1,0),0) -> 0 | F76: =IF('4.Valoración'!F5<>"",IF('4.Valoración'!F5>2.5,1,0),0) -> 0 | G76: =IF('4.Valoración'!G5<>"",IF('4.Valoración'!G5>2.5,1,0),0) -> 0 | H76: =IF('4.Valoración'!H5<>"",IF('4.Valoración'!H5>2.5,1,0),0) -> 0 | I76: =IF('4.Valoración'!I5<>"",IF('4.Valoración'!I5>2.5,1,0),0) -> 0 | ... K76: =IF('4.Valoración'!K5<>"",IF('4.Valoración'!K5>2.5,1,0),0) -> 0 | L76: =SUM(B76:K76) -> 0
