Workbook

Sheet Instrucciones
B2: Instrucciones de uso
B4: - Modifica solo las celdas con fondo AZUL FLOJO. Los datos "clave" que debes modificar manualmente para la valoración están marcados con números en NARANJA (Hojas 1 y 4)
B6: - Debes introducir todas las partidas con el MISMO SIGNO QUE EN TIKR (Número negativo = SALIDA DE CAJA. Número positivo = ENTRADA DE CAJA)
B8: - Opcional: Para que la plantilla obtenga los datos desde TIKR debes darle al botón "Copy Table" de cada estado financiero en TIKR y pegarlos en la celda A1 de las hojas 7 (IS), 8 (BS) y 9 (CF)
B10: - OJO: Solo es válido para TIKR en INGLÉS, y es recomendable pegar los datos con "formato de destino"
B12: - Si no te aparece el botón "Copy table", debes seleccionar a mano los datos. Te sitúas con el cursor en la esquina izquierda superior de la tabla de TIKR y desde la franja negra "Income Statement | TIKR.com", arrastras hacia abajo para seleccionar todos los datos de la tabla. Después copias y pegas en la plantilla, como siempre.
B14: - Si no captura bien los datos, revisa que el separador decimal de tu aplicación de hoja de cálculo coincida con TIKR. También puedes probar a ocultar los decimales en TIKR ("Decimals to display" => 0) y pegar de nuevo los datos
B16: Novedades plantilla REITs v2024.1
B18: - Nueva plantilla de valoración adaptada para REITs
B20: - Hoja 1.IS: P&L adaptada para REITs
B22: - Hoja 3.ROIC: Cálculo del ROIC "adaptado" para REITs, usando el AFFO en el denominador en lugar de EBIT * (1 - T)
B24: - Hoja 3.ROIC: ajuste de las estimaciones a futuro del Equity. Ahora tendrá en cuenta las recompras, emisiones de acciones y los dividendos
B26: - Hoja 4.Valoración: adaptada para REITs: cálculo de valor intrínseco a partir de los múltiplos P/FFO y P/AFFO

Sheet 1.FFO
B1: Funds From Operations | J1: AJUSTAR MANUALMENTE
A2: (millones, excepto EPS) | B2: =IFERROR(IF(VLOOKUP("Income Statement*",'7.TIKR_IS'!$A:$K,COLUMN(B3),FALSE)="","",IFERROR(YEAR(VLOOKUP("Income Statement*",'7.TIKR_IS'!$A:$K,COLUMN(B3),FALSE)),"2014")),"") | C2: =IFERROR(IF(VLOOKUP("Income Statement*",'7.TIKR_IS'!$A:$K,COLUMN(C3),FALSE)="","",IFERROR(YEAR(VLOOKUP("Income Statement*",'7.TIKR_IS'!$A:$K,COLUMN(C3),FALSE)),B2+1)),"") | D2: =IFERROR(IF(VLOOKUP("Income Statement*",'7.TIKR_IS'!$A:$K,COLUMN(D3),FALSE)="","",IFERROR(YEAR(VLOOKUP("Income Statement*",'7.TIKR_IS'!$A:$K,COLUMN(D3),FALSE)),C2+1)),"") | E2: =IFERROR(IF(VLOOKUP("Income Statement*",'7.TIKR_IS'!$A:$K,COLUMN(E3),FALSE)="","",IFERROR(YEAR(VLOOKUP("Income Statement*",'7.TIKR_IS'!$A:$K,COLUMN(E3),FALSE)),D2+1)),"") | F2: =IFERROR(IF(VLOOKUP("Income Statement*",'7.TIKR_IS'!$A:$K,COLUMN(F3),FALSE)="","",IFERROR(YEAR(VLOOKUP("Income Statement*",'7.TIKR_IS'!$A:$K,COLUMN(F3),FALSE)),E2+1)),"") | G2: =IFERROR(IF(VLOOKUP("Income Statement*",'7.TIKR_IS'!$A:$K,COLUMN(G3),FALSE)="","",IFERROR(YEAR(VLOOKUP("Income Statement*",'7.TIKR_IS'!$A:$K,COLUMN(G3),FALSE)),F2+1)),"") | H2: =IFERROR(IF(VLOOKUP("Income Statement*",'7.TIKR_IS'!$A:$K,COLUMN(H3),FALSE)="","",IFERROR(YEAR(VLOOKUP("Income Statement*",'7.TIKR_IS'!$A:$K,COLUMN(H3),FALSE)),G2+1)),"") | I2: =IFERROR(IF(VLOOKUP("Income Statement*",'7.TIKR_IS'!$A:$K,COLUMN(I3),FALSE)="","",IFERROR(YEAR(VLOOKUP("Income Statement*",'7.TIKR_IS'!$A:$K,COLUMN(I3),FALSE)),H2+1)),"") | J2: =IFERROR(IF(VLOOKUP("Income Statement*",'7.TIKR_IS'!$A:$K,COLUMN(J3),FALSE)="","",IFERROR(YEAR(VLOOKUP("Income Statement*",'7.TIKR_IS'!$A:$K,COLUMN(J3),FALSE)),I2+1)),"") | K2: =IFERROR(IF(VLOOKUP("Income Statement*",'7.TIKR_IS'!$A:$K,COLUMN(K3),FALSE)="","",IFERROR(YEAR(VLOOKUP("Income Statement*",'7.TIKR_IS'!$A:$K,COLUMN(K3),FALSE)),J2+1)),"") | L2: =IF(K2<>"",(K2+1)&"e","") | M2: =IF(L2<>"",(LEFT(L2,4)+1)&"e","") | N2: =IF(M2<>"",(LEFT(M2,4)+1)&"e","") | O2: =IF(N2<>"",(LEFT(N2,4)+1)&"e","") | P2: =IF(O2<>"",(LEFT(O2,4)+1)&"e","") | R2: Proyección a futuro | S2: ="Promedio "&CHAR(10)&B2&" - "&K2 -> Promedio - | T2: ="Estimaciones "&CHAR(10)&L2&" - "&P2 -> Estimaciones -
A3: Sales | B3: =IFERROR(VLOOKUP("Total Revenues*",'7.TIKR_IS'!$A:$K,COLUMN(B3),FALSE),"0") -> 0 | C3: =IFERROR(VLOOKUP("Total Revenues*",'7.TIKR_IS'!$A:$K,COLUMN(C3),FALSE),"0") -> 0 | D3: =IFERROR(VLOOKUP("Total Revenues*",'7.TIKR_IS'!$A:$K,COLUMN(D3),FALSE),"0") -> 0 | E3: =IFERROR(VLOOKUP("Total Revenues*",'7.TIKR_IS'!$A:$K,COLUMN(E3),FALSE),"0") -> 0 | F3: =IFERROR(VLOOKUP("Total Revenues*",'7.TIKR_IS'!$A:$K,COLUMN(F3),FALSE),"0") -> 0 | G3: =IFERROR(VLOOKUP("Total Revenues*",'7.TIKR_IS'!$A:$K,COLUMN(G3),FALSE),"0") -> 0 | H3: =IFERROR(VLOOKUP("Total Revenues*",'7.TIKR_IS'!$A:$K,COLUMN(H3),FALSE),"0") -> 0 | I3: =IFERROR(VLOOKUP("Total Revenues*",'7.TIKR_IS'!$A:$K,COLUMN(I3),FALSE),"0") -> 0 | ... K3: =IFERROR(VLOOKUP("Total Revenues*",'7.TIKR_IS'!$A:$K,COLUMN(K3),FALSE),"0") -> 0 | L3: =IFERROR((K3*$T$3)+K3,"") | M3: =IFERROR((L3*$T$3)+L3,"") | N3: =IFERROR((M3*$T$3)+M3,"") | O3: =IFERROR((N3*$T$3)+N3,"") | P3: =IFERROR((O3*$T$3)+O3,"") | R3: Crecimiento en Ventas | S3: =IFERROR(AVERAGE(C4:K4),"") | T3: =S3
A4: Y/Y Growth % | C4: =IFERROR((C3-B3)/B3,"") | D4: =IFERROR((D3-C3)/C3,"") | E4: =IFERROR((E3-D3)/D3,"") | F4: =IFERROR((F3-E3)/E3,"") | G4: =IFERROR((G3-F3)/F3,"") | H4: =IFERROR((H3-G3)/G3,"") | I4: =IFERROR((I3-H3)/H3,"") | J4: =IFERROR((J3-I3)/I3,"") | K4: =IFERROR((K3-J3)/J3,"") | L4: =$T$3 | M4: =$T$3 | N4: =$T$3 | O4: =$T$3 | P4: =$T$3 | R4: Margen FFO | S4: =IFERROR(AVERAGE(B6:K6),"") | T4: =S4
A5: Funds From Operations (FFO) * | B5: =IFERROR(VLOOKUP("FFO",'7.TIKR_IS'!$A:$K,COLUMN(B2),FALSE),"0") -> 0 | C5: =IFERROR(VLOOKUP("FFO",'7.TIKR_IS'!$A:$K,COLUMN(C2),FALSE),"0") -> 0 | D5: =IFERROR(VLOOKUP("FFO",'7.TIKR_IS'!$A:$K,COLUMN(D2),FALSE),"0") -> 0 | E5: =IFERROR(VLOOKUP("FFO",'7.TIKR_IS'!$A:$K,COLUMN(E2),FALSE),"0") -> 0 | F5: =IFERROR(VLOOKUP("FFO",'7.TIKR_IS'!$A:$K,COLUMN(F2),FALSE),"0") -> 0 | G5: =IFERROR(VLOOKUP("FFO",'7.TIKR_IS'!$A:$K,COLUMN(G2),FALSE),"0") -> 0 | H5: =IFERROR(VLOOKUP("FFO",'7.TIKR_IS'!$A:$K,COLUMN(H2),FALSE),"0") -> 0 | I5: =IFERROR(VLOOKUP("FFO",'7.TIKR_IS'!$A:$K,COLUMN(I2),FALSE),"0") -> 0 | ... K5: =IFERROR(VLOOKUP("FFO",'7.TIKR_IS'!$A:$K,COLUMN(K2),FALSE),"0") -> 0 | L5: =IFERROR(L3*$T$4,"") | M5: =IFERROR(M3*$T$4,"") | N5: =IFERROR(N3*$T$4,"") | O5: =IFERROR(O3*$T$4,"") | P5: =IFERROR(P3*$T$4,"") | R5: CapEx Mtto. / Ventas % | S5: =IFERROR(AVERAGE(ABS(SUM(B7:K7))/SUM(B3:K3)),"") | T5: =S5
A6: FFO margin % | B6: =IFERROR((B5/B3),"") | C6: =IFERROR((C5/C3),"") | D6: =IFERROR((D5/D3),"") | E6: =IFERROR((E5/E3),"") | F6: =IFERROR((F5/F3),"") | G6: =IFERROR((G5/G3),"") | H6: =IFERROR((H5/H3),"") | I6: =IFERROR((I5/I3),"") | ... P6: =IFERROR((P5/P3),"") | R6: Aumento nº acciones | S6: =IFERROR(AVERAGE(C12:K12),"") | T6: =S6
A7: CapEx Mantenimiento - en negativo ** | L7: =IFERROR(-$T$5*L3,"") | M7: =IFERROR(-$T$5*M3,"") | N7: =IFERROR(-$T$5*N3,"") | O7: =IFERROR(-$T$5*O3,"") | P7: =IFERROR(-$T$5*P3,"")
A8: CapEx / Ventas % | B8: =IFERROR(-B7/B3,"") | C8: =IFERROR(-C7/C3,"") | D8: =IFERROR(-D7/D3,"") | E8: =IFERROR(-E7/E3,"") | F8: =IFERROR(-F7/F3,"") | G8: =IFERROR(-G7/G3,"") | H8: =IFERROR(-H7/H3,"") | I8: =IFERROR(-I7/I3,"") | ... P8: =IFERROR(-P7/P3,"")
A9: Adjusted Funds From Operations (AFFO) | B9: =B5+B7 -> 0 | C9: =C5+C7 -> 0 | D9: =D5+D7 -> 0 | E9: =E5+E7 -> 0 | F9: =F5+F7 -> 0 | G9: =G5+G7 -> 0 | H9: =H5+H7 -> 0 | I9: =I5+I7 -> 0 | ... K9: =K5+K7 -> 0 | L9: =IFERROR(L5+L7,"") | M9: =IFERROR(M5+M7,"") | N9: =IFERROR(N5+N7,"") | O9: =IFERROR(O5+O7,"") | P9: =IFERROR(P5+P7,"") | T9: AJUSTAR MANUALMENTE
A10: AFFO margin % | B10: =IFERROR(B9/B3,"") | C10: =IFERROR(C9/C3,"") | D10: =IFERROR(D9/D3,"") | E10: =IFERROR(E9/E3,"") | F10: =IFERROR(F9/F3,"") | G10: =IFERROR(G9/G3,"") | H10: =IFERROR(H9/H3,"") | I10: =IFERROR(I9/I3,"") | ... P10: =IFERROR(P9/P3,"")
A11: Fully diluted shares - millones | B11: =IFERROR(VLOOKUP("*Diluted Shares Outstanding*",'7.TIKR_IS'!$A:$K,COLUMN(B11),FALSE),"0") -> 0 | C11: =IFERROR(VLOOKUP("*Diluted Shares Outstanding*",'7.TIKR_IS'!$A:$K,COLUMN(C11),FALSE),"0") -> 0 | D11: =IFERROR(VLOOKUP("*Diluted Shares Outstanding*",'7.TIKR_IS'!$A:$K,COLUMN(D11),FALSE),"0") -> 0 | E11: =IFERROR(VLOOKUP("*Diluted Shares Outstanding*",'7.TIKR_IS'!$A:$K,COLUMN(E11),FALSE),"0") -> 0 | F11: =IFERROR(VLOOKUP("*Diluted Shares Outstanding*",'7.TIKR_IS'!$A:$K,COLUMN(F11),FALSE),"0") -> 0 | G11: =IFERROR(VLOOKUP("*Diluted Shares Outstanding*",'7.TIKR_IS'!$A:$K,COLUMN(G11),FALSE),"0") -> 0 | H11: =IFERROR(VLOOKUP("*Diluted Shares Outstanding*",'7.TIKR_IS'!$A:$K,COLUMN(H11),FALSE),"0") -> 0 | I11: =IFERROR(VLOOKUP("*Diluted Shares Outstanding*",'7.TIKR_IS'!$A:$K,COLUMN(I11),FALSE),"0") -> 0 | ... K11: =IFERROR(VLOOKUP("*Diluted Shares Outstanding*",'7.TIKR_IS'!$A:$K,COLUMN(K11),FALSE),"0") -> 0 | L11: =IFERROR(K11*(1+$T$6),"") | M11: =IFERROR(L11*(1+$T$6),"") | N11: =IFERROR(M11*(1+$T$6),"") | O11: =IFERROR(N11*(1+$T$6),"") | P11: =IFERROR(O11*(1+$T$6),"")
A12: Y/Y Growth % | C12: =IFERROR((C11-B11)/B11,"") | D12: =IFERROR((D11-C11)/C11,"") | E12: =IFERROR((E11-D11)/D11,"") | F12: =IFERROR((F11-E11)/E11,"") | G12: =IFERROR((G11-F11)/F11,"") | H12: =IFERROR((H11-G11)/G11,"") | I12: =IFERROR((I11-H11)/H11,"") | J12: =IFERROR((J11-I11)/I11,"") | ... P12: =IFERROR((P11-O11)/O11,"")
B14: * TIKR no muestra el FFO en la cuenta gratuita ni en la PLUS, solo aparece en la PRO (la más cara). La mayoría de REITs detallan el FFO en su informe anual, pero NO es obligatorio, ya que es una métrica "Non-GAAP".
B16: ** Cuidado con el CapEx de mantenimiento. La depreciación está inflada en algunos REITs. Debemos ajustarla manualmente con el CapEx de mantenimiento que nos facilite la empresa en su informe anual. Ejemplo real con Realty Income (NYSE:O) en el año fiscal 2023: Depreciation 1.244m vs "Recurring Capital Expenditure" de 331m. Es una partida "inventada" por la directiva ("Non-GAAP"). Por tanto, NO aparece en los Financials de TIKR

Sheet 3.ROIC
B1: Retornos sobre el capital invertido
A2: (millones) | B2: ='1.FFO'!B$2 | C2: ='1.FFO'!C$2 | D2: ='1.FFO'!D$2 | E2: ='1.FFO'!E$2 | F2: ='1.FFO'!F$2 | G2: ='1.FFO'!G$2 | H2: ='1.FFO'!H$2 | I2: ='1.FFO'!I$2 | ... P2: ='1.FFO'!P$2
A3: AFFO | B3: ='1.FFO'!B9 -> 0 | C3: ='1.FFO'!C9 -> 0 | D3: ='1.FFO'!D9 -> 0 | E3: ='1.FFO'!E9 -> 0 | F3: ='1.FFO'!F9 -> 0 | G3: ='1.FFO'!G9 -> 0 | H3: ='1.FFO'!H9 -> 0 | I3: ='1.FFO'!I9 -> 0 | ... K3: ='1.FFO'!K9 -> 0 | L3: =IFERROR('1.FFO'!L5*PRODUCT(1-'1.FFO'!#REF!),"") | M3: =IFERROR('1.FFO'!M5*PRODUCT(1-'1.FFO'!#REF!),"") | N3: =IFERROR('1.FFO'!N5*PRODUCT(1-'1.FFO'!#REF!),"") | O3: =IFERROR('1.FFO'!O5*PRODUCT(1-'1.FFO'!#REF!),"") | P3: =IFERROR('1.FFO'!P5*PRODUCT(1-'1.FFO'!#REF!),"")
A4: Cash and cash equivalents | B4: =IFERROR(VLOOKUP("Cash And Equivalents*",'8.TIKR_BS'!$A:$K,COLUMN(B4),FALSE),"0") -> 0 | C4: =IFERROR(VLOOKUP("Cash And Equivalents*",'8.TIKR_BS'!$A:$K,COLUMN(C4),FALSE),"0") -> 0 | D4: =IFERROR(VLOOKUP("Cash And Equivalents*",'8.TIKR_BS'!$A:$K,COLUMN(D4),FALSE),"0") -> 0 | E4: =IFERROR(VLOOKUP("Cash And Equivalents*",'8.TIKR_BS'!$A:$K,COLUMN(E4),FALSE),"0") -> 0 | F4: =IFERROR(VLOOKUP("Cash And Equivalents*",'8.TIKR_BS'!$A:$K,COLUMN(F4),FALSE),"0") -> 0 | G4: =IFERROR(VLOOKUP("Cash And Equivalents*",'8.TIKR_BS'!$A:$K,COLUMN(G4),FALSE),"0") -> 0 | H4: =IFERROR(VLOOKUP("Cash And Equivalents*",'8.TIKR_BS'!$A:$K,COLUMN(H4),FALSE),"0") -> 0 | I4: =IFERROR(VLOOKUP("Cash And Equivalents*",'8.TIKR_BS'!$A:$K,COLUMN(I4),FALSE),"0") -> 0 | ... K4: =IFERROR(VLOOKUP("Cash And Equivalents*",'8.TIKR_BS'!$A:$K,COLUMN(K4),FALSE),"0") -> 0 | L4: =IFERROR(K4/'1.FFO'!K3*'1.FFO'!L3,"") | M4: =IFERROR(L4/'1.FFO'!L3*'1.FFO'!M3,"") | N4: =IFERROR(M4/'1.FFO'!M3*'1.FFO'!N3,"") | O4: =IFERROR(N4/'1.FFO'!N3*'1.FFO'!O3,"") | P4: =IFERROR(O4/'1.FFO'!O3*'1.FFO'!P3,"")
A5: (-) Marketable Securities | B5: =IFERROR(VLOOKUP("Total Cash And Short Term Investments*",'8.TIKR_BS'!$A:$K,COLUMN(B5),FALSE)-B4,"0") -> 0 | C5: =IFERROR(VLOOKUP("Total Cash And Short Term Investments*",'8.TIKR_BS'!$A:$K,COLUMN(C5),FALSE)-C4,"0") -> 0 | D5: =IFERROR(VLOOKUP("Total Cash And Short Term Investments*",'8.TIKR_BS'!$A:$K,COLUMN(D5),FALSE)-D4,"0") -> 0 | E5: =IFERROR(VLOOKUP("Total Cash And Short Term Investments*",'8.TIKR_BS'!$A:$K,COLUMN(E5),FALSE)-E4,"0") -> 0 | F5: =IFERROR(VLOOKUP("Total Cash And Short Term Investments*",'8.TIKR_BS'!$A:$K,COLUMN(F5),FALSE)-F4,"0") -> 0 | G5: =IFERROR(VLOOKUP("Total Cash And Short Term Investments*",'8.TIKR_BS'!$A:$K,COLUMN(G5),FALSE)-G4,"0") -> 0 | H5: =IFERROR(VLOOKUP("Total Cash And Short Term Investments*",'8.TIKR_BS'!$A:$K,COLUMN(H5),FALSE)-H4,"0") -> 0 | I5: =IFERROR(VLOOKUP("Total Cash And Short Term Investments*",'8.TIKR_BS'!$A:$K,COLUMN(I5),FALSE)-I4,"0") -> 0 | ... K5: =IFERROR(VLOOKUP("Total Cash And Short Term Investments*",'8.TIKR_BS'!$A:$K,COLUMN(K5),FALSE)-K4,"0") -> 0 | L5: =IFERROR(K5/'1.FFO'!K3*'1.FFO'!L3,"") | M5: =IFERROR(L5/'1.FFO'!L3*'1.FFO'!M3,"") | N5: =IFERROR(M5/'1.FFO'!M3*'1.FFO'!N3,"") | O5: =IFERROR(N5/'1.FFO'!N3*'1.FFO'!O3,"") | P5: =IFERROR(O5/'1.FFO'!O3*'1.FFO'!P3,"")
A6: (+) Short-Term Debt | B6: =IFERROR(VLOOKUP("Short-term Borrowings*",'8.TIKR_BS'!$A:$K,COLUMN(B6),FALSE),"0")+IFERROR(VLOOKUP("Current Portion of Long-Term Debt*",'8.TIKR_BS'!$A:$K,COLUMN(B6),FALSE),"0") -> 0 | C6: =IFERROR(VLOOKUP("Short-term Borrowings*",'8.TIKR_BS'!$A:$K,COLUMN(C6),FALSE),"0")+IFERROR(VLOOKUP("Current Portion of Long-Term Debt*",'8.TIKR_BS'!$A:$K,COLUMN(C6),FALSE),"0") -> 0 | D6: =IFERROR(VLOOKUP("Short-term Borrowings*",'8.TIKR_BS'!$A:$K,COLUMN(D6),FALSE),"0")+IFERROR(VLOOKUP("Current Portion of Long-Term Debt*",'8.TIKR_BS'!$A:$K,COLUMN(D6),FALSE),"0") -> 0 | E6: =IFERROR(VLOOKUP("Short-term Borrowings*",'8.TIKR_BS'!$A:$K,COLUMN(E6),FALSE),"0")+IFERROR(VLOOKUP("Current Portion of Long-Term Debt*",'8.TIKR_BS'!$A:$K,COLUMN(E6),FALSE),"0") -> 0 | F6: =IFERROR(VLOOKUP("Short-term Borrowings*",'8.TIKR_BS'!$A:$K,COLUMN(F6),FALSE),"0")+IFERROR(VLOOKUP("Current Portion of Long-Term Debt*",'8.TIKR_BS'!$A:$K,COLUMN(F6),FALSE),"0") -> 0 | G6: =IFERROR(VLOOKUP("Short-term Borrowings*",'8.TIKR_BS'!$A:$K,COLUMN(G6),FALSE),"0")+IFERROR(VLOOKUP("Current Portion of Long-Term Debt*",'8.TIKR_BS'!$A:$K,COLUMN(G6),FALSE),"0") -> 0 | H6: =IFERROR(VLOOKUP("Short-term Borrowings*",'8.TIKR_BS'!$A:$K,COLUMN(H6),FALSE),"0")+IFERROR(VLOOKUP("Current Portion of Long-Term Debt*",'8.TIKR_BS'!$A:$K,COLUMN(H6),FALSE),"0") -> 0 | I6: =IFERROR(VLOOKUP("Short-term Borrowings*",'8.TIKR_BS'!$A:$K,COLUMN(I6),FALSE),"0")+IFERROR(VLOOKUP("Current Portion of Long-Term Debt*",'8.TIKR_BS'!$A:$K,COLUMN(I6),FALSE),"0") -> 0 | ... K6: =IFERROR(VLOOKUP("Short-term Borrowings*",'8.TIKR_BS'!$A:$K,COLUMN(K6),FALSE),"0")+IFERROR(VLOOKUP("Current Portion of Long-Term Debt*",'8.TIKR_BS'!$A:$K,COLUMN(K6),FALSE),"0") -> 0 | L6: =IFERROR(IF((L4+L5+'4.Valoración'!L4)*TIKR_Cálculos!$B$7>0,(L4+L5+'4.Valoración'!L4)*TIKR_Cálculos!$B$7,0),"0") -> 0 | M6: =IFERROR(IF((M4+M5+'4.Valoración'!M4)*TIKR_Cálculos!$B$7>0,(M4+M5+'4.Valoración'!M4)*TIKR_Cálculos!$B$7,0),"0") -> 0 | N6: =IFERROR(IF((N4+N5+'4.Valoración'!N4)*TIKR_Cálculos!$B$7>0,(N4+N5+'4.Valoración'!N4)*TIKR_Cálculos!$B$7,0),"0") -> 0 | O6: =IFERROR(IF((O4+O5+'4.Valoración'!O4)*TIKR_Cálculos!$B$7>0,(O4+O5+'4.Valoración'!O4)*TIKR_Cálculos!$B$7,0),"0") -> 0 | P6: =IFERROR(IF((P4+P5+'4.Valoración'!P4)*TIKR_Cálculos!$B$7>0,(P4+P5+'4.Valoración'!P4)*TIKR_Cálculos!$B$7,0),"0") -> 0
A7: (+) Long-Term Debt | B7: =IFERROR(VLOOKUP("Long-term Borrowings*",'8.TIKR_BS'!$A:$K,COLUMN(B7),FALSE),"0")+IFERROR(VLOOKUP("Long-Term Debt*",'8.TIKR_BS'!$A:$K,COLUMN(B7),FALSE),"0") -> 0 | C7: =IFERROR(VLOOKUP("Long-term Borrowings*",'8.TIKR_BS'!$A:$K,COLUMN(C7),FALSE),"0")+IFERROR(VLOOKUP("Long-Term Debt*",'8.TIKR_BS'!$A:$K,COLUMN(C7),FALSE),"0") -> 0 | D7: =IFERROR(VLOOKUP("Long-term Borrowings*",'8.TIKR_BS'!$A:$K,COLUMN(D7),FALSE),"0")+IFERROR(VLOOKUP("Long-Term Debt*",'8.TIKR_BS'!$A:$K,COLUMN(D7),FALSE),"0") -> 0 | E7: =IFERROR(VLOOKUP("Long-term Borrowings*",'8.TIKR_BS'!$A:$K,COLUMN(E7),FALSE),"0")+IFERROR(VLOOKUP("Long-Term Debt*",'8.TIKR_BS'!$A:$K,COLUMN(E7),FALSE),"0") -> 0 | F7: =IFERROR(VLOOKUP("Long-term Borrowings*",'8.TIKR_BS'!$A:$K,COLUMN(F7),FALSE),"0")+IFERROR(VLOOKUP("Long-Term Debt*",'8.TIKR_BS'!$A:$K,COLUMN(F7),FALSE),"0") -> 0 | G7: =IFERROR(VLOOKUP("Long-term Borrowings*",'8.TIKR_BS'!$A:$K,COLUMN(G7),FALSE),"0")+IFERROR(VLOOKUP("Long-Term Debt*",'8.TIKR_BS'!$A:$K,COLUMN(G7),FALSE),"0") -> 0 | H7: =IFERROR(VLOOKUP("Long-term Borrowings*",'8.TIKR_BS'!$A:$K,COLUMN(H7),FALSE),"0")+IFERROR(VLOOKUP("Long-Term Debt*",'8.TIKR_BS'!$A:$K,COLUMN(H7),FALSE),"0") -> 0 | I7: =IFERROR(VLOOKUP("Long-term Borrowings*",'8.TIKR_BS'!$A:$K,COLUMN(I7),FALSE),"0")+IFERROR(VLOOKUP("Long-Term Debt*",'8.TIKR_BS'!$A:$K,COLUMN(I7),FALSE),"0") -> 0 | ... K7: =IFERROR(VLOOKUP("Long-term Borrowings*",'8.TIKR_BS'!$A:$K,COLUMN(K7),FALSE),"0")+IFERROR(VLOOKUP("Long-Term Debt*",'8.TIKR_BS'!$A:$K,COLUMN(K7),FALSE),"0") -> 0 | L7: =IFERROR(IF((L4+L5+'4.Valoración'!L4)*TIKR_Cálculos!$B$8>0,(L4+L5+'4.Valoración'!L4)*TIKR_Cálculos!$B$8,0),"0") -> 0 | M7: =IFERROR(IF((M4+M5+'4.Valoración'!M4)*TIKR_Cálculos!$B$8>0,(M4+M5+'4.Valoración'!M4)*TIKR_Cálculos!$B$8,0),"0") -> 0 | N7: =IFERROR(IF((N4+N5+'4.Valoración'!N4)*TIKR_Cálculos!$B$8>0,(N4+N5+'4.Valoración'!N4)*TIKR_Cálculos!$B$8,0),"0") -> 0 | O7: =IFERROR(IF((O4+O5+'4.Valoración'!O4)*TIKR_Cálculos!$B$8>0,(O4+O5+'4.Valoración'!O4)*TIKR_Cálculos!$B$8,0),"0") -> 0 | P7: =IFERROR(IF((P4+P5+'4.Valoración'!P4)*TIKR_Cálculos!$B$8>0,(P4+P5+'4.Valoración'!P4)*TIKR_Cálculos!$B$8,0),"0") -> 0
A8: (+) Current Operating Leases Liabilities | B8: =IFERROR(VLOOKUP("Current Portion of Capital Lease Obligations*",'8.TIKR_BS'!$A:$K,COLUMN(B8),FALSE),"0") -> 0 | C8: =IFERROR(VLOOKUP("Current Portion of Capital Lease Obligations*",'8.TIKR_BS'!$A:$K,COLUMN(C8),FALSE),"0") -> 0 | D8: =IFERROR(VLOOKUP("Current Portion of Capital Lease Obligations*",'8.TIKR_BS'!$A:$K,COLUMN(D8),FALSE),"0") -> 0 | E8: =IFERROR(VLOOKUP("Current Portion of Capital Lease Obligations*",'8.TIKR_BS'!$A:$K,COLUMN(E8),FALSE),"0") -> 0 | F8: =IFERROR(VLOOKUP("Current Portion of Capital Lease Obligations*",'8.TIKR_BS'!$A:$K,COLUMN(F8),FALSE),"0") -> 0 | G8: =IFERROR(VLOOKUP("Current Portion of Capital Lease Obligations*",'8.TIKR_BS'!$A:$K,COLUMN(G8),FALSE),"0") -> 0 | H8: =IFERROR(VLOOKUP("Current Portion of Capital Lease Obligations*",'8.TIKR_BS'!$A:$K,COLUMN(H8),FALSE),"0") -> 0 | I8: =IFERROR(VLOOKUP("Current Portion of Capital Lease Obligations*",'8.TIKR_BS'!$A:$K,COLUMN(I8),FALSE),"0") -> 0 | ... K8: =IFERROR(VLOOKUP("Current Portion of Capital Lease Obligations*",'8.TIKR_BS'!$A:$K,COLUMN(K8),FALSE),"0") -> 0 | L8: =IFERROR(K8*'1.FFO'!$T$3+K8,"") | M8: =IFERROR(L8*'1.FFO'!$T$3+L8,"") | N8: =IFERROR(M8*'1.FFO'!$T$3+M8,"") | O8: =IFERROR(N8*'1.FFO'!$T$3+N8,"") | P8: =IFERROR(O8*'1.FFO'!$T$3+O8,"")
A9: (+) Non-Current Operating Leases Liabilities | B9: =IFERROR(VLOOKUP("Capital Leases*",'8.TIKR_BS'!$A:$K,COLUMN(B9),FALSE),"0") -> 0 | C9: =IFERROR(VLOOKUP("Capital Leases*",'8.TIKR_BS'!$A:$K,COLUMN(C9),FALSE),"0") -> 0 | D9: =IFERROR(VLOOKUP("Capital Leases*",'8.TIKR_BS'!$A:$K,COLUMN(D9),FALSE),"0") -> 0 | E9: =IFERROR(VLOOKUP("Capital Leases*",'8.TIKR_BS'!$A:$K,COLUMN(E9),FALSE),"0") -> 0 | F9: =IFERROR(VLOOKUP("Capital Leases*",'8.TIKR_BS'!$A:$K,COLUMN(F9),FALSE),"0") -> 0 | G9: =IFERROR(VLOOKUP("Capital Leases*",'8.TIKR_BS'!$A:$K,COLUMN(G9),FALSE),"0") -> 0 | H9: =IFERROR(VLOOKUP("Capital Leases*",'8.TIKR_BS'!$A:$K,COLUMN(H9),FALSE),"0") -> 0 | I9: =IFERROR(VLOOKUP("Capital Leases*",'8.TIKR_BS'!$A:$K,COLUMN(I9),FALSE),"0") -> 0 | ... K9: =IFERROR(VLOOKUP("Capital Leases*",'8.TIKR_BS'!$A:$K,COLUMN(K9),FALSE),"0") -> 0 | L9: =IFERROR(K9*'1.FFO'!$T$3+K9,"") | M9: =IFERROR(L9*'1.FFO'!$T$3+L9,"") | N9: =IFERROR(M9*'1.FFO'!$T$3+M9,"") | O9: =IFERROR(N9*'1.FFO'!$T$3+N9,"") | P9: =IFERROR(O9*'1.FFO'!$T$3+O9,"")
A10: (+) Equity | B10: =IFERROR(VLOOKUP("Total Equity*",'8.TIKR_BS'!$A:$K,COLUMN(B10),FALSE),"0") -> 0 | C10: =IFERROR(VLOOKUP("Total Equity*",'8.TIKR_BS'!$A:$K,COLUMN(C10),FALSE),"0") -> 0 | D10: =IFERROR(VLOOKUP("Total Equity*",'8.TIKR_BS'!$A:$K,COLUMN(D10),FALSE),"0") -> 0 | E10: =IFERROR(VLOOKUP("Total Equity*",'8.TIKR_BS'!$A:$K,COLUMN(E10),FALSE),"0") -> 0 | F10: =IFERROR(VLOOKUP("Total Equity*",'8.TIKR_BS'!$A:$K,COLUMN(F10),FALSE),"0") -> 0 | G10: =IFERROR(VLOOKUP("Total Equity*",'8.TIKR_BS'!$A:$K,COLUMN(G10),FALSE),"0") -> 0 | H10: =IFERROR(VLOOKUP("Total Equity*",'8.TIKR_BS'!$A:$K,COLUMN(H10),FALSE),"0") -> 0 | I10: =IFERROR(VLOOKUP("Total Equity*",'8.TIKR_BS'!$A:$K,COLUMN(I10),FALSE),"0") -> 0 | ... K10: =IFERROR(VLOOKUP("Total Equity*",'8.TIKR_BS'!$A:$K,COLUMN(K10),FALSE),"0") -> 0 | L10: =IFERROR(K10+TIKR_Cálculos!L44+'1.FFO'!L12*'4.Valoración'!L3,"") | M10: =IFERROR(L10+TIKR_Cálculos!M44+'1.FFO'!M12*'4.Valoración'!M3,"") | N10: =IFERROR(M10+TIKR_Cálculos!N44+'1.FFO'!N12*'4.Valoración'!N3,"") | O10: =IFERROR(N10+TIKR_Cálculos!O44+'1.FFO'!O12*'4.Valoración'!O3,"") | P10: =IFERROR(O10+TIKR_Cálculos!P44+'1.FFO'!P12*'4.Valoración'!P3,"")
A11: Invested Capital | B11: =B10+B6+B7+B8+B9 -> 0 | C11: =C10+C6+C7+C8+C9 -> 0 | D11: =D10+D6+D7+D8+D9 -> 0 | E11: =E10+E6+E7+E8+E9 -> 0 | F11: =F10+F6+F7+F8+F9 -> 0 | G11: =G10+G6+G7+G8+G9 -> 0 | H11: =H10+H6+H7+H8+H9 -> 0 | I11: =I10+I6+I7+I8+I9 -> 0 | ... K11: =K10+K6+K7+K8+K9 -> 0 | L11: =IFERROR(L10+L6+L7+L8+L9,"") | M11: =IFERROR(M10+M6+M7+M8+M9,"") | N11: =IFERROR(N10+N6+N7+N8+N9,"") | O11: =IFERROR(O10+O6+O7+O8+O9,"") | P11: =IFERROR(P10+P6+P7+P8+P9,"")
A13: Ratio de rentabilidad | B13: ='1.FFO'!B$2 | C13: ='1.FFO'!C$2 | D13: ='1.FFO'!D$2 | E13: ='1.FFO'!E$2 | F13: ='1.FFO'!F$2 | G13: ='1.FFO'!G$2 | H13: ='1.FFO'!H$2 | I13: ='1.FFO'!I$2 | ... P13: ='1.FFO'!P$2 | R13: ="Promedio "&CHAR(10)&B$2&" - "&K$2 -> Promedio -
A14: ROIC | B14: =IFERROR(B3/B11,"") | C14: =IFERROR(C3/C11,"") | D14: =IFERROR(D3/D11,"") | E14: =IFERROR(E3/E11,"") | F14: =IFERROR(F3/F11,"") | G14: =IFERROR(G3/G11,"") | H14: =IFERROR(H3/H11,"") | I14: =IFERROR(I3/I11,"") | ... P14: =IFERROR(P3/P11,"") | R14: =IFERROR(AVERAGE(B14:K14),"")

Sheet 4.Valoración
B1: Valoración
A2: Valoración (millones) | B2: ='1.FFO'!B$2 | C2: ='1.FFO'!C$2 | D2: ='1.FFO'!D$2 | E2: ='1.FFO'!E$2 | F2: ='1.FFO'!F$2 | G2: ='1.FFO'!G$2 | H2: ='1.FFO'!H$2 | I2: ='1.FFO'!I$2 | ... P2: ='1.FFO'!P$2
A3: Market cap | K3: =$D$8*'1.FFO'!K11 -> 0 | L3: =IFERROR($D$8*'1.FFO'!L11,"") | M3: =IFERROR($D$8*'1.FFO'!M11,"") | N3: =IFERROR($D$8*'1.FFO'!N11,"") | O3: =IFERROR($D$8*'1.FFO'!O11,"") | P3: =IFERROR($D$8*'1.FFO'!P11,"")
A4: Net Debt (si es caja neta va en NEGATIVO) | B4: =('3.ROIC'!B7+'3.ROIC'!B6)-('3.ROIC'!B4+'3.ROIC'!B5) -> 0 | C4: =('3.ROIC'!C7+'3.ROIC'!C6)-('3.ROIC'!C4+'3.ROIC'!C5) -> 0 | D4: =('3.ROIC'!D7+'3.ROIC'!D6)-('3.ROIC'!D4+'3.ROIC'!D5) -> 0 | E4: =('3.ROIC'!E7+'3.ROIC'!E6)-('3.ROIC'!E4+'3.ROIC'!E5) -> 0 | F4: =('3.ROIC'!F7+'3.ROIC'!F6)-('3.ROIC'!F4+'3.ROIC'!F5) -> 0 | G4: =('3.ROIC'!G7+'3.ROIC'!G6)-('3.ROIC'!G4+'3.ROIC'!G5) -> 0 | H4: =('3.ROIC'!H7+'3.ROIC'!H6)-('3.ROIC'!H4+'3.ROIC'!H5) -> 0 | I4: =('3.ROIC'!I7+'3.ROIC'!I6)-('3.ROIC'!I4+'3.ROIC'!I5) -> 0 | ... K4: =('3.ROIC'!K7+'3.ROIC'!K6)-('3.ROIC'!K4+'3.ROIC'!K5) -> 0 | L4: =IFERROR(L5*TIKR_Cálculos!L40,"") | M4: =IFERROR(M5*TIKR_Cálculos!M40,"") | N4: =IFERROR(N5*TIKR_Cálculos!N40,"") | O4: =IFERROR(O5*TIKR_Cálculos!O40,"") | P4: =IFERROR(P5*TIKR_Cálculos!P40,"")
A5: Deuda neta / EBITDA | B5: =IFERROR('4.Valoración'!B4/TIKR_Cálculos!B40,"") | C5: =IFERROR('4.Valoración'!C4/TIKR_Cálculos!C40,"") | D5: =IFERROR('4.Valoración'!D4/TIKR_Cálculos!D40,"") | E5: =IFERROR('4.Valoración'!E4/TIKR_Cálculos!E40,"") | F5: =IFERROR('4.Valoración'!F4/TIKR_Cálculos!F40,"") | G5: =IFERROR('4.Valoración'!G4/TIKR_Cálculos!G40,"") | H5: =IFERROR('4.Valoración'!H4/TIKR_Cálculos!H40,"") | I5: =IFERROR('4.Valoración'!I4/TIKR_Cálculos!I40,"") | ... K5: =IFERROR('4.Valoración'!K4/TIKR_Cálculos!K40,"") | L5: =IFERROR(AVERAGE('4.Valoración'!B5:K5),"") | M5: =L5 | N5: =M5 | O5: =N5 | P5: =O5 | Q5: AJUSTAR MANUALMENTE
A6: Enterprise Value (EV) | K6: =K3+K4 -> 0 | L6: =IFERROR((L3+L4),"") | M6: =IFERROR((M3+M4),"") | N6: =IFERROR((N3+N4),"") | O6: =IFERROR((O3+O4),"") | P6: =IFERROR((P3+P4),"")
A8: Precio por acción actual
A10: Precio de compra para obtener un retorno anual >=15% | D10: =IF($D$8<>"",IF(K18<15%,F18/2,D8),"")
A12: Múltiplos de valoración | B12: LTM | C12: NTM | D12: Objetivo
A13: P / FFO | B13: =IF($D$8<>"",IFERROR($D$8/('1.FFO'!K5/'1.FFO'!K11),""),"") | C13: =IF($D$8<>"",IFERROR($D$8/('1.FFO'!L5/'1.FFO'!L11),""),"") | D13: =C13
A14: P / AFFO | B14: =IF($D$8<>"",IFERROR($D$8/('1.FFO'!K9/'1.FFO'!K11),""),"") | C14: =IF($D$8<>"",IFERROR($D$8/('1.FFO'!L9/'1.FFO'!L11),""),"") | D14: =C14 | F14: AJUSTAR MANUALMENTE
A16: Precio objetivo | B16: =L2 | C16: =M2 | D16: =N2 | E16: =O2 | F16: =P2 | H16: ="Retorno Anualizado"&CHAR(10)&"valorando por..." -> Retorno Anualizado valorando por... | K16: ="CAGR"&CHAR(10)&"5 años" -> CAGR 5 años
A17: P / FFO | B17: =IF($D$8<>"",IFERROR(('1.FFO'!L5*$D$13)/'1.FFO'!L11,""),"") | C17: =IF($D$8<>"",IFERROR(('1.FFO'!M5*$D$13)/'1.FFO'!M11,""),"") | D17: =IF($D$8<>"",IFERROR(('1.FFO'!N5*$D$13)/'1.FFO'!N11,""),"") | E17: =IF($D$8<>"",IFERROR(('1.FFO'!O5*$D$13)/'1.FFO'!O11,""),"") | F17: =IF($D$8<>"",IFERROR(('1.FFO'!P5*$D$13)/'1.FFO'!P11,""),"") | H17: P / FFO | K17: =IFERROR((F17/$D$8)^(1/5)-1,"")
A18: P / AFFO | B18: =IF($D$8<>"",IFERROR(('1.FFO'!L9*$D$14)/'1.FFO'!L11,""),"") | C18: =IF($D$8<>"",IFERROR(('1.FFO'!M9*$D$14)/'1.FFO'!M11,""),"") | D18: =IF($D$8<>"",IFERROR(('1.FFO'!N9*$D$14)/'1.FFO'!N11,""),"") | E18: =IF($D$8<>"",IFERROR(('1.FFO'!O9*$D$14)/'1.FFO'!O11,""),"") | F18: =IF($D$8<>"",IFERROR(('1.FFO'!P9*$D$14)/'1.FFO'!P11,""),"") | H18: P / AFFO | K18: =IFERROR((F18/$D$8)^(1/5)-1,"")
A19: Promedio | B19: =IFERROR(AVERAGE(B17:B18),"") | C19: =IFERROR(AVERAGE(C17:C18),"") | D19: =IFERROR(AVERAGE(D17:D18),"") | E19: =IFERROR(AVERAGE(E17:E18),"") | F19: =IFERROR(AVERAGE(F17:F18),"") | H19: Promedio | K19: =IFERROR(AVERAGE(K17:K18),"")
A20: Margen de seguridad | B20: =IFERROR((B19/$D$8)-1,"") | C20: =IFERROR((C19/$D$8)-1,"") | D20: =IFERROR((D19/$D$8)-1,"") | E20: =IFERROR((E19/$D$8)-1,"") | F20: =IFERROR((F19/$D$8)-1,"")

Sheet 5.Red Flags
B1: Posibles "Red Flags"
A2: Posibles "red flags" (1) | B2: ='1.FFO'!B$2 | C2: ='1.FFO'!C$2 | D2: ='1.FFO'!D$2 | E2: ='1.FFO'!E$2 | F2: ='1.FFO'!F$2 | G2: ='1.FFO'!G$2 | H2: ='1.FFO'!H$2 | I2: ='1.FFO'!I$2 | ... K2: ='1.FFO'!K$2
A3: Como % de ventas...
A4: Impairments | B4: =IFERROR(ABS(VLOOKUP("Asset Writedown*",'7.TIKR_IS'!$A:$K,COLUMN(#REF!),FALSE)/'1.FFO'!B3),0%)+IFERROR(ABS(VLOOKUP("Impairment of Goodwill*",'7.TIKR_IS'!$A:$K,COLUMN(#REF!),FALSE)/'1.FFO'!B3),0%) -> 0 | C4: =IFERROR(ABS(VLOOKUP("Asset Writedown*",'7.TIKR_IS'!$A:$K,COLUMN(#REF!),FALSE)/'1.FFO'!C3),0%)+IFERROR(ABS(VLOOKUP("Impairment of Goodwill*",'7.TIKR_IS'!$A:$K,COLUMN(#REF!),FALSE)/'1.FFO'!C3),0%) -> 0 | D4: =IFERROR(ABS(VLOOKUP("Asset Writedown*",'7.TIKR_IS'!$A:$K,COLUMN(#REF!),FALSE)/'1.FFO'!D3),0%)+IFERROR(ABS(VLOOKUP("Impairment of Goodwill*",'7.TIKR_IS'!$A:$K,COLUMN(#REF!),FALSE)/'1.FFO'!D3),0%) -> 0 | E4: =IFERROR(ABS(VLOOKUP("Asset Writedown*",'7.TIKR_IS'!$A:$K,COLUMN(#REF!),FALSE)/'1.FFO'!E3),0%)+IFERROR(ABS(VLOOKUP("Impairment of Goodwill*",'7.TIKR_IS'!$A:$K,COLUMN(#REF!),FALSE)/'1.FFO'!E3),0%) -> 0 | F4: =IFERROR(ABS(VLOOKUP("Asset Writedown*",'7.TIKR_IS'!$A:$K,COLUMN(#REF!),FALSE)/'1.FFO'!F3),0%)+IFERROR(ABS(VLOOKUP("Impairment of Goodwill*",'7.TIKR_IS'!$A:$K,COLUMN(#REF!),FALSE)/'1.FFO'!F3),0%) -> 0 | G4: =IFERROR(ABS(VLOOKUP("Asset Writedown*",'7.TIKR_IS'!$A:$K,COLUMN(#REF!),FALSE)/'1.FFO'!G3),0%)+IFERROR(ABS(VLOOKUP("Impairment of Goodwill*",'7.TIKR_IS'!$A:$K,COLUMN(#REF!),FALSE)/'1.FFO'!G3),0%) -> 0 | H4: =IFERROR(ABS(VLOOKUP("Asset Writedown*",'7.TIKR_IS'!$A:$K,COLUMN(#REF!),FALSE)/'1.FFO'!H3),0%)+IFERROR(ABS(VLOOKUP("Impairment of Goodwill*",'7.TIKR_IS'!$A:$K,COLUMN(#REF!),FALSE)/'1.FFO'!H3),0%) -> 0 | I4: =IFERROR(ABS(VLOOKUP("Asset Writedown*",'7.TIKR_IS'!$A:$K,COLUMN(#REF!),FALSE)/'1.FFO'!I3),0%)+IFERROR(ABS(VLOOKUP("Impairment of Goodwill*",'7.TIKR_IS'!$A:$K,COLUMN(#REF!),FALSE)/'1.FFO'!I3),0%) -> 0 | ... K4: =IFERROR(ABS(VLOOKUP("Asset Writedown*",'7.TIKR_IS'!$A:$K,COLUMN(#REF!),FALSE)/'1.FFO'!K3),0%)+IFERROR(ABS(VLOOKUP("Impairment of Goodwill*",'7.TIKR_IS'!$A:$K,COLUMN(#REF!),FALSE)/'1.FFO'!K3),0%) -> 0
A5: Desinversiones | B5: =IFERROR(VLOOKUP("Divestitures*",'9.TIKR_CF'!$A:$K,COLUMN(B2),FALSE)/'1.FFO'!B3,0%) -> 0 | C5: =IFERROR(VLOOKUP("Divestitures*",'9.TIKR_CF'!$A:$K,COLUMN(C2),FALSE)/'1.FFO'!C3,0%) -> 0 | D5: =IFERROR(VLOOKUP("Divestitures*",'9.TIKR_CF'!$A:$K,COLUMN(D2),FALSE)/'1.FFO'!D3,0%) -> 0 | E5: =IFERROR(VLOOKUP("Divestitures*",'9.TIKR_CF'!$A:$K,COLUMN(E2),FALSE)/'1.FFO'!E3,0%) -> 0 | F5: =IFERROR(VLOOKUP("Divestitures*",'9.TIKR_CF'!$A:$K,COLUMN(F2),FALSE)/'1.FFO'!F3,0%) -> 0 | G5: =IFERROR(VLOOKUP("Divestitures*",'9.TIKR_CF'!$A:$K,COLUMN(G2),FALSE)/'1.FFO'!G3,0%) -> 0 | H5: =IFERROR(VLOOKUP("Divestitures*",'9.TIKR_CF'!$A:$K,COLUMN(H2),FALSE)/'1.FFO'!H3,0%) -> 0 | I5: =IFERROR(VLOOKUP("Divestitures*",'9.TIKR_CF'!$A:$K,COLUMN(I2),FALSE)/'1.FFO'!I3,0%) -> 0 | ... K5: =IFERROR(VLOOKUP("Divestitures*",'9.TIKR_CF'!$A:$K,COLUMN(K2),FALSE)/'1.FFO'!K3,0%) -> 0
A6: Pagos en acciones | B6: =IFERROR(VLOOKUP("Stock-based compensation*",'9.TIKR_CF'!$A:$K,COLUMN(B1),FALSE)/'1.FFO'!B2,0%) -> 0 | C6: =IFERROR(VLOOKUP("Stock-based compensation*",'9.TIKR_CF'!$A:$K,COLUMN(C1),FALSE)/'1.FFO'!C2,0%) -> 0 | D6: =IFERROR(VLOOKUP("Stock-based compensation*",'9.TIKR_CF'!$A:$K,COLUMN(D1),FALSE)/'1.FFO'!D2,0%) -> 0 | E6: =IFERROR(VLOOKUP("Stock-based compensation*",'9.TIKR_CF'!$A:$K,COLUMN(E1),FALSE)/'1.FFO'!E2,0%) -> 0 | F6: =IFERROR(VLOOKUP("Stock-based compensation*",'9.TIKR_CF'!$A:$K,COLUMN(F1),FALSE)/'1.FFO'!F2,0%) -> 0 | G6: =IFERROR(VLOOKUP("Stock-based compensation*",'9.TIKR_CF'!$A:$K,COLUMN(G1),FALSE)/'1.FFO'!G2,0%) -> 0 | H6: =IFERROR(VLOOKUP("Stock-based compensation*",'9.TIKR_CF'!$A:$K,COLUMN(H1),FALSE)/'1.FFO'!H2,0%) -> 0 | I6: =IFERROR(VLOOKUP("Stock-based compensation*",'9.TIKR_CF'!$A:$K,COLUMN(I1),FALSE)/'1.FFO'!I2,0%) -> 0 | ... K6: =IFERROR(VLOOKUP("Stock-based compensation*",'9.TIKR_CF'!$A:$K,COLUMN(K1),FALSE)/'1.FFO'!K2,0%) -> 0
A7: Emisión de acciones | B7: =IFERROR(VLOOKUP("Issuance of Common Stock*",'9.TIKR_CF'!$A:$K,COLUMN(B2),FALSE)/'1.FFO'!B3,0%) -> 0 | C7: =IFERROR(VLOOKUP("Issuance of Common Stock*",'9.TIKR_CF'!$A:$K,COLUMN(C2),FALSE)/'1.FFO'!C3,0%) -> 0 | D7: =IFERROR(VLOOKUP("Issuance of Common Stock*",'9.TIKR_CF'!$A:$K,COLUMN(D2),FALSE)/'1.FFO'!D3,0%) -> 0 | E7: =IFERROR(VLOOKUP("Issuance of Common Stock*",'9.TIKR_CF'!$A:$K,COLUMN(E2),FALSE)/'1.FFO'!E3,0%) -> 0 | F7: =IFERROR(VLOOKUP("Issuance of Common Stock*",'9.TIKR_CF'!$A:$K,COLUMN(F2),FALSE)/'1.FFO'!F3,0%) -> 0 | G7: =IFERROR(VLOOKUP("Issuance of Common Stock*",'9.TIKR_CF'!$A:$K,COLUMN(G2),FALSE)/'1.FFO'!G3,0%) -> 0 | H7: =IFERROR(VLOOKUP("Issuance of Common Stock*",'9.TIKR_CF'!$A:$K,COLUMN(H2),FALSE)/'1.FFO'!H3,0%) -> 0 | I7: =IFERROR(VLOOKUP("Issuance of Common Stock*",'9.TIKR_CF'!$A:$K,COLUMN(I2),FALSE)/'1.FFO'!I3,0%) -> 0 | ... K7: =IFERROR(VLOOKUP("Issuance of Common Stock*",'9.TIKR_CF'!$A:$K,COLUMN(K2),FALSE)/'1.FFO'!K3,0%) -> 0
A9: Posibles "red flags" (2) | B9: Total
A10: # de años con...
A11: Decrecimiento de ventas | B11: =TIKR_Cálculos!L31 -> 0
A12: Decrecimiento de margen FFO | B12: =TIKR_Cálculos!L32 -> 0
A13: AFFO negativo | B13: =TIKR_Cálculos!L33 -> 0
A14: ROIC "Pobre" (<10%) | B14: =TIKR_Cálculos!L34 -> 0
A15: Ratio Deuda Neta / EBITDA elevado (>5x) | B15: =TIKR_Cálculos!L35 -> 0

Sheet 7.TIKR_IS

Sheet 8.TIKR_BS

Sheet 9.TIKR_CF

Sheet 10.Glosario
B2: Beneficio "contable" | C2: Opción 1 | D2: Opción 2 | E2: Opción 3
B3: EBITDA | C3: Net Income + Interests (net) + Taxes + Depreciation + Amortization | D3: Ingresos - Gastos de Explotación | E3: EBIT + D&A
B4: EBIT | C4: Net Income + Interests (net) + Taxes | D4: Ingresos - Gastos de Explotación - D&A | E4: EBITDA - D&A
B5: EBT | C5: Net Income + Interests (net) | D5: Ingresos - Gastos de Explotación - D&A - Interests (net) - Other financial items | E5: EBIT - Interests (net) - Other financial items
B6: Net Income | C6: Ingresos - Gastos de Explotación - D&A - Interests (net) - Other financial items - taxes | D6: EBT - Taxes
B7: EPS | C7: Net Income / Nº total de acciones diluídas
B9: Valoración | C9: Opción 1 | D9: Opción 2 | E9: Opción 3
B10: Net Debt (Deuda Financiera Neta) | C10: Short-Term Debt + Short-Term Borrowings + Long-Term Debt + Long-Term Borrowings - Cash
B11: Market Cap. | C11: Nº de acciones totales diluídas x Precio por acción
B12: Enterprise Value (EV) | C12: Market Cap + Net Debt | D12: Market Cap - Caja Neta
B13: EV / EBITDA | C13: Enterprise Value / EBITDA
B14: EV / EBIT | C14: Enterprise Value / EBIT
B15: EV / FCF | C15: Enterprise Value / FCF
B16: PER | C16: Market Cap. / Beneficio Neto | D16: Precio por acción / EPS
B18: Márgenes % | C18: Opción 1 | D18: Opción 2 | E18: Opción 3
B19: EBITDA | C19: EBITDA / Ventas x 100
B20: EBIT | C20: EBIT / Ventas x 100
B21: Neto | C21: Net Income / Ventas x 100
B22: FCF | C22: FCF / Ventas x 100
B24: Rentabilidad % | C24: Opción 1 | D24: Opción 2 | E24: Opción 3
B25: ROIC | C25: EBIT * (1 - T) / Capital Invertido | D25: Capital Invertido = Equity + Deuda financiera total + Operating Leases Total – Marketable Securities
B26: ROE | C26: Net Income / Equity
B27: ROA | C27: Net Income / Total Assets
B29: FCF | C29: Opción 1 | D29: Opción 2 | E29: Opción 3
B30: Working Capital (WC) | C30: Inventarios + Cuentas a Cobrar de Clientes - Cuentas a pagar a proveedores | D30: Inventories + Accounts Receivable + Accounts Payable | E30: En empresas ligeras de activos podemos restar también la partida "Unearned revenue", tanto "Current" como "Non-current"
B31: Variación de WC (CWC) | C31: WC año más reciente - WC año anterior. (P.ej.: WC 2021 - WC 2020) | D31: Si la CWC es positiva DISMINUYE el FCF ya que la empresa tiene que financiar ese aumento de inventarios y/o de cuentas a cobrar | E31: Si la CWC es negativa AUMENTA el FCF, ya que se 'libera'' capital, es como si la empresa vendiese inventarios y/o cobrase más facturas a clientes
B32: CapEx de Mantenimiento | C32: Si la directiva no proporciona un capex de mantenimiento exacto, usaremos la D&A como "atajo" para el capex de mantenimiento en los casos que el capex total sea notablemente superior a la D&A | D32: Otra opción es usar el % CapEx / Sales del sector, pero esto lleva trabajo, no hay una página que recoja este ratio para todas y cada una de los cientos de industrias que componen todos los sectores
B33: FCF | C33: EBITDA - Interests (net) - Taxes - CapEx Mantenimiento - Variación de WC

Sheet TIKR_Cálculos
A3: Valoración | B3: ='1.FFO'!L2 | C3: ='1.FFO'!M2 | D3: ='1.FFO'!N2 | E3: ='1.FFO'!O2 | F3: ='1.FFO'!P2
A4: Precio actual | B4: ='4.Valoración'!$D$8 -> 0 | C4: ='4.Valoración'!$D$8 -> 0 | D4: ='4.Valoración'!$D$8 -> 0 | E4: ='4.Valoración'!$D$8 -> 0 | F4: ='4.Valoración'!$D$8 -> 0
A6: Deuda Neta | B6: ='1.FFO'!K2
A7: % Corto plazo | B7: =IFERROR(SUM('3.ROIC'!$B$6:$K$6)/SUM('3.ROIC'!$B$6:$K$7),0) -> 0
A8: % Largo plazo | B8: =IF(B7=0,0,1-B7) -> 0
A9: Caja histórica acumulada | B9: =SUM('3.ROIC'!B4:K5) -> 0
A10: Marketable securities acumulados | B10: =SUM('3.ROIC'!B5:K5) -> 0
A11: Deuda histórica acumulada | B11: =SUM('3.ROIC'!B6:K7) -> 0
A12: Deuda neta histórica acumulada | B12: =B11-B9 -> 0
A13: Interest income acumulado | B13: =SUM('1.FFO'!#REF!) -> #REF!
A14: Interest expense acumulado | B14: =SUM('1.FFO'!#REF!) -> #REF!
A15: % Interest income promedio | B15: =IFERROR(B13/B10,0) -> 0
A16: % Interest expense promedio | B16: =ABS(SUM('1.FFO'!#REF!))/B11 -> #REF!
A18: Asignación de capital | B18: ='1.FFO'!B2 | C18: ='1.FFO'!C2 | D18: ='1.FFO'!D2 | E18: ='1.FFO'!E2 | F18: ='1.FFO'!F2 | G18: ='1.FFO'!G2 | H18: ='1.FFO'!H2 | I18: ='1.FFO'!I2 | ... K18: ='1.FFO'!K2 | L18: Acumulado
A19: Dividendos | B19: =IFERROR(ABS(VLOOKUP("Common & Preferred Stock Dividends Paid*",'9.TIKR_CF'!$A:$K,COLUMN(B3),FALSE)),"0") -> 0 | C19: =IFERROR(ABS(VLOOKUP("Common & Preferred Stock Dividends Paid*",'9.TIKR_CF'!$A:$K,COLUMN(C3),FALSE)),"0") -> 0 | D19: =IFERROR(ABS(VLOOKUP("Common & Preferred Stock Dividends Paid*",'9.TIKR_CF'!$A:$K,COLUMN(D3),FALSE)),"0") -> 0 | E19: =IFERROR(ABS(VLOOKUP("Common & Preferred Stock Dividends Paid*",'9.TIKR_CF'!$A:$K,COLUMN(E3),FALSE)),"0") -> 0 | F19: =IFERROR(ABS(VLOOKUP("Common & Preferred Stock Dividends Paid*",'9.TIKR_CF'!$A:$K,COLUMN(F3),FALSE)),"0") -> 0 | G19: =IFERROR(ABS(VLOOKUP("Common & Preferred Stock Dividends Paid*",'9.TIKR_CF'!$A:$K,COLUMN(G3),FALSE)),"0") -> 0 | H19: =IFERROR(ABS(VLOOKUP("Common & Preferred Stock Dividends Paid*",'9.TIKR_CF'!$A:$K,COLUMN(H3),FALSE)),"0") -> 0 | I19: =IFERROR(ABS(VLOOKUP("Common & Preferred Stock Dividends Paid*",'9.TIKR_CF'!$A:$K,COLUMN(I3),FALSE)),"0") -> 0 | ... K19: =IFERROR(ABS(VLOOKUP("Common & Preferred Stock Dividends Paid*",'9.TIKR_CF'!$A:$K,COLUMN(K3),FALSE)),"0") -> 0 | L19: =SUM(B19:K19) -> 0
A20: Recompras | B20: =IFERROR(ABS(VLOOKUP("Repurchase of Common Stock*",'9.TIKR_CF'!$A:$K,COLUMN(B4),FALSE)),"0") -> 0 | C20: =IFERROR(ABS(VLOOKUP("Repurchase of Common Stock*",'9.TIKR_CF'!$A:$K,COLUMN(C4),FALSE)),"0") -> 0 | D20: =IFERROR(ABS(VLOOKUP("Repurchase of Common Stock*",'9.TIKR_CF'!$A:$K,COLUMN(D4),FALSE)),"0") -> 0 | E20: =IFERROR(ABS(VLOOKUP("Repurchase of Common Stock*",'9.TIKR_CF'!$A:$K,COLUMN(E4),FALSE)),"0") -> 0 | F20: =IFERROR(ABS(VLOOKUP("Repurchase of Common Stock*",'9.TIKR_CF'!$A:$K,COLUMN(F4),FALSE)),"0") -> 0 | G20: =IFERROR(ABS(VLOOKUP("Repurchase of Common Stock*",'9.TIKR_CF'!$A:$K,COLUMN(G4),FALSE)),"0") -> 0 | H20: =IFERROR(ABS(VLOOKUP("Repurchase of Common Stock*",'9.TIKR_CF'!$A:$K,COLUMN(H4),FALSE)),"0") -> 0 | I20: =IFERROR(ABS(VLOOKUP("Repurchase of Common Stock*",'9.TIKR_CF'!$A:$K,COLUMN(I4),FALSE)),"0") -> 0 | ... K20: =IFERROR(ABS(VLOOKUP("Repurchase of Common Stock*",'9.TIKR_CF'!$A:$K,COLUMN(K4),FALSE)),"0") -> 0 | L20: =SUM(B20:K20) -> 0
A21: Adquisiciones (Crecimiento inorgánico) | B21: =ABS(IFERROR(VLOOKUP("Cash Acquisitions*",'9.TIKR_CF'!$A:$K,COLUMN(B21),FALSE),"0")) -> 0 | C21: =ABS(IFERROR(VLOOKUP("Cash Acquisitions*",'9.TIKR_CF'!$A:$K,COLUMN(C21),FALSE),"0")) -> 0 | D21: =ABS(IFERROR(VLOOKUP("Cash Acquisitions*",'9.TIKR_CF'!$A:$K,COLUMN(D21),FALSE),"0")) -> 0 | E21: =ABS(IFERROR(VLOOKUP("Cash Acquisitions*",'9.TIKR_CF'!$A:$K,COLUMN(E21),FALSE),"0")) -> 0 | F21: =ABS(IFERROR(VLOOKUP("Cash Acquisitions*",'9.TIKR_CF'!$A:$K,COLUMN(F21),FALSE),"0")) -> 0 | G21: =ABS(IFERROR(VLOOKUP("Cash Acquisitions*",'9.TIKR_CF'!$A:$K,COLUMN(G21),FALSE),"0")) -> 0 | H21: =ABS(IFERROR(VLOOKUP("Cash Acquisitions*",'9.TIKR_CF'!$A:$K,COLUMN(H21),FALSE),"0")) -> 0 | I21: =ABS(IFERROR(VLOOKUP("Cash Acquisitions*",'9.TIKR_CF'!$A:$K,COLUMN(I21),FALSE),"0")) -> 0 | ... K21: =ABS(IFERROR(VLOOKUP("Cash Acquisitions*",'9.TIKR_CF'!$A:$K,COLUMN(K21),FALSE),"0")) -> 0 | L21: =SUM(B21:K21) -> 0
A22: Repago de deuda neto | B22: =IFERROR(ABS(VLOOKUP("Total Debt Repaid*",'9.TIKR_CF'!$A:$K,COLUMN(B8),FALSE))-VLOOKUP("Total Debt Issued*",'9.TIKR_CF'!$A:$K,COLUMN(B8),FALSE),0) -> 0 | C22: =IFERROR(ABS(VLOOKUP("Total Debt Repaid*",'9.TIKR_CF'!$A:$K,COLUMN(C8),FALSE))-VLOOKUP("Total Debt Issued*",'9.TIKR_CF'!$A:$K,COLUMN(C8),FALSE),0) -> 0 | D22: =IFERROR(ABS(VLOOKUP("Total Debt Repaid*",'9.TIKR_CF'!$A:$K,COLUMN(D8),FALSE))-VLOOKUP("Total Debt Issued*",'9.TIKR_CF'!$A:$K,COLUMN(D8),FALSE),0) -> 0 | E22: =IFERROR(ABS(VLOOKUP("Total Debt Repaid*",'9.TIKR_CF'!$A:$K,COLUMN(E8),FALSE))-VLOOKUP("Total Debt Issued*",'9.TIKR_CF'!$A:$K,COLUMN(E8),FALSE),0) -> 0 | F22: =IFERROR(ABS(VLOOKUP("Total Debt Repaid*",'9.TIKR_CF'!$A:$K,COLUMN(F8),FALSE))-VLOOKUP("Total Debt Issued*",'9.TIKR_CF'!$A:$K,COLUMN(F8),FALSE),0) -> 0 | G22: =IFERROR(ABS(VLOOKUP("Total Debt Repaid*",'9.TIKR_CF'!$A:$K,COLUMN(G8),FALSE))-VLOOKUP("Total Debt Issued*",'9.TIKR_CF'!$A:$K,COLUMN(G8),FALSE),0) -> 0 | H22: =IFERROR(ABS(VLOOKUP("Total Debt Repaid*",'9.TIKR_CF'!$A:$K,COLUMN(H8),FALSE))-VLOOKUP("Total Debt Issued*",'9.TIKR_CF'!$A:$K,COLUMN(H8),FALSE),0) -> 0 | I22: =IFERROR(ABS(VLOOKUP("Total Debt Repaid*",'9.TIKR_CF'!$A:$K,COLUMN(I8),FALSE))-VLOOKUP("Total Debt Issued*",'9.TIKR_CF'!$A:$K,COLUMN(I8),FALSE),0) -> 0 | ... K22: =IFERROR(ABS(VLOOKUP("Total Debt Repaid*",'9.TIKR_CF'!$A:$K,COLUMN(K8),FALSE))-VLOOKUP("Total Debt Issued*",'9.TIKR_CF'!$A:$K,COLUMN(K8),FALSE),0) -> 0 | L22: =SUM(B22:K22) -> 0
A24: Crecimiento
B25: ='1.FFO'!C$2 | C25: ='1.FFO'!D$2 | D25: ='1.FFO'!E$2 | E25: ='1.FFO'!F$2 | F25: ='1.FFO'!G$2 | G25: ='1.FFO'!H$2 | H25: ='1.FFO'!I$2 | I25: ='1.FFO'!J$2 | J25: ='1.FFO'!K$2
A26: Ventas | B26: ='1.FFO'!C4 | C26: ='1.FFO'!D4 | D26: ='1.FFO'!E4 | E26: ='1.FFO'!F4 | F26: ='1.FFO'!G4 | G26: ='1.FFO'!H4 | H26: ='1.FFO'!I4 | I26: ='1.FFO'!J4 | J26: ='1.FFO'!K4
A27: EPS
A30: Posibles red flags | B30: ='1.FFO'!B2 | C30: ='1.FFO'!C2 | D30: ='1.FFO'!D2 | E30: ='1.FFO'!E2 | F30: ='1.FFO'!F2 | G30: ='1.FFO'!G2 | H30: ='1.FFO'!H2 | I30: ='1.FFO'!I2 | ... K30: ='1.FFO'!K2 | L30: Total
A31: Decrecimiento ventas | C31: =IF('1.FFO'!C4<0,1,0) -> 0 | D31: =IF('1.FFO'!D4<0,1,0) -> 0 | E31: =IF('1.FFO'!E4<0,1,0) -> 0 | F31: =IF('1.FFO'!F4<0,1,0) -> 0 | G31: =IF('1.FFO'!G4<0,1,0) -> 0 | H31: =IF('1.FFO'!H4<0,1,0) -> 0 | I31: =IF('1.FFO'!I4<0,1,0) -> 0 | J31: =IF('1.FFO'!J4<0,1,0) -> 0 | K31: =IF('1.FFO'!K4<0,1,0) -> 0 | L31: =SUM(B31:K31) -> 0
A32: Decrecimiento margen FFO | C32: =IF('1.FFO'!C6<'1.FFO'!B6,1,0) -> 0 | D32: =IF('1.FFO'!D6<'1.FFO'!C6,1,0) -> 0 | E32: =IF('1.FFO'!E6<'1.FFO'!D6,1,0) -> 0 | F32: =IF('1.FFO'!F6<'1.FFO'!E6,1,0) -> 0 | G32: =IF('1.FFO'!G6<'1.FFO'!F6,1,0) -> 0 | H32: =IF('1.FFO'!H6<'1.FFO'!G6,1,0) -> 0 | I32: =IF('1.FFO'!I6<'1.FFO'!H6,1,0) -> 0 | J32: =IF('1.FFO'!J6<'1.FFO'!I6,1,0) -> 0 | K32: =IF('1.FFO'!K6<'1.FFO'!J6,1,0) -> 0 | L32: =SUM(B32:K32) -> 0
A33: AFFO negativo | B33: =IF('1.FFO'!B9<0,1,0) -> 0 | C33: =IF('1.FFO'!C9<0,1,0) -> 0 | D33: =IF('1.FFO'!D9<0,1,0) -> 0 | E33: =IF('1.FFO'!E9<0,1,0) -> 0 | F33: =IF('1.FFO'!F9<0,1,0) -> 0 | G33: =IF('1.FFO'!G9<0,1,0) -> 0 | H33: =IF('1.FFO'!H9<0,1,0) -> 0 | I33: =IF('1.FFO'!I9<0,1,0) -> 0 | ... K33: =IF('1.FFO'!K9<0,1,0) -> 0 | L33: =SUM(B33:K33) -> 0
A34: ROIC "Pobre" (<10%) | B34: =IF('3.ROIC'!B14<10%,1,0) -> 0 | C34: =IF('3.ROIC'!C14<10%,1,0) -> 0 | D34: =IF('3.ROIC'!D14<10%,1,0) -> 0 | E34: =IF('3.ROIC'!E14<10%,1,0) -> 0 | F34: =IF('3.ROIC'!F14<10%,1,0) -> 0 | G34: =IF('3.ROIC'!G14<10%,1,0) -> 0 | H34: =IF('3.ROIC'!H14<10%,1,0) -> 0 | I34: =IF('3.ROIC'!I14<10%,1,0) -> 0 | ... K34: =IF('3.ROIC'!K14<10%,1,0) -> 0 | L34: =SUM(B34:K34) -> 0
A35: Ratio Deuda Neta / EBITDA elevado (>5x) | B35: =IF('4.Valoración'!B5<>"",IF('4.Valoración'!B5>5,1,0),0) -> 0 | C35: =IF('4.Valoración'!C5<>"",IF('4.Valoración'!C5>5,1,0),0) -> 0 | D35: =IF('4.Valoración'!D5<>"",IF('4.Valoración'!D5>5,1,0),0) -> 0 | E35: =IF('4.Valoración'!E5<>"",IF('4.Valoración'!E5>5,1,0),0) -> 0 | F35: =IF('4.Valoración'!F5<>"",IF('4.Valoración'!F5>5,1,0),0) -> 0 | G35: =IF('4.Valoración'!G5<>"",IF('4.Valoración'!G5>5,1,0),0) -> 0 | H35: =IF('4.Valoración'!H5<>"",IF('4.Valoración'!H5>5,1,0),0) -> 0 | I35: =IF('4.Valoración'!I5<>"",IF('4.Valoración'!I5>5,1,0),0) -> 0 | ... K35: =IF('4.Valoración'!K5<>"",IF('4.Valoración'!K5>5,1,0),0) -> 0 | L35: =SUM(B35:K35) -> 0
B39: =B18 | C39: =C18 | D39: =D18 | E39: =E18 | F39: =F18 | G39: =G18 | H39: =H18 | I39: =I18 | ... K39: =K18 | L39: ='1.FFO'!L2 | M39: ='1.FFO'!M2 | N39: ='1.FFO'!N2 | O39: ='1.FFO'!O2 | P39: ='1.FFO'!P2
A40: EBITDA | B40: =IFERROR(ABS(VLOOKUP("EBITDA*",'7.TIKR_IS'!$A:$K,COLUMN(B3),FALSE)),"0") -> 0 | C40: =IFERROR(ABS(VLOOKUP("EBITDA*",'7.TIKR_IS'!$A:$K,COLUMN(C3),FALSE)),"0") -> 0 | D40: =IFERROR(ABS(VLOOKUP("EBITDA*",'7.TIKR_IS'!$A:$K,COLUMN(D3),FALSE)),"0") -> 0 | E40: =IFERROR(ABS(VLOOKUP("EBITDA*",'7.TIKR_IS'!$A:$K,COLUMN(E3),FALSE)),"0") -> 0 | F40: =IFERROR(ABS(VLOOKUP("EBITDA*",'7.TIKR_IS'!$A:$K,COLUMN(F3),FALSE)),"0") -> 0 | G40: =IFERROR(ABS(VLOOKUP("EBITDA*",'7.TIKR_IS'!$A:$K,COLUMN(G3),FALSE)),"0") -> 0 | H40: =IFERROR(ABS(VLOOKUP("EBITDA*",'7.TIKR_IS'!$A:$K,COLUMN(H3),FALSE)),"0") -> 0 | I40: =IFERROR(ABS(VLOOKUP("EBITDA*",'7.TIKR_IS'!$A:$K,COLUMN(I3),FALSE)),"0") -> 0 | ... K40: =IFERROR(ABS(VLOOKUP("EBITDA*",'7.TIKR_IS'!$A:$K,COLUMN(K3),FALSE)),"0") -> 0 | L40: =IFERROR(L41*'1.FFO'!L3,"") | M40: =IFERROR(M41*'1.FFO'!M3,"") | N40: =IFERROR(N41*'1.FFO'!N3,"") | O40: =IFERROR(O41*'1.FFO'!O3,"") | P40: =IFERROR(P41*'1.FFO'!P3,"")
A41: EBITDA margin % | B41: =IFERROR(B40/'1.FFO'!B3,"") | C41: =IFERROR(C40/'1.FFO'!C3,"") | D41: =IFERROR(D40/'1.FFO'!D3,"") | E41: =IFERROR(E40/'1.FFO'!E3,"") | F41: =IFERROR(F40/'1.FFO'!F3,"") | G41: =IFERROR(G40/'1.FFO'!G3,"") | H41: =IFERROR(H40/'1.FFO'!H3,"") | I41: =IFERROR(I40/'1.FFO'!I3,"") | ... K41: =IFERROR(K40/'1.FFO'!K3,"") | L41: =K41 | M41: =L41 | N41: =M41 | O41: =N41 | P41: =O41
A42: Net Income | B42: =IFERROR(ABS(VLOOKUP("Net Income*",'7.TIKR_IS'!$A:$K,COLUMN(B3),FALSE)),"0") -> 0 | C42: =IFERROR(ABS(VLOOKUP("Net Income*",'7.TIKR_IS'!$A:$K,COLUMN(C3),FALSE)),"0") -> 0 | D42: =IFERROR(ABS(VLOOKUP("Net Income*",'7.TIKR_IS'!$A:$K,COLUMN(D3),FALSE)),"0") -> 0 | E42: =IFERROR(ABS(VLOOKUP("Net Income*",'7.TIKR_IS'!$A:$K,COLUMN(E3),FALSE)),"0") -> 0 | F42: =IFERROR(ABS(VLOOKUP("Net Income*",'7.TIKR_IS'!$A:$K,COLUMN(F3),FALSE)),"0") -> 0 | G42: =IFERROR(ABS(VLOOKUP("Net Income*",'7.TIKR_IS'!$A:$K,COLUMN(G3),FALSE)),"0") -> 0 | H42: =IFERROR(ABS(VLOOKUP("Net Income*",'7.TIKR_IS'!$A:$K,COLUMN(H3),FALSE)),"0") -> 0 | I42: =IFERROR(ABS(VLOOKUP("Net Income*",'7.TIKR_IS'!$A:$K,COLUMN(I3),FALSE)),"0") -> 0 | ... K42: =IFERROR(ABS(VLOOKUP("Net Income*",'7.TIKR_IS'!$A:$K,COLUMN(K3),FALSE)),"0") -> 0 | L42: =IFERROR(L43*'1.FFO'!L3,"") | M42: =IFERROR(M43*'1.FFO'!M3,"") | N42: =IFERROR(N43*'1.FFO'!N3,"") | O42: =IFERROR(O43*'1.FFO'!O3,"") | P42: =IFERROR(P43*'1.FFO'!P3,"")
A43: Net margin % | B43: =IFERROR(B42/'1.FFO'!B3,"") | C43: =IFERROR(C42/'1.FFO'!C3,"") | D43: =IFERROR(D42/'1.FFO'!D3,"") | E43: =IFERROR(E42/'1.FFO'!E3,"") | F43: =IFERROR(F42/'1.FFO'!F3,"") | G43: =IFERROR(G42/'1.FFO'!G3,"") | H43: =IFERROR(H42/'1.FFO'!H3,"") | I43: =IFERROR(I42/'1.FFO'!I3,"") | ... K43: =IFERROR(K42/'1.FFO'!K3,"") | L43: =K43 | M43: =L43 | N43: =M43 | O43: =N43 | P43: =O43
A44: Net Income after dividends | B44: =B42*(1-90%) -> 0 | C44: =C42*(1-90%) -> 0 | D44: =D42*(1-90%) -> 0 | E44: =E42*(1-90%) -> 0 | F44: =F42*(1-90%) -> 0 | G44: =G42*(1-90%) -> 0 | H44: =H42*(1-90%) -> 0 | I44: =I42*(1-90%) -> 0 | ... P44: =P42*(1-90%) -> #VALUE!
