Workbook

Sheet Instrucciones
B2: Instrucciones de uso
B4: - Modifica solo las celdas con fondo AZUL FLOJO. Los datos "clave" que debes modificar manualmente para la valoración están marcados con números en NARANJA (Hojas 1, 3 y 4)
B6: - Debes introducir todas las partidas con el MISMO SIGNO QUE EN TIKR (Número negativo = SALIDA DE CAJA. Número positivo = ENTRADA DE CAJA)
B8: - Opcional: Para que la plantilla obtenga los datos desde TIKR debes darle al botón "Copy Table" de cada estado financiero en TIKR y pegarlos en la celda A1 de las hojas 7 (IS), 8 (BS) y 9 (CF)
B10: - OJO: Solo es válido para TIKR en INGLÉS, y es recomendable pegar los datos con "formato de destino"
B12: - Si no te aparece el botón "Copy table", debes seleccionar a mano los datos. Te sitúas con el cursor en la esquina izquierda superior de la tabla de TIKR y desde la franja negra "Income Statement | TIKR.com", arrastras hacia abajo para seleccionar todos los datos de la tabla. Después copias y pegas en la plantilla, como siempre.
B14: - Si no captura bien los datos, revisa que el separador decimal de tu aplicación de hoja de cálculo coincida con TIKR. También puedes probar a ocultar los decimales en TIKR ("Decimals to display" => 0) y pegar de nuevo los datos
B16: Novedades plantilla v2024.1
B18: - Nueva plantilla de valoración adaptada para empresas financieras
B20: - Hoja 1.IS: P&L adaptada para financieras. También se han añadido ratios de rentabilidad (ROA y ROE) y apalancamiento (Deuda / Equity)
B22: - Hoja 4.Valoración: Valoración por P/B y PER

Sheet 1.IS
B1: Income Statement
A2: (millones, excepto EPS) | B2: =IFERROR(IF(VLOOKUP("Income Statement*",'7.TIKR_IS'!$A:$K,COLUMN(B3),FALSE)="","",IFERROR(YEAR(VLOOKUP("Income Statement*",'7.TIKR_IS'!$A:$K,COLUMN(B3),FALSE)),"2014")),"") | C2: =IFERROR(IF(VLOOKUP("Income Statement*",'7.TIKR_IS'!$A:$K,COLUMN(C3),FALSE)="","",IFERROR(YEAR(VLOOKUP("Income Statement*",'7.TIKR_IS'!$A:$K,COLUMN(C3),FALSE)),B2+1)),"") | D2: =IFERROR(IF(VLOOKUP("Income Statement*",'7.TIKR_IS'!$A:$K,COLUMN(D3),FALSE)="","",IFERROR(YEAR(VLOOKUP("Income Statement*",'7.TIKR_IS'!$A:$K,COLUMN(D3),FALSE)),C2+1)),"") | E2: =IFERROR(IF(VLOOKUP("Income Statement*",'7.TIKR_IS'!$A:$K,COLUMN(E3),FALSE)="","",IFERROR(YEAR(VLOOKUP("Income Statement*",'7.TIKR_IS'!$A:$K,COLUMN(E3),FALSE)),D2+1)),"") | F2: =IFERROR(IF(VLOOKUP("Income Statement*",'7.TIKR_IS'!$A:$K,COLUMN(F3),FALSE)="","",IFERROR(YEAR(VLOOKUP("Income Statement*",'7.TIKR_IS'!$A:$K,COLUMN(F3),FALSE)),E2+1)),"") | G2: =IFERROR(IF(VLOOKUP("Income Statement*",'7.TIKR_IS'!$A:$K,COLUMN(G3),FALSE)="","",IFERROR(YEAR(VLOOKUP("Income Statement*",'7.TIKR_IS'!$A:$K,COLUMN(G3),FALSE)),F2+1)),"") | H2: =IFERROR(IF(VLOOKUP("Income Statement*",'7.TIKR_IS'!$A:$K,COLUMN(H3),FALSE)="","",IFERROR(YEAR(VLOOKUP("Income Statement*",'7.TIKR_IS'!$A:$K,COLUMN(H3),FALSE)),G2+1)),"") | I2: =IFERROR(IF(VLOOKUP("Income Statement*",'7.TIKR_IS'!$A:$K,COLUMN(I3),FALSE)="","",IFERROR(YEAR(VLOOKUP("Income Statement*",'7.TIKR_IS'!$A:$K,COLUMN(I3),FALSE)),H2+1)),"") | J2: =IFERROR(IF(VLOOKUP("Income Statement*",'7.TIKR_IS'!$A:$K,COLUMN(J3),FALSE)="","",IFERROR(YEAR(VLOOKUP("Income Statement*",'7.TIKR_IS'!$A:$K,COLUMN(J3),FALSE)),I2+1)),"") | K2: =IFERROR(IF(VLOOKUP("Income Statement*",'7.TIKR_IS'!$A:$K,COLUMN(K3),FALSE)="","",IFERROR(YEAR(VLOOKUP("Income Statement*",'7.TIKR_IS'!$A:$K,COLUMN(K3),FALSE)),J2+1)),"") | L2: =IF(K2<>"",(K2+1)&"e","") | M2: =IF(L2<>"",(LEFT(L2,4)+1)&"e","") | N2: =IF(M2<>"",(LEFT(M2,4)+1)&"e","") | O2: =IF(N2<>"",(LEFT(N2,4)+1)&"e","") | P2: =IF(O2<>"",(LEFT(O2,4)+1)&"e","") | R2: Proyección a futuro | S2: ="Promedio "&CHAR(10)&B2&" - "&K2 -> Promedio - | T2: ="Estimaciones "&CHAR(10)&L2&" - "&P2 -> Estimaciones -
A3: Sales | B3: =IFERROR(VLOOKUP("Total Revenues*",'7.TIKR_IS'!$A:$K,COLUMN(B3),FALSE),"0") -> 0 | C3: =IFERROR(VLOOKUP("Total Revenues*",'7.TIKR_IS'!$A:$K,COLUMN(C3),FALSE),"0") -> 0 | D3: =IFERROR(VLOOKUP("Total Revenues*",'7.TIKR_IS'!$A:$K,COLUMN(D3),FALSE),"0") -> 0 | E3: =IFERROR(VLOOKUP("Total Revenues*",'7.TIKR_IS'!$A:$K,COLUMN(E3),FALSE),"0") -> 0 | F3: =IFERROR(VLOOKUP("Total Revenues*",'7.TIKR_IS'!$A:$K,COLUMN(F3),FALSE),"0") -> 0 | G3: =IFERROR(VLOOKUP("Total Revenues*",'7.TIKR_IS'!$A:$K,COLUMN(G3),FALSE),"0") -> 0 | H3: =IFERROR(VLOOKUP("Total Revenues*",'7.TIKR_IS'!$A:$K,COLUMN(H3),FALSE),"0") -> 0 | I3: =IFERROR(VLOOKUP("Total Revenues*",'7.TIKR_IS'!$A:$K,COLUMN(I3),FALSE),"0") -> 0 | ... K3: =IFERROR(VLOOKUP("Total Revenues*",'7.TIKR_IS'!$A:$K,COLUMN(K3),FALSE),"0") -> 0 | L3: =IFERROR((K3*$T$3)+K3,"") | M3: =IFERROR((L3*$T$3)+L3,"") | N3: =IFERROR((M3*$T$3)+M3,"") | O3: =IFERROR((N3*$T$3)+N3,"") | P3: =IFERROR((O3*$T$3)+O3,"") | R3: Crecimiento en Ventas | S3: =IFERROR(AVERAGE(C4:K4),"") | T3: =S3
A4: Y/Y Growth % | C4: =IFERROR((C3-B3)/B3,"") | D4: =IFERROR((D3-C3)/C3,"") | E4: =IFERROR((E3-D3)/D3,"") | F4: =IFERROR((F3-E3)/E3,"") | G4: =IFERROR((G3-F3)/F3,"") | H4: =IFERROR((H3-G3)/G3,"") | I4: =IFERROR((I3-H3)/H3,"") | J4: =IFERROR((J3-I3)/I3,"") | K4: =IFERROR((K3-J3)/J3,"") | L4: =$T$3 | M4: =$T$3 | N4: =$T$3 | O4: =$T$3 | P4: =$T$3 | R4: Margen EBT | S4: =IFERROR(AVERAGE(B6:K6),"") | T4: =S4
A5: Earnings Before Taxes (EBT) | B5: =IFERROR(VLOOKUP("EBT Incl. Unusual Items*",'7.TIKR_IS'!$A:$K,COLUMN(B2),FALSE),"0") -> 0 | C5: =IFERROR(VLOOKUP("EBT Incl. Unusual Items*",'7.TIKR_IS'!$A:$K,COLUMN(C2),FALSE),"0") -> 0 | D5: =IFERROR(VLOOKUP("EBT Incl. Unusual Items*",'7.TIKR_IS'!$A:$K,COLUMN(D2),FALSE),"0") -> 0 | E5: =IFERROR(VLOOKUP("EBT Incl. Unusual Items*",'7.TIKR_IS'!$A:$K,COLUMN(E2),FALSE),"0") -> 0 | F5: =IFERROR(VLOOKUP("EBT Incl. Unusual Items*",'7.TIKR_IS'!$A:$K,COLUMN(F2),FALSE),"0") -> 0 | G5: =IFERROR(VLOOKUP("EBT Incl. Unusual Items*",'7.TIKR_IS'!$A:$K,COLUMN(G2),FALSE),"0") -> 0 | H5: =IFERROR(VLOOKUP("EBT Incl. Unusual Items*",'7.TIKR_IS'!$A:$K,COLUMN(H2),FALSE),"0") -> 0 | I5: =IFERROR(VLOOKUP("EBT Incl. Unusual Items*",'7.TIKR_IS'!$A:$K,COLUMN(I2),FALSE),"0") -> 0 | ... K5: =IFERROR(VLOOKUP("EBT Incl. Unusual Items*",'7.TIKR_IS'!$A:$K,COLUMN(K2),FALSE),"0") -> 0 | L5: =IFERROR(L3*$T$4,"") | M5: =IFERROR(M3*$T$4,"") | N5: =IFERROR(N3*$T$4,"") | O5: =IFERROR(O3*$T$4,"") | P5: =IFERROR(P3*$T$4,"") | R5: Effective Tax rate | S5: =IFERROR(AVERAGE(B8:K8),"") | T5: =S5
A6: EBT margin % | B6: =IFERROR((B5/B3),"") | C6: =IFERROR((C5/C3),"") | D6: =IFERROR((D5/D3),"") | E6: =IFERROR((E5/E3),"") | F6: =IFERROR((F5/F3),"") | G6: =IFERROR((G5/G3),"") | H6: =IFERROR((H5/H3),"") | I6: =IFERROR((I5/I3),"") | ... P6: =IFERROR((P5/P3),"") | R6: Aumento nº acciones | S6: =IFERROR(AVERAGE(C12:K12),"") | T6: =S6
A7: Taxes | B7: =IFERROR(VLOOKUP("Income Tax Expense*",'7.TIKR_IS'!$A:$K,COLUMN(B2),FALSE),"0") -> 0 | C7: =IFERROR(VLOOKUP("Income Tax Expense*",'7.TIKR_IS'!$A:$K,COLUMN(C2),FALSE),"0") -> 0 | D7: =IFERROR(VLOOKUP("Income Tax Expense*",'7.TIKR_IS'!$A:$K,COLUMN(D2),FALSE),"0") -> 0 | E7: =IFERROR(VLOOKUP("Income Tax Expense*",'7.TIKR_IS'!$A:$K,COLUMN(E2),FALSE),"0") -> 0 | F7: =IFERROR(VLOOKUP("Income Tax Expense*",'7.TIKR_IS'!$A:$K,COLUMN(F2),FALSE),"0") -> 0 | G7: =IFERROR(VLOOKUP("Income Tax Expense*",'7.TIKR_IS'!$A:$K,COLUMN(G2),FALSE),"0") -> 0 | H7: =IFERROR(VLOOKUP("Income Tax Expense*",'7.TIKR_IS'!$A:$K,COLUMN(H2),FALSE),"0") -> 0 | I7: =IFERROR(VLOOKUP("Income Tax Expense*",'7.TIKR_IS'!$A:$K,COLUMN(I2),FALSE),"0") -> 0 | ... K7: =IFERROR(VLOOKUP("Income Tax Expense*",'7.TIKR_IS'!$A:$K,COLUMN(K2),FALSE),"0") -> 0 | L7: =IFERROR(-$T$5*L5,"") | M7: =IFERROR(-$T$5*M5,"") | N7: =IFERROR(-$T$5*N5,"") | O7: =IFERROR(-$T$5*O5,"") | P7: =IFERROR(-$T$5*P5,"")
A8: Effective Tax Rate % | B8: =IFERROR(-B7/B5,"") | C8: =IFERROR(-C7/C5,"") | D8: =IFERROR(-D7/D5,"") | E8: =IFERROR(-E7/E5,"") | F8: =IFERROR(-F7/F5,"") | G8: =IFERROR(-G7/G5,"") | H8: =IFERROR(-H7/H5,"") | I8: =IFERROR(-I7/I5,"") | ... P8: =IFERROR(-P7/P5,"") | T8: AJUSTAR MANUALMENTE
A9: Net Income | B9: =B5+B7 -> 0 | C9: =C5+C7 -> 0 | D9: =D5+D7 -> 0 | E9: =E5+E7 -> 0 | F9: =F5+F7 -> 0 | G9: =G5+G7 -> 0 | H9: =H5+H7 -> 0 | I9: =I5+I7 -> 0 | ... K9: =K5+K7 -> 0 | L9: =IFERROR(L5+L7,"") | M9: =IFERROR(M5+M7,"") | N9: =IFERROR(N5+N7,"") | O9: =IFERROR(O5+O7,"") | P9: =IFERROR(P5+P7,"")
A10: Net Margin % | B10: =IFERROR(B9/B3,"") | C10: =IFERROR(C9/C3,"") | D10: =IFERROR(D9/D3,"") | E10: =IFERROR(E9/E3,"") | F10: =IFERROR(F9/F3,"") | G10: =IFERROR(G9/G3,"") | H10: =IFERROR(H9/H3,"") | I10: =IFERROR(I9/I3,"") | ... P10: =IFERROR(P9/P3,"")
A11: Fully diluted shares - millones | B11: =IFERROR(VLOOKUP("*Diluted Shares Outstanding*",'7.TIKR_IS'!$A:$K,COLUMN(B11),FALSE),"0") -> 0 | C11: =IFERROR(VLOOKUP("*Diluted Shares Outstanding*",'7.TIKR_IS'!$A:$K,COLUMN(C11),FALSE),"0") -> 0 | D11: =IFERROR(VLOOKUP("*Diluted Shares Outstanding*",'7.TIKR_IS'!$A:$K,COLUMN(D11),FALSE),"0") -> 0 | E11: =IFERROR(VLOOKUP("*Diluted Shares Outstanding*",'7.TIKR_IS'!$A:$K,COLUMN(E11),FALSE),"0") -> 0 | F11: =IFERROR(VLOOKUP("*Diluted Shares Outstanding*",'7.TIKR_IS'!$A:$K,COLUMN(F11),FALSE),"0") -> 0 | G11: =IFERROR(VLOOKUP("*Diluted Shares Outstanding*",'7.TIKR_IS'!$A:$K,COLUMN(G11),FALSE),"0") -> 0 | H11: =IFERROR(VLOOKUP("*Diluted Shares Outstanding*",'7.TIKR_IS'!$A:$K,COLUMN(H11),FALSE),"0") -> 0 | I11: =IFERROR(VLOOKUP("*Diluted Shares Outstanding*",'7.TIKR_IS'!$A:$K,COLUMN(I11),FALSE),"0") -> 0 | ... K11: =IFERROR(VLOOKUP("*Diluted Shares Outstanding*",'7.TIKR_IS'!$A:$K,COLUMN(K11),FALSE),"0") -> 0 | L11: =IFERROR(K11*(1+$T$6),"") | M11: =IFERROR(L11*(1+$T$6),"") | N11: =IFERROR(M11*(1+$T$6),"") | O11: =IFERROR(N11*(1+$T$6),"") | P11: =IFERROR(O11*(1+$T$6),"")
A12: Y/Y Growth % | C12: =IFERROR((C11-B11)/B11,"") | D12: =IFERROR((D11-C11)/C11,"") | E12: =IFERROR((E11-D11)/D11,"") | F12: =IFERROR((F11-E11)/E11,"") | G12: =IFERROR((G11-F11)/F11,"") | H12: =IFERROR((H11-G11)/G11,"") | I12: =IFERROR((I11-H11)/H11,"") | J12: =IFERROR((J11-I11)/I11,"") | ... P12: =IFERROR((P11-O11)/O11,"")
A13: Earnings Per Share (Diluted) | B13: =IFERROR(B9/B11,"") | C13: =IFERROR(C9/C11,"") | D13: =IFERROR(D9/D11,"") | E13: =IFERROR(E9/E11,"") | F13: =IFERROR(F9/F11,"") | G13: =IFERROR(G9/G11,"") | H13: =IFERROR(H9/H11,"") | I13: =IFERROR(I9/I11,"") | ... P13: =IFERROR(P9/P11,"")
A16: Rentabilidad | B16: =IFERROR(IF(VLOOKUP("Income Statement*",'7.TIKR_IS'!$A:$K,COLUMN(B17),FALSE)="","",IFERROR(YEAR(VLOOKUP("Income Statement*",'7.TIKR_IS'!$A:$K,COLUMN(B17),FALSE)),"2013")),"") | C16: =IFERROR(IF(VLOOKUP("Income Statement*",'7.TIKR_IS'!$A:$K,COLUMN(C17),FALSE)="","",IFERROR(YEAR(VLOOKUP("Income Statement*",'7.TIKR_IS'!$A:$K,COLUMN(C17),FALSE)),"2013")),"") | D16: =IFERROR(IF(VLOOKUP("Income Statement*",'7.TIKR_IS'!$A:$K,COLUMN(D17),FALSE)="","",IFERROR(YEAR(VLOOKUP("Income Statement*",'7.TIKR_IS'!$A:$K,COLUMN(D17),FALSE)),"2013")),"") | E16: =IFERROR(IF(VLOOKUP("Income Statement*",'7.TIKR_IS'!$A:$K,COLUMN(E17),FALSE)="","",IFERROR(YEAR(VLOOKUP("Income Statement*",'7.TIKR_IS'!$A:$K,COLUMN(E17),FALSE)),"2013")),"") | F16: =IFERROR(IF(VLOOKUP("Income Statement*",'7.TIKR_IS'!$A:$K,COLUMN(F17),FALSE)="","",IFERROR(YEAR(VLOOKUP("Income Statement*",'7.TIKR_IS'!$A:$K,COLUMN(F17),FALSE)),"2013")),"") | G16: =IFERROR(IF(VLOOKUP("Income Statement*",'7.TIKR_IS'!$A:$K,COLUMN(G17),FALSE)="","",IFERROR(YEAR(VLOOKUP("Income Statement*",'7.TIKR_IS'!$A:$K,COLUMN(G17),FALSE)),"2013")),"") | H16: =IFERROR(IF(VLOOKUP("Income Statement*",'7.TIKR_IS'!$A:$K,COLUMN(H17),FALSE)="","",IFERROR(YEAR(VLOOKUP("Income Statement*",'7.TIKR_IS'!$A:$K,COLUMN(H17),FALSE)),"2013")),"") | I16: =IFERROR(IF(VLOOKUP("Income Statement*",'7.TIKR_IS'!$A:$K,COLUMN(I17),FALSE)="","",IFERROR(YEAR(VLOOKUP("Income Statement*",'7.TIKR_IS'!$A:$K,COLUMN(I17),FALSE)),"2013")),"") | ... K16: =IFERROR(IF(VLOOKUP("Income Statement*",'7.TIKR_IS'!$A:$K,COLUMN(K17),FALSE)="","",IFERROR(YEAR(VLOOKUP("Income Statement*",'7.TIKR_IS'!$A:$K,COLUMN(K17),FALSE)),"2013")),"") | L16: =IF(K16<>"",(K16+1)&"e","") | M16: =IF(L16<>"",(LEFT(L16,4)+1)&"e","") | N16: =IF(M16<>"",(LEFT(M16,4)+1)&"e","") | O16: =IF(N16<>"",(LEFT(N16,4)+1)&"e","") | P16: =IF(O16<>"",(LEFT(O16,4)+1)&"e","") | R16: ="Promedio "&B2&" - "&K2 -> Promedio -
A17: ROA | B17: =IFERROR(B9/VLOOKUP("Total Assets",'8.TIKR_BS'!$A:$K,COLUMN(B2),FALSE),"") | C17: =IFERROR(C9/VLOOKUP("Total Assets",'8.TIKR_BS'!$A:$K,COLUMN(C2),FALSE),"") | D17: =IFERROR(D9/VLOOKUP("Total Assets",'8.TIKR_BS'!$A:$K,COLUMN(D2),FALSE),"") | E17: =IFERROR(E9/VLOOKUP("Total Assets",'8.TIKR_BS'!$A:$K,COLUMN(E2),FALSE),"") | F17: =IFERROR(F9/VLOOKUP("Total Assets",'8.TIKR_BS'!$A:$K,COLUMN(F2),FALSE),"") | G17: =IFERROR(G9/VLOOKUP("Total Assets",'8.TIKR_BS'!$A:$K,COLUMN(G2),FALSE),"") | H17: =IFERROR(H9/VLOOKUP("Total Assets",'8.TIKR_BS'!$A:$K,COLUMN(H2),FALSE),"") | I17: =IFERROR(I9/VLOOKUP("Total Assets",'8.TIKR_BS'!$A:$K,COLUMN(I2),FALSE),"") | ... K17: =IFERROR(K9/VLOOKUP("Total Assets",'8.TIKR_BS'!$A:$K,COLUMN(K2),FALSE),"") | L17: - | M17: - | N17: - | O17: - | P17: - | R17: =IFERROR(AVERAGE(B17:K17),"")
A18: ROE | B18: =IFERROR(B9/TIKR_Cálculos!B26,"") | C18: =IFERROR(C9/TIKR_Cálculos!C26,"") | D18: =IFERROR(D9/TIKR_Cálculos!D26,"") | E18: =IFERROR(E9/TIKR_Cálculos!E26,"") | F18: =IFERROR(F9/TIKR_Cálculos!F26,"") | G18: =IFERROR(G9/TIKR_Cálculos!G26,"") | H18: =IFERROR(H9/TIKR_Cálculos!H26,"") | I18: =IFERROR(I9/TIKR_Cálculos!I26,"") | ... P18: =IFERROR(P9/TIKR_Cálculos!P26,"") | R18: =IFERROR(AVERAGE(B18:K18),"")
A20: Apalancamiento | B20: =IFERROR(IF(VLOOKUP("Income Statement*",'7.TIKR_IS'!$A:$K,COLUMN(B21),FALSE)="","",IFERROR(YEAR(VLOOKUP("Income Statement*",'7.TIKR_IS'!$A:$K,COLUMN(B21),FALSE)),"2013")),"") | C20: =IFERROR(IF(VLOOKUP("Income Statement*",'7.TIKR_IS'!$A:$K,COLUMN(C21),FALSE)="","",IFERROR(YEAR(VLOOKUP("Income Statement*",'7.TIKR_IS'!$A:$K,COLUMN(C21),FALSE)),"2013")),"") | D20: =IFERROR(IF(VLOOKUP("Income Statement*",'7.TIKR_IS'!$A:$K,COLUMN(D21),FALSE)="","",IFERROR(YEAR(VLOOKUP("Income Statement*",'7.TIKR_IS'!$A:$K,COLUMN(D21),FALSE)),"2013")),"") | E20: =IFERROR(IF(VLOOKUP("Income Statement*",'7.TIKR_IS'!$A:$K,COLUMN(E21),FALSE)="","",IFERROR(YEAR(VLOOKUP("Income Statement*",'7.TIKR_IS'!$A:$K,COLUMN(E21),FALSE)),"2013")),"") | F20: =IFERROR(IF(VLOOKUP("Income Statement*",'7.TIKR_IS'!$A:$K,COLUMN(F21),FALSE)="","",IFERROR(YEAR(VLOOKUP("Income Statement*",'7.TIKR_IS'!$A:$K,COLUMN(F21),FALSE)),"2013")),"") | G20: =IFERROR(IF(VLOOKUP("Income Statement*",'7.TIKR_IS'!$A:$K,COLUMN(G21),FALSE)="","",IFERROR(YEAR(VLOOKUP("Income Statement*",'7.TIKR_IS'!$A:$K,COLUMN(G21),FALSE)),"2013")),"") | H20: =IFERROR(IF(VLOOKUP("Income Statement*",'7.TIKR_IS'!$A:$K,COLUMN(H21),FALSE)="","",IFERROR(YEAR(VLOOKUP("Income Statement*",'7.TIKR_IS'!$A:$K,COLUMN(H21),FALSE)),"2013")),"") | I20: =IFERROR(IF(VLOOKUP("Income Statement*",'7.TIKR_IS'!$A:$K,COLUMN(I21),FALSE)="","",IFERROR(YEAR(VLOOKUP("Income Statement*",'7.TIKR_IS'!$A:$K,COLUMN(I21),FALSE)),"2013")),"") | ... K20: =IFERROR(IF(VLOOKUP("Income Statement*",'7.TIKR_IS'!$A:$K,COLUMN(K21),FALSE)="","",IFERROR(YEAR(VLOOKUP("Income Statement*",'7.TIKR_IS'!$A:$K,COLUMN(K21),FALSE)),"2013")),"")
A21: Deuda / Equity | B21: =IFERROR(TIKR_Cálculos!B29,"") | C21: =IFERROR(TIKR_Cálculos!C29,"") | D21: =IFERROR(TIKR_Cálculos!D29,"") | E21: =IFERROR(TIKR_Cálculos!E29,"") | F21: =IFERROR(TIKR_Cálculos!F29,"") | G21: =IFERROR(TIKR_Cálculos!G29,"") | H21: =IFERROR(TIKR_Cálculos!H29,"") | I21: =IFERROR(TIKR_Cálculos!I29,"") | ... K21: =IFERROR(TIKR_Cálculos!K29,"")

Sheet 4.Valoración
B1: Valoración
A2: Valoración (millones) | B2: ='1.IS'!K$2 | C2: ='1.IS'!L$2 | D2: ='1.IS'!M$2 | E2: ='1.IS'!N$2 | F2: ='1.IS'!O$2 | G2: ='1.IS'!P$2
A3: Market cap | B3: =$D$7*'1.IS'!K11 -> 0 | C3: =IFERROR($D$7*'1.IS'!L11,"") | D3: =IFERROR($D$7*'1.IS'!M11,"") | E3: =IFERROR($D$7*'1.IS'!N11,"") | F3: =IFERROR($D$7*'1.IS'!O11,"") | G3: =IFERROR($D$7*'1.IS'!P11,"")
A4: Book Value por acción | B4: =IF($D$7<>"",TIKR_Cálculos!K26/'1.IS'!K11,"") | C4: =IF($D$7<>"",TIKR_Cálculos!L26/'1.IS'!L11,"") | D4: =IF($D$7<>"",TIKR_Cálculos!M26/'1.IS'!M11,"") | E4: =IF($D$7<>"",TIKR_Cálculos!N26/'1.IS'!N11,"") | F4: =IF($D$7<>"",TIKR_Cálculos!O26/'1.IS'!O11,"") | G4: =IF($D$7<>"",TIKR_Cálculos!P26/'1.IS'!P11,"")
A5: EPS | B5: ='1.IS'!K13 | C5: ='1.IS'!L13 | D5: ='1.IS'!M13 | E5: ='1.IS'!N13 | F5: ='1.IS'!O13 | G5: ='1.IS'!P13
A7: Precio por acción actual
A9: Precio de compra para obtener un retorno anual >=15% | D9: =IF($D$7<>"",IF(K17<15%,F17/2,D7),"")
A11: Múltiplos de valoración | B11: LTM | C11: NTM | D11: Objetivo
A12: Price / Book | B12: =IF($D$7<>"",D7/B4,"") | C12: =IF($D$7<>"",D7/C4,"") | D12: =C12
A13: PER | B13: =IF($D$7<>"",$D$7/'1.IS'!K13,"") | C13: =IF($D$7<>"",$D$7/'1.IS'!L13,"") | D13: =C13 | F13: AJUSTAR MANUALMENTE
A15: Precio objetivo | B15: =C2 | C15: =D2 | D15: =E2 | E15: =F2 | F15: =G2 | H15: ="Retorno Anualizado"&CHAR(10)&"valorando por..." -> Retorno Anualizado valorando por... | K15: ="CAGR"&CHAR(10)&"5 años" -> CAGR 5 años
A16: Price / Book | B16: =IF($D$7<>"",IFERROR($D$12*C4,""),"") | C16: =IF($D$7<>"",IFERROR($D$12*D4,""),"") | D16: =IF($D$7<>"",IFERROR($D$12*E4,""),"") | E16: =IF($D$7<>"",IFERROR($D$12*F4,""),"") | F16: =IF($D$7<>"",IFERROR($D$12*G4,""),"") | H16: P/ B | K16: =IFERROR((F16/$D$7)^(1/5)-1,"")
A17: PER | B17: =IF($D$7<>"",IFERROR($D$13*C5,""),"") | C17: =IF($D$7<>"",IFERROR($D$13*D5,""),"") | D17: =IF($D$7<>"",IFERROR($D$13*E5,""),"") | E17: =IF($D$7<>"",IFERROR($D$13*F5,""),"") | F17: =IF($D$7<>"",IFERROR($D$13*G5,""),"") | H17: PER | K17: =IFERROR((F17/$D$7)^(1/5)-1,"")
A18: Promedio | B18: =IFERROR(AVERAGE(B16:B17),"") | C18: =IFERROR(AVERAGE(C16:C17),"") | D18: =IFERROR(AVERAGE(D16:D17),"") | E18: =IFERROR(AVERAGE(E16:E17),"") | F18: =IFERROR(AVERAGE(F16:F17),"") | H18: Promedio | K18: =IFERROR(AVERAGE(K16:K17),"")
A19: Margen de seguridad | B19: =IFERROR((B18/$D$7)-1,"") | C19: =IFERROR((C18/$D$7)-1,"") | D19: =IFERROR((D18/$D$7)-1,"") | E19: =IFERROR((E18/$D$7)-1,"") | F19: =IFERROR((F18/$D$7)-1,"")

Sheet 5.Red Flags
B1: Posibles "Red Flags"
A2: Posibles "red flags" (1) | B2: ='1.IS'!B$2 | C2: ='1.IS'!C$2 | D2: ='1.IS'!D$2 | E2: ='1.IS'!E$2 | F2: ='1.IS'!F$2 | G2: ='1.IS'!G$2 | H2: ='1.IS'!H$2 | I2: ='1.IS'!I$2 | ... K2: ='1.IS'!K$2
A3: Como % de ventas...
A4: Pagos en acciones | B4: =IFERROR(VLOOKUP("Stock-based compensation*",'9.TIKR_CF'!$A:$K,COLUMN(B1),FALSE)/'1.IS'!B2,"") | C4: =IFERROR(VLOOKUP("Stock-based compensation*",'9.TIKR_CF'!$A:$K,COLUMN(C1),FALSE)/'1.IS'!C2,"") | D4: =IFERROR(VLOOKUP("Stock-based compensation*",'9.TIKR_CF'!$A:$K,COLUMN(D1),FALSE)/'1.IS'!D2,"") | E4: =IFERROR(VLOOKUP("Stock-based compensation*",'9.TIKR_CF'!$A:$K,COLUMN(E1),FALSE)/'1.IS'!E2,"") | F4: =IFERROR(VLOOKUP("Stock-based compensation*",'9.TIKR_CF'!$A:$K,COLUMN(F1),FALSE)/'1.IS'!F2,"") | G4: =IFERROR(VLOOKUP("Stock-based compensation*",'9.TIKR_CF'!$A:$K,COLUMN(G1),FALSE)/'1.IS'!G2,"") | H4: =IFERROR(VLOOKUP("Stock-based compensation*",'9.TIKR_CF'!$A:$K,COLUMN(H1),FALSE)/'1.IS'!H2,"") | I4: =IFERROR(VLOOKUP("Stock-based compensation*",'9.TIKR_CF'!$A:$K,COLUMN(I1),FALSE)/'1.IS'!I2,"") | ... K4: =IFERROR(VLOOKUP("Stock-based compensation*",'9.TIKR_CF'!$A:$K,COLUMN(K1),FALSE)/'1.IS'!K2,"")
A5: Emisión de acciones | B5: =IFERROR(VLOOKUP("Issuance of Common Stock*",'9.TIKR_CF'!$A:$K,COLUMN(B2),FALSE)/'1.IS'!B3,"") | C5: =IFERROR(VLOOKUP("Issuance of Common Stock*",'9.TIKR_CF'!$A:$K,COLUMN(C2),FALSE)/'1.IS'!C3,"") | D5: =IFERROR(VLOOKUP("Issuance of Common Stock*",'9.TIKR_CF'!$A:$K,COLUMN(D2),FALSE)/'1.IS'!D3,"") | E5: =IFERROR(VLOOKUP("Issuance of Common Stock*",'9.TIKR_CF'!$A:$K,COLUMN(E2),FALSE)/'1.IS'!E3,"") | F5: =IFERROR(VLOOKUP("Issuance of Common Stock*",'9.TIKR_CF'!$A:$K,COLUMN(F2),FALSE)/'1.IS'!F3,"") | G5: =IFERROR(VLOOKUP("Issuance of Common Stock*",'9.TIKR_CF'!$A:$K,COLUMN(G2),FALSE)/'1.IS'!G3,"") | H5: =IFERROR(VLOOKUP("Issuance of Common Stock*",'9.TIKR_CF'!$A:$K,COLUMN(H2),FALSE)/'1.IS'!H3,"") | I5: =IFERROR(VLOOKUP("Issuance of Common Stock*",'9.TIKR_CF'!$A:$K,COLUMN(I2),FALSE)/'1.IS'!I3,"") | ... K5: =IFERROR(VLOOKUP("Issuance of Common Stock*",'9.TIKR_CF'!$A:$K,COLUMN(K2),FALSE)/'1.IS'!K3,"")
A7: Posibles "red flags" (2) | B7: Total
A8: # de años con...
A9: Decrecimiento de ventas | B9: =TIKR_Cálculos!L20 -> 0
A10: Decrecimiento de margen EBT | B10: =TIKR_Cálculos!L21 -> 0
A11: Net Income negativo | B11: =TIKR_Cálculos!L22 -> 0
A12: ROE "Pobre" (<10%) | B12: =TIKR_Cálculos!L23 -> 0

Sheet 7.TIKR_IS

Sheet 8.TIKR_BS

Sheet 9.TIKR_CF

Sheet 10.Glosario
B2: Beneficio "contable" | C2: Opción 1 | D2: Opción 2 | E2: Opción 3
B3: EBITDA | C3: Net Income + Interests (net) + Taxes + Depreciation + Amortization | D3: Ingresos - Gastos de Explotación | E3: EBIT + D&A
B4: EBIT | C4: Net Income + Interests (net) + Taxes | D4: Ingresos - Gastos de Explotación - D&A | E4: EBITDA - D&A
B5: EBT | C5: Net Income + Interests (net) | D5: Ingresos - Gastos de Explotación - D&A - Interests (net) - Other financial items | E5: EBIT - Interests (net) - Other financial items
B6: Net Income | C6: Ingresos - Gastos de Explotación - D&A - Interests (net) - Other financial items - taxes | D6: EBT - Taxes
B7: EPS | C7: Net Income / Nº total de acciones diluídas
B9: Valoración | C9: Opción 1 | D9: Opción 2 | E9: Opción 3
B10: Net Debt (Deuda Financiera Neta) | C10: Short-Term Debt + Short-Term Borrowings + Long-Term Debt + Long-Term Borrowings - Cash
B11: Market Cap. | C11: Nº de acciones totales diluídas x Precio por acción
B12: Enterprise Value (EV) | C12: Market Cap + Net Debt | D12: Market Cap - Caja Neta
B13: EV / EBITDA | C13: Enterprise Value / EBITDA
B14: EV / EBIT | C14: Enterprise Value / EBIT
B15: EV / FCF | C15: Enterprise Value / FCF
B16: PER | C16: Market Cap. / Beneficio Neto | D16: Precio por acción / EPS
B18: Márgenes % | C18: Opción 1 | D18: Opción 2 | E18: Opción 3
B19: EBITDA | C19: EBITDA / Ventas x 100
B20: EBIT | C20: EBIT / Ventas x 100
B21: Neto | C21: Net Income / Ventas x 100
B22: FCF | C22: FCF / Ventas x 100
B24: Rentabilidad % | C24: Opción 1 | D24: Opción 2 | E24: Opción 3
B25: ROIC | C25: EBIT * (1 - T) / Capital Invertido | D25: Capital Invertido = Equity + Deuda financiera total + Operating Leases Total – Marketable Securities
B26: ROE | C26: Net Income / Equity
B27: ROA | C27: Net Income / Total Assets
B29: FCF | C29: Opción 1 | D29: Opción 2 | E29: Opción 3
B30: Working Capital (WC) | C30: Inventarios + Cuentas a Cobrar de Clientes - Cuentas a pagar a proveedores | D30: Inventories + Accounts Receivable + Accounts Payable | E30: En empresas ligeras de activos podemos restar también la partida "Unearned revenue", tanto "Current" como "Non-current"
B31: Variación de WC (CWC) | C31: WC año más reciente - WC año anterior. (P.ej.: WC 2021 - WC 2020) | D31: Si la CWC es positiva DISMINUYE el FCF ya que la empresa tiene que financiar ese aumento de inventarios y/o de cuentas a cobrar | E31: Si la CWC es negativa AUMENTA el FCF, ya que se 'libera'' capital, es como si la empresa vendiese inventarios y/o cobrase más facturas a clientes
B32: CapEx de Mantenimiento | C32: Si la directiva no proporciona un capex de mantenimiento exacto, usaremos la D&A como "atajo" para el capex de mantenimiento en los casos que el capex total sea notablemente superior a la D&A | D32: Otra opción es usar el % CapEx / Sales del sector, pero esto lleva trabajo, no hay una página que recoja este ratio para todas y cada una de los cientos de industrias que componen todos los sectores
B33: FCF | C33: EBITDA - Interests (net) - Taxes - CapEx Mantenimiento - Variación de WC

Sheet TIKR_Cálculos
A3: Valoración | B3: ='1.IS'!L2 | C3: ='1.IS'!M2 | D3: ='1.IS'!N2 | E3: ='1.IS'!O2 | F3: ='1.IS'!P2
A4: Precio actual | B4: ='4.Valoración'!$D$7 -> 0 | C4: ='4.Valoración'!$D$7 -> 0 | D4: ='4.Valoración'!$D$7 -> 0 | E4: ='4.Valoración'!$D$7 -> 0 | F4: ='4.Valoración'!$D$7 -> 0
A7: Asignación de capital | B7: ='1.IS'!B2 | C7: ='1.IS'!C2 | D7: ='1.IS'!D2 | E7: ='1.IS'!E2 | F7: ='1.IS'!F2 | G7: ='1.IS'!G2 | H7: ='1.IS'!H2 | I7: ='1.IS'!I2 | ... K7: ='1.IS'!K2 | L7: Acumulado
A8: Dividendos | B8: =IFERROR(ABS(VLOOKUP("Common & Preferred Stock Dividends Paid*",'9.TIKR_CF'!$A:$K,COLUMN(B8),FALSE)),"0") -> 0 | C8: =IFERROR(ABS(VLOOKUP("Common & Preferred Stock Dividends Paid*",'9.TIKR_CF'!$A:$K,COLUMN(C8),FALSE)),"0") -> 0 | D8: =IFERROR(ABS(VLOOKUP("Common & Preferred Stock Dividends Paid*",'9.TIKR_CF'!$A:$K,COLUMN(D8),FALSE)),"0") -> 0 | E8: =IFERROR(ABS(VLOOKUP("Common & Preferred Stock Dividends Paid*",'9.TIKR_CF'!$A:$K,COLUMN(E8),FALSE)),"0") -> 0 | F8: =IFERROR(ABS(VLOOKUP("Common & Preferred Stock Dividends Paid*",'9.TIKR_CF'!$A:$K,COLUMN(F8),FALSE)),"0") -> 0 | G8: =IFERROR(ABS(VLOOKUP("Common & Preferred Stock Dividends Paid*",'9.TIKR_CF'!$A:$K,COLUMN(G8),FALSE)),"0") -> 0 | H8: =IFERROR(ABS(VLOOKUP("Common & Preferred Stock Dividends Paid*",'9.TIKR_CF'!$A:$K,COLUMN(H8),FALSE)),"0") -> 0 | I8: =IFERROR(ABS(VLOOKUP("Common & Preferred Stock Dividends Paid*",'9.TIKR_CF'!$A:$K,COLUMN(I8),FALSE)),"0") -> 0 | ... K8: =IFERROR(ABS(VLOOKUP("Common & Preferred Stock Dividends Paid*",'9.TIKR_CF'!$A:$K,COLUMN(K8),FALSE)),"0") -> 0 | L8: =SUM(B8:K8) -> 0
A9: Recompras | B9: =IFERROR(ABS(VLOOKUP("Repurchase of Common Stock*",'9.TIKR_CF'!$A:$K,COLUMN(B9),FALSE)),"0") -> 0 | C9: =IFERROR(ABS(VLOOKUP("Repurchase of Common Stock*",'9.TIKR_CF'!$A:$K,COLUMN(C9),FALSE)),"0") -> 0 | D9: =IFERROR(ABS(VLOOKUP("Repurchase of Common Stock*",'9.TIKR_CF'!$A:$K,COLUMN(D9),FALSE)),"0") -> 0 | E9: =IFERROR(ABS(VLOOKUP("Repurchase of Common Stock*",'9.TIKR_CF'!$A:$K,COLUMN(E9),FALSE)),"0") -> 0 | F9: =IFERROR(ABS(VLOOKUP("Repurchase of Common Stock*",'9.TIKR_CF'!$A:$K,COLUMN(F9),FALSE)),"0") -> 0 | G9: =IFERROR(ABS(VLOOKUP("Repurchase of Common Stock*",'9.TIKR_CF'!$A:$K,COLUMN(G9),FALSE)),"0") -> 0 | H9: =IFERROR(ABS(VLOOKUP("Repurchase of Common Stock*",'9.TIKR_CF'!$A:$K,COLUMN(H9),FALSE)),"0") -> 0 | I9: =IFERROR(ABS(VLOOKUP("Repurchase of Common Stock*",'9.TIKR_CF'!$A:$K,COLUMN(I9),FALSE)),"0") -> 0 | ... K9: =IFERROR(ABS(VLOOKUP("Repurchase of Common Stock*",'9.TIKR_CF'!$A:$K,COLUMN(K9),FALSE)),"0") -> 0 | L9: =SUM(B9:K9) -> 0
A10: Adquisiciones (Crecimiento inorgánico) | B10: =ABS(IFERROR(VLOOKUP("Cash Acquisitions*",'9.TIKR_CF'!$A:$K,COLUMN(B10),FALSE),"0")) -> 0 | C10: =ABS(IFERROR(VLOOKUP("Cash Acquisitions*",'9.TIKR_CF'!$A:$K,COLUMN(C10),FALSE),"0")) -> 0 | D10: =ABS(IFERROR(VLOOKUP("Cash Acquisitions*",'9.TIKR_CF'!$A:$K,COLUMN(D10),FALSE),"0")) -> 0 | E10: =ABS(IFERROR(VLOOKUP("Cash Acquisitions*",'9.TIKR_CF'!$A:$K,COLUMN(E10),FALSE),"0")) -> 0 | F10: =ABS(IFERROR(VLOOKUP("Cash Acquisitions*",'9.TIKR_CF'!$A:$K,COLUMN(F10),FALSE),"0")) -> 0 | G10: =ABS(IFERROR(VLOOKUP("Cash Acquisitions*",'9.TIKR_CF'!$A:$K,COLUMN(G10),FALSE),"0")) -> 0 | H10: =ABS(IFERROR(VLOOKUP("Cash Acquisitions*",'9.TIKR_CF'!$A:$K,COLUMN(H10),FALSE),"0")) -> 0 | I10: =ABS(IFERROR(VLOOKUP("Cash Acquisitions*",'9.TIKR_CF'!$A:$K,COLUMN(I10),FALSE),"0")) -> 0 | ... K10: =ABS(IFERROR(VLOOKUP("Cash Acquisitions*",'9.TIKR_CF'!$A:$K,COLUMN(K10),FALSE),"0")) -> 0 | L10: =SUM(B10:K10) -> 0
A11: Repago de deuda neto | B11: =IFERROR(ABS(VLOOKUP("Total Debt Repaid*",'9.TIKR_CF'!$A:$K,COLUMN(B11),FALSE))-VLOOKUP("Total Debt Issued*",'9.TIKR_CF'!$A:$K,COLUMN(B11),FALSE),0) -> 0 | C11: =IFERROR(ABS(VLOOKUP("Total Debt Repaid*",'9.TIKR_CF'!$A:$K,COLUMN(C11),FALSE))-VLOOKUP("Total Debt Issued*",'9.TIKR_CF'!$A:$K,COLUMN(C11),FALSE),0) -> 0 | D11: =IFERROR(ABS(VLOOKUP("Total Debt Repaid*",'9.TIKR_CF'!$A:$K,COLUMN(D11),FALSE))-VLOOKUP("Total Debt Issued*",'9.TIKR_CF'!$A:$K,COLUMN(D11),FALSE),0) -> 0 | E11: =IFERROR(ABS(VLOOKUP("Total Debt Repaid*",'9.TIKR_CF'!$A:$K,COLUMN(E11),FALSE))-VLOOKUP("Total Debt Issued*",'9.TIKR_CF'!$A:$K,COLUMN(E11),FALSE),0) -> 0 | F11: =IFERROR(ABS(VLOOKUP("Total Debt Repaid*",'9.TIKR_CF'!$A:$K,COLUMN(F11),FALSE))-VLOOKUP("Total Debt Issued*",'9.TIKR_CF'!$A:$K,COLUMN(F11),FALSE),0) -> 0 | G11: =IFERROR(ABS(VLOOKUP("Total Debt Repaid*",'9.TIKR_CF'!$A:$K,COLUMN(G11),FALSE))-VLOOKUP("Total Debt Issued*",'9.TIKR_CF'!$A:$K,COLUMN(G11),FALSE),0) -> 0 | H11: =IFERROR(ABS(VLOOKUP("Total Debt Repaid*",'9.TIKR_CF'!$A:$K,COLUMN(H11),FALSE))-VLOOKUP("Total Debt Issued*",'9.TIKR_CF'!$A:$K,COLUMN(H11),FALSE),0) -> 0 | I11: =IFERROR(ABS(VLOOKUP("Total Debt Repaid*",'9.TIKR_CF'!$A:$K,COLUMN(I11),FALSE))-VLOOKUP("Total Debt Issued*",'9.TIKR_CF'!$A:$K,COLUMN(I11),FALSE),0) -> 0 | ... K11: =IFERROR(ABS(VLOOKUP("Total Debt Repaid*",'9.TIKR_CF'!$A:$K,COLUMN(K11),FALSE))-VLOOKUP("Total Debt Issued*",'9.TIKR_CF'!$A:$K,COLUMN(K11),FALSE),0) -> 0 | L11: =SUM(B11:K11) -> 0
A13: Crecimiento
B14: ='1.IS'!C$2 | C14: ='1.IS'!D$2 | D14: ='1.IS'!E$2 | E14: ='1.IS'!F$2 | F14: ='1.IS'!G$2 | G14: ='1.IS'!H$2 | H14: ='1.IS'!I$2 | I14: ='1.IS'!J$2 | J14: ='1.IS'!K$2
A15: Ventas | B15: ='1.IS'!C4 | C15: ='1.IS'!D4 | D15: ='1.IS'!E4 | E15: ='1.IS'!F4 | F15: ='1.IS'!G4 | G15: ='1.IS'!H4 | H15: ='1.IS'!I4 | I15: ='1.IS'!J4 | J15: ='1.IS'!K4
A16: EPS
A19: Posibles red flags | B19: ='1.IS'!B2 | C19: ='1.IS'!C2 | D19: ='1.IS'!D2 | E19: ='1.IS'!E2 | F19: ='1.IS'!F2 | G19: ='1.IS'!G2 | H19: ='1.IS'!H2 | I19: ='1.IS'!I2 | ... K19: ='1.IS'!K2 | L19: Total
A20: Decrecimiento ventas | C20: =IF('1.IS'!C4<0,1,0) -> 0 | D20: =IF('1.IS'!D4<0,1,0) -> 0 | E20: =IF('1.IS'!E4<0,1,0) -> 0 | F20: =IF('1.IS'!F4<0,1,0) -> 0 | G20: =IF('1.IS'!G4<0,1,0) -> 0 | H20: =IF('1.IS'!H4<0,1,0) -> 0 | I20: =IF('1.IS'!I4<0,1,0) -> 0 | J20: =IF('1.IS'!J4<0,1,0) -> 0 | K20: =IF('1.IS'!K4<0,1,0) -> 0 | L20: =SUM(B20:K20) -> 0
A21: Decrecimiento margen EBT | C21: =IF('1.IS'!C6<'1.IS'!B6,1,0) -> 0 | D21: =IF('1.IS'!D6<'1.IS'!C6,1,0) -> 0 | E21: =IF('1.IS'!E6<'1.IS'!D6,1,0) -> 0 | F21: =IF('1.IS'!F6<'1.IS'!E6,1,0) -> 0 | G21: =IF('1.IS'!G6<'1.IS'!F6,1,0) -> 0 | H21: =IF('1.IS'!H6<'1.IS'!G6,1,0) -> 0 | I21: =IF('1.IS'!I6<'1.IS'!H6,1,0) -> 0 | J21: =IF('1.IS'!J6<'1.IS'!I6,1,0) -> 0 | K21: =IF('1.IS'!K6<'1.IS'!J6,1,0) -> 0 | L21: =SUM(B21:K21) -> 0
A22: Net Income negativo | B22: =IF('1.IS'!B9<0,1,0) -> 0 | C22: =IF('1.IS'!C9<0,1,0) -> 0 | D22: =IF('1.IS'!D9<0,1,0) -> 0 | E22: =IF('1.IS'!E9<0,1,0) -> 0 | F22: =IF('1.IS'!F9<0,1,0) -> 0 | G22: =IF('1.IS'!G9<0,1,0) -> 0 | H22: =IF('1.IS'!H9<0,1,0) -> 0 | I22: =IF('1.IS'!I9<0,1,0) -> 0 | ... K22: =IF('1.IS'!K9<0,1,0) -> 0 | L22: =SUM(B22:K22) -> 0
A23: ROE "Pobre" (<10%) | B23: =IF('1.IS'!B18<10%,1,0) -> 0 | C23: =IF('1.IS'!C18<10%,1,0) -> 0 | D23: =IF('1.IS'!D18<10%,1,0) -> 0 | E23: =IF('1.IS'!E18<10%,1,0) -> 0 | F23: =IF('1.IS'!F18<10%,1,0) -> 0 | G23: =IF('1.IS'!G18<10%,1,0) -> 0 | H23: =IF('1.IS'!H18<10%,1,0) -> 0 | I23: =IF('1.IS'!I18<10%,1,0) -> 0 | ... K23: =IF('1.IS'!K18<10%,1,0) -> 0 | L23: =SUM(B23:K23) -> 0
A25: Valoración | B25: ='1.IS'!B2 | C25: ='1.IS'!C2 | D25: ='1.IS'!D2 | E25: ='1.IS'!E2 | F25: ='1.IS'!F2 | G25: ='1.IS'!G2 | H25: ='1.IS'!H2 | I25: ='1.IS'!I2 | ... P25: ='1.IS'!P2
A26: Equity | B26: =VLOOKUP("Total Equity*",'8.TIKR_BS'!$A:$K,COLUMN(B2),FALSE) -> #N/A | C26: =VLOOKUP("Total Equity*",'8.TIKR_BS'!$A:$K,COLUMN(C2),FALSE) -> #N/A | D26: =VLOOKUP("Total Equity*",'8.TIKR_BS'!$A:$K,COLUMN(D2),FALSE) -> #N/A | E26: =VLOOKUP("Total Equity*",'8.TIKR_BS'!$A:$K,COLUMN(E2),FALSE) -> #N/A | F26: =VLOOKUP("Total Equity*",'8.TIKR_BS'!$A:$K,COLUMN(F2),FALSE) -> #N/A | G26: =VLOOKUP("Total Equity*",'8.TIKR_BS'!$A:$K,COLUMN(G2),FALSE) -> #N/A | H26: =VLOOKUP("Total Equity*",'8.TIKR_BS'!$A:$K,COLUMN(H2),FALSE) -> #N/A | I26: =VLOOKUP("Total Equity*",'8.TIKR_BS'!$A:$K,COLUMN(I2),FALSE) -> #N/A | ... K26: =VLOOKUP("Total Equity*",'8.TIKR_BS'!$A:$K,COLUMN(K2),FALSE) -> #N/A | L26: =K26+'1.IS'!L9 -> #N/A | M26: =L26+'1.IS'!M9 -> #N/A | N26: =M26+'1.IS'!N9 -> #N/A | O26: =N26+'1.IS'!O9 -> #N/A | P26: =O26+'1.IS'!P9 -> #N/A
A28: Apalancamiento | B28: ='1.IS'!B2 | C28: ='1.IS'!C2 | D28: ='1.IS'!D2 | E28: ='1.IS'!E2 | F28: ='1.IS'!F2 | G28: ='1.IS'!G2 | H28: ='1.IS'!H2 | I28: ='1.IS'!I2 | ... K28: ='1.IS'!K2
A29: Deuda / Equity | B29: =VLOOKUP("Total Liabilities*",'8.TIKR_BS'!$A:$K,COLUMN(B2),FALSE)/B26 -> #N/A | C29: =VLOOKUP("Total Liabilities*",'8.TIKR_BS'!$A:$K,COLUMN(C2),FALSE)/C26 -> #N/A | D29: =VLOOKUP("Total Liabilities*",'8.TIKR_BS'!$A:$K,COLUMN(D2),FALSE)/D26 -> #N/A | E29: =VLOOKUP("Total Liabilities*",'8.TIKR_BS'!$A:$K,COLUMN(E2),FALSE)/E26 -> #N/A | F29: =VLOOKUP("Total Liabilities*",'8.TIKR_BS'!$A:$K,COLUMN(F2),FALSE)/F26 -> #N/A | G29: =VLOOKUP("Total Liabilities*",'8.TIKR_BS'!$A:$K,COLUMN(G2),FALSE)/G26 -> #N/A | H29: =VLOOKUP("Total Liabilities*",'8.TIKR_BS'!$A:$K,COLUMN(H2),FALSE)/H26 -> #N/A | I29: =VLOOKUP("Total Liabilities*",'8.TIKR_BS'!$A:$K,COLUMN(I2),FALSE)/I26 -> #N/A | ... K29: =VLOOKUP("Total Liabilities*",'8.TIKR_BS'!$A:$K,COLUMN(K2),FALSE)/K26 -> #N/A
